Workbook
Name Alloys: Validation!$H$16:$H$24
Name alt_pg1_foot: '4b. Quote no pricing'!$B$52:$H$52
Name alt_pg2_foot: '4b. Quote no pricing'!$B$108:$H$108
Name alt_pg3_foot: '4b. Quote no pricing'!$B$163:$H$163
Name alt_pg4_foot: '4b. Quote no pricing'!$B$218:$H$218
Name alt_pg5_foot: '4b. Quote no pricing'!$B$273:$H$273
Name alt_pg6_foot: '4b. Quote no pricing'!$B$328:$H$328
Name Ano_Fin_Cost: 'Pricing Matrix'!#REF!
Name ap: Validation!$R$19
Name ap_or_pp: Validation!$R$2:$T$11
Name AP_PP_factor: 'Pricing Matrix'!$K$5
Name Applicator: Validation!$R$2:$R$11
Name Applicator_ano: Validation!$V$2:$V$5
Name attention: '1.Project Details'!$B$12
Name colour_code: Colour_Groups!$C$4:$D$94
Name COLOURS: Colour_Groups!$A$4:$D$94
Name customer: '1.Project Details'!$B$11
Name Delivery: 'Pricing Matrix'!$H$3
Name file_source: BOM_Import!$G$1
Name Fin_Cost_Price: 'Pricing Matrix'!$E$44
Name Fin_Sell_Price: 'Pricing Matrix'!$F$44
Name FinBulk_Cost_Price: 'Pricing Matrix'!$E$46
Name FinBulk_Sell_Price: 'Pricing Matrix'!$F$46
Name finish: '1.Project Details'!$B$32
Name finish_anodised: Validation!$AB$2:$AB$4
Name finish_applicator_value: '1.Project Details'!$B$26
Name finish_code_value: '1.Project Details'!$E$30
Name finish_common: BOM_Import!$L$11
Name Finish_Custom_Code: '1.Project Details'!$E$31
Name Finish_Custom_Name: '1.Project Details'!$B$31
Name finish_group_value: '1.Project Details'!$B$28
Name finish_groups: Validation!$R$2:$U$11
Name finish_list: BOM_Import!$K$11:$K$15
Name finish_mill: Validation!$W$2
Name finish_name_value: '1.Project Details'!$B$30
Name finish_pc_capral: Validation!$X$2:$X$7
Name finish_pc_other: Validation!$Z$2:$Z$5
Name finish_perimeter: Validation!$R$15:$R$16
Name finish_type: Validation!$S$15:$S$17
Name finish_type_value: '1.Project Details'!$B$24
Name FinNonBulk_Cost_Price: 'Pricing Matrix'!$E$47
Name FinNonBulk_Sell_Price: 'Pricing Matrix'!$F$47
Name GRP1_Long: Colour_Groups!$C$4:$C$31
Name GRP2_Long: Colour_Groups!$C$32:$C$43
Name Grp20_Long: Colour_Groups!$C$90:$C$91
Name Grp25_Long: Colour_Groups!$C$92:$C$93
Name Grp3_Long: Colour_Groups!$C$44:$C$56
Name Grp4_Long: Colour_Groups!$C$57:$C$63
Name Grp5_Long: Colour_Groups!$C$64:$C$89
Name GrpNA_Long: Colour_Groups!$C$3
Name GrpPOA_Long: Colour_Groups!$C$94
Name hide_twopage: '2b.Quote MF ALT'!$G$52:$J$52
Name hide_twopage: '4b. Quote no pricing'!$G$52:$H$52
Name hide_twopage: '2.Quote'!$G$52:$J$52
Name local_logo: '1.Project Details'!$B$23
Name local_logo_opt: Validation!$E$2:$E$4
Name Market_Segment: Validation!$A$2:$A$13
Name metalcost: 'Pricing Matrix'!$O$5
Name MF_ALT: '1.Project Details'!$E$24
Name No: Validation!$X$13

Sheet DATA
A1: Section | B1: Basic material | C1: RD | D1: Mass / M | E1: AP | F1: PP | G1: Mat_Grp | H1: PH | I1: PH Text | J1: External Material Group | K1: subsill | L1: Wall Thickness | M1: TB (No, PLS, PDB) | N1: SQ01 Report
A2: =N9 -> SUNDRY-1 | B2: =O9 -> Sundry description - 1 | C2: N | D2: =P9 -> 1 | E2: =Q9 -> 200 | F2: =R9 -> 200 | G2: =IF(LEFT(Table5[[#This Row],[Section]],3)="ETB","AE3000","") | K2: =_xlfn.IFNA(VLOOKUP(Table5[[#This Row],[Section]],SubSill_Tier,2,FALSE),0) -> 0 | L2: =IFERROR(IF(LEFT(G2,2)="AI",IF(_xlfn.NUMBERVALUE(IFERROR(LEFT(IF(ISERROR(FIND("X",UPPER(B2))),UPPER(B2),RIGHT(UPPER(B2),LEN(UPPER(B2))-FIND("~",SUBSTITUTE(UPPER(B2),"X","~",LEN(UPPER(B2))-LEN(SUBSTITUTE(UPPER(B2),"X","")))))),FIND(" ",IF(ISERROR(FIND("X",UPPER(B2))),UPPER(B2),RIGHT(UPPER(B2),LEN(UPPER(B2))-FIND("~",SUBSTITUTE(UPPER(B2),"X","~",LEN(UPPER(B2))-LEN(SUBSTITUTE(UPPER(B2),"X","")))))),1)-1),IF(ISERROR(FIND("X",UPPER(B2))),UPPER(B2),RIGHT(UPPER(B2),LEN(UPPER(B2))-FIND("~",SUBSTITUTE(UPPER(B2),"X","~",LEN(UPPER(B2))-LEN(SUBSTITUTE(UPPER(B2),"X",""))))))),".")>=5,"Wall",""),""),"") | M2: {=_xlfn.IFS(NOT(ISERROR(VLOOKUP(Table5[[#This Row],[Section]],TB_notTB,1,FALSE))),"No",LEFT(Table5[[#This Row],[Section]],3)="ETB","PLS",LEFT(Table5[[#This Row],[Section]],1)="7","PDB",NOT(ISBLANK(Table5[[#This Row],[Section]])),"No")} -> No | N2: SQ01 - Pricing - 1_MAT_INFO
A3: =N10 -> SUNDRY-2 | B3: =O10 -> Sundry description - 2 | C3: N | D3: =P10 -> 0 | E3: =Q10 -> 0 | F3: =R10 -> 0 | G3: =IF(LEFT(Table5[[#This Row],[Section]],3)="ETB","AE3000","") | K3: =_xlfn.IFNA(VLOOKUP(Table5[[#This Row],[Section]],SubSill_Tier,2,FALSE),0) -> 0 | L3: =IFERROR(IF(LEFT(G3,2)="AI",IF(_xlfn.NUMBERVALUE(IFERROR(LEFT(IF(ISERROR(FIND("X",UPPER(B3))),UPPER(B3),RIGHT(UPPER(B3),LEN(UPPER(B3))-FIND("~",SUBSTITUTE(UPPER(B3),"X","~",LEN(UPPER(B3))-LEN(SUBSTITUTE(UPPER(B3),"X","")))))),FIND(" ",IF(ISERROR(FIND("X",UPPER(B3))),UPPER(B3),RIGHT(UPPER(B3),LEN(UPPER(B3))-FIND("~",SUBSTITUTE(UPPER(B3),"X","~",LEN(UPPER(B3))-LEN(SUBSTITUTE(UPPER(B3),"X","")))))),1)-1),IF(ISERROR(FIND("X",UPPER(B3))),UPPER(B3),RIGHT(UPPER(B3),LEN(UPPER(B3))-FIND("~",SUBSTITUTE(UPPER(B3),"X","~",LEN(UPPER(B3))-LEN(SUBSTITUTE(UPPER(B3),"X",""))))))),".")>=5,"Wall",""),""),"") | M3: {=_xlfn.IFS(NOT(ISERROR(VLOOKUP(Table5[[#This Row],[Section]],TB_notTB,1,FALSE))),"No",LEFT(Table5[[#This Row],[Section]],3)="ETB","PLS",LEFT(Table5[[#This Row],[Section]],1)="7","PDB",NOT(ISBLANK(Table5[[#This Row],[Section]])),"No")} -> No | N3: Layout = Andrew
A4: =N11 -> SUNDRY-3 | B4: =O11 -> Sundry description - 3 | C4: N | D4: =P11 -> 0 | E4: =Q11 -> 0 | F4: =R11 -> 0 | G4: =IF(LEFT(Table5[[#This Row],[Section]],3)="ETB","AE3000","") | K4: =_xlfn.IFNA(VLOOKUP(Table5[[#This Row],[Section]],SubSill_Tier,2,FALSE),0) -> 0 | L4: =IFERROR(IF(LEFT(G4,2)="AI",IF(_xlfn.NUMBERVALUE(IFERROR(LEFT(IF(ISERROR(FIND("X",UPPER(B4))),UPPER(B4),RIGHT(UPPER(B4),LEN(UPPER(B4))-FIND("~",SUBSTITUTE(UPPER(B4),"X","~",LEN(UPPER(B4))-LEN(SUBSTITUTE(UPPER(B4),"X","")))))),FIND(" ",IF(ISERROR(FIND("X",UPPER(B4))),UPPER(B4),RIGHT(UPPER(B4),LEN(UPPER(B4))-FIND("~",SUBSTITUTE(UPPER(B4),"X","~",LEN(UPPER(B4))-LEN(SUBSTITUTE(UPPER(B4),"X","")))))),1)-1),IF(ISERROR(FIND("X",UPPER(B4))),UPPER(B4),RIGHT(UPPER(B4),LEN(UPPER(B4))-FIND("~",SUBSTITUTE(UPPER(B4),"X","~",LEN(UPPER(B4))-LEN(SUBSTITUTE(UPPER(B4),"X",""))))))),".")>=5,"Wall",""),""),"") | M4: {=_xlfn.IFS(NOT(ISERROR(VLOOKUP(Table5[[#This Row],[Section]],TB_notTB,1,FALSE))),"No",LEFT(Table5[[#This Row],[Section]],3)="ETB","PLS",LEFT(Table5[[#This Row],[Section]],1)="7","PDB",NOT(ISBLANK(Table5[[#This Row],[Section]])),"No")} -> No | N4: Export by ZDIE | O4: EDGE: Export by ZALC & ZALS for AE3500 to AE3999. Convert Material to number. Change last column to be MPG instead of Material Price Group
A5: =N12 -> SUNDRY-4 | B5: =O12 -> Sundry description - 4 | C5: N | D5: =P12 -> 0 | E5: =Q12 -> 0 | F5: =R12 -> 0 | G5: =IF(LEFT(Table5[[#This Row],[Section]],3)="ETB","AE3000","") | K5: =_xlfn.IFNA(VLOOKUP(Table5[[#This Row],[Section]],SubSill_Tier,2,FALSE),0) -> 0 | L5: =IFERROR(IF(LEFT(G5,2)="AI",IF(_xlfn.NUMBERVALUE(IFERROR(LEFT(IF(ISERROR(FIND("X",UPPER(B5))),UPPER(B5),RIGHT(UPPER(B5),LEN(UPPER(B5))-FIND("~",SUBSTITUTE(UPPER(B5),"X","~",LEN(UPPER(B5))-LEN(SUBSTITUTE(UPPER(B5),"X","")))))),FIND(" ",IF(ISERROR(FIND("X",UPPER(B5))),UPPER(B5),RIGHT(UPPER(B5),LEN(UPPER(B5))-FIND("~",SUBSTITUTE(UPPER(B5),"X","~",LEN(UPPER(B5))-LEN(SUBSTITUTE(UPPER(B5),"X","")))))),1)-1),IF(ISERROR(FIND("X",UPPER(B5))),UPPER(B5),RIGHT(UPPER(B5),LEN(UPPER(B5))-FIND("~",SUBSTITUTE(UPPER(B5),"X","~",LEN(UPPER(B5))-LEN(SUBSTITUTE(UPPER(B5),"X",""))))))),".")>=5,"Wall",""),""),"") | M5: {=_xlfn.IFS(NOT(ISERROR(VLOOKUP(Table5[[#This Row],[Section]],TB_notTB,1,FALSE))),"No",LEFT(Table5[[#This Row],[Section]],3)="ETB","PLS",LEFT(Table5[[#This Row],[Section]],1)="7","PDB",NOT(ISBLANK(Table5[[#This Row],[Section]])),"No")} -> No | N5: Export to AE*, AG*, AI*, AR* (each separately)
A6: =N13 -> SUNDRY-5 | B6: =O13 -> Sundry description - 5 | C6: N | D6: =P13 -> 0 | E6: =Q13 -> 0 | F6: =R13 -> 0 | G6: =IF(LEFT(Table5[[#This Row],[Section]],3)="ETB","AE3000","") | K6: =_xlfn.IFNA(VLOOKUP(Table5[[#This Row],[Section]],SubSill_Tier,2,FALSE),0) -> 0 | L6: =IFERROR(IF(LEFT(G6,2)="AI",IF(_xlfn.NUMBERVALUE(IFERROR(LEFT(IF(ISERROR(FIND("X",UPPER(B6))),UPPER(B6),RIGHT(UPPER(B6),LEN(UPPER(B6))-FIND("~",SUBSTITUTE(UPPER(B6),"X","~",LEN(UPPER(B6))-LEN(SUBSTITUTE(UPPER(B6),"X","")))))),FIND(" ",IF(ISERROR(FIND("X",UPPER(B6))),UPPER(B6),RIGHT(UPPER(B6),LEN(UPPER(B6))-FIND("~",SUBSTITUTE(UPPER(B6),"X","~",LEN(UPPER(B6))-LEN(SUBSTITUTE(UPPER(B6),"X","")))))),1)-1),IF(ISERROR(FIND("X",UPPER(B6))),UPPER(B6),RIGHT(UPPER(B6),LEN(UPPER(B6))-FIND("~",SUBSTITUTE(UPPER(B6),"X","~",LEN(UPPER(B6))-LEN(SUBSTITUTE(UPPER(B6),"X",""))))))),".")>=5,"Wall",""),""),"") | M6: {=_xlfn.IFS(NOT(ISERROR(VLOOKUP(Table5[[#This Row],[Section]],TB_notTB,1,FALSE))),"No",LEFT(Table5[[#This Row],[Section]],3)="ETB","PLS",LEFT(Table5[[#This Row],[Section]],1)="7","PDB",NOT(ISBLANK(Table5[[#This Row],[Section]])),"No")} -> No | N6: Select View button and Excel in place. Copy & Paste into a new book, sort by section then paste into here
A7: =N14 -> SUNDRY-6 | B7: =O14 -> Sundry description - 6 | C7: N | D7: =P14 -> 0 | E7: =Q14 -> 0 | F7: =R14 -> 0 | G7: =IF(LEFT(Table5[[#This Row],[Section]],3)="ETB","AE3000","") | K7: =_xlfn.IFNA(VLOOKUP(Table5[[#This Row],[Section]],SubSill_Tier,2,FALSE),0) -> 0 | L7: =IFERROR(IF(LEFT(G7,2)="AI",IF(_xlfn.NUMBERVALUE(IFERROR(LEFT(IF(ISERROR(FIND("X",UPPER(B7))),UPPER(B7),RIGHT(UPPER(B7),LEN(UPPER(B7))-FIND("~",SUBSTITUTE(UPPER(B7),"X","~",LEN(UPPER(B7))-LEN(SUBSTITUTE(UPPER(B7),"X","")))))),FIND(" ",IF(ISERROR(FIND("X",UPPER(B7))),UPPER(B7),RIGHT(UPPER(B7),LEN(UPPER(B7))-FIND("~",SUBSTITUTE(UPPER(B7),"X","~",LEN(UPPER(B7))-LEN(SUBSTITUTE(UPPER(B7),"X","")))))),1)-1),IF(ISERROR(FIND("X",UPPER(B7))),UPPER(B7),RIGHT(UPPER(B7),LEN(UPPER(B7))-FIND("~",SUBSTITUTE(UPPER(B7),"X","~",LEN(UPPER(B7))-LEN(SUBSTITUTE(UPPER(B7),"X",""))))))),".")>=5,"Wall",""),""),"") | M7: {=_xlfn.IFS(NOT(ISERROR(VLOOKUP(Table5[[#This Row],[Section]],TB_notTB,1,FALSE))),"No",LEFT(Table5[[#This Row],[Section]],3)="ETB","PLS",LEFT(Table5[[#This Row],[Section]],1)="7","PDB",NOT(ISBLANK(Table5[[#This Row],[Section]])),"No")} -> No | N7: Ensure formula in Mat_Grp column extends all way down to last section
A8: =N15 -> SUNDRY-7 | B8: =O15 -> Sundry description - 7 | C8: N | D8: =P15 -> 0 | E8: =Q15 -> 0 | F8: =R15 -> 0 | G8: =IF(LEFT(Table5[[#This Row],[Section]],3)="ETB","AE3000","") | K8: =_xlfn.IFNA(VLOOKUP(Table5[[#This Row],[Section]],SubSill_Tier,2,FALSE),0) -> 0 | L8: =IFERROR(IF(LEFT(G8,2)="AI",IF(_xlfn.NUMBERVALUE(IFERROR(LEFT(IF(ISERROR(FIND("X",UPPER(B8))),UPPER(B8),RIGHT(UPPER(B8),LEN(UPPER(B8))-FIND("~",SUBSTITUTE(UPPER(B8),"X","~",LEN(UPPER(B8))-LEN(SUBSTITUTE(UPPER(B8),"X","")))))),FIND(" ",IF(ISERROR(FIND("X",UPPER(B8))),UPPER(B8),RIGHT(UPPER(B8),LEN(UPPER(B8))-FIND("~",SUBSTITUTE(UPPER(B8),"X","~",LEN(UPPER(B8))-LEN(SUBSTITUTE(UPPER(B8),"X","")))))),1)-1),IF(ISERROR(FIND("X",UPPER(B8))),UPPER(B8),RIGHT(UPPER(B8),LEN(UPPER(B8))-FIND("~",SUBSTITUTE(UPPER(B8),"X","~",LEN(UPPER(B8))-LEN(SUBSTITUTE(UPPER(B8),"X",""))))))),".")>=5,"Wall",""),""),"") | M8: {=_xlfn.IFS(NOT(ISERROR(VLOOKUP(Table5[[#This Row],[Section]],TB_notTB,1,FALSE))),"No",LEFT(Table5[[#This Row],[Section]],3)="ETB","PLS",LEFT(Table5[[#This Row],[Section]],1)="7","PDB",NOT(ISBLANK(Table5[[#This Row],[Section]])),"No")} -> No | N8: SUNDRY ITEMS | O8: SUNDRY DESCRIPTIONS | P8: Mass / M | Q8: AP | R8: PP
A9: =N16 -> SUNDRY-8 | B9: =O16 -> Sundry description - 8 | C9: N | D9: =P16 -> 0 | E9: =Q16 -> 0 | F9: =R16 -> 0 | G9: =IF(LEFT(Table5[[#This Row],[Section]],3)="ETB","AE3000","") | K9: =_xlfn.IFNA(VLOOKUP(Table5[[#This Row],[Section]],SubSill_Tier,2,FALSE),0) -> 0 | L9: =IFERROR(IF(LEFT(G9,2)="AI",IF(_xlfn.NUMBERVALUE(IFERROR(LEFT(IF(ISERROR(FIND("X",UPPER(B9))),UPPER(B9),RIGHT(UPPER(B9),LEN(UPPER(B9))-FIND("~",SUBSTITUTE(UPPER(B9),"X","~",LEN(UPPER(B9))-LEN(SUBSTITUTE(UPPER(B9),"X","")))))),FIND(" ",IF(ISERROR(FIND("X",UPPER(B9))),UPPER(B9),RIGHT(UPPER(B9),LEN(UPPER(B9))-FIND("~",SUBSTITUTE(UPPER(B9),"X","~",LEN(UPPER(B9))-LEN(SUBSTITUTE(UPPER(B9),"X","")))))),1)-1),IF(ISERROR(FIND("X",UPPER(B9))),UPPER(B9),RIGHT(UPPER(B9),LEN(UPPER(B9))-FIND("~",SUBSTITUTE(UPPER(B9),"X","~",LEN(UPPER(B9))-LEN(SUBSTITUTE(UPPER(B9),"X",""))))))),".")>=5,"Wall",""),""),"") | M9: {=_xlfn.IFS(NOT(ISERROR(VLOOKUP(Table5[[#This Row],[Section]],TB_notTB,1,FALSE))),"No",LEFT(Table5[[#This Row],[Section]],3)="ETB","PLS",LEFT(Table5[[#This Row],[Section]],1)="7","PDB",NOT(ISBLANK(Table5[[#This Row],[Section]])),"No")} -> No | N9: SUNDRY-1 | O9: Sundry description - 1 | P9: 1 | Q9: 200 | R9: 200
A10: =N17 -> SUNDRY-9 | B10: =O17 -> Sundry description - 9 | C10: N | D10: =P17 -> 0 | E10: =Q17 -> 0 | F10: =R17 -> 0 | G10: =IF(LEFT(Table5[[#This Row],[Section]],3)="ETB","AE3000","") | K10: =_xlfn.IFNA(VLOOKUP(Table5[[#This Row],[Section]],SubSill_Tier,2,FALSE),0) -> 0 | L10: =IFERROR(IF(LEFT(G10,2)="AI",IF(_xlfn.NUMBERVALUE(IFERROR(LEFT(IF(ISERROR(FIND("X",UPPER(B10))),UPPER(B10),RIGHT(UPPER(B10),LEN(UPPER(B10))-FIND("~",SUBSTITUTE(UPPER(B10),"X","~",LEN(UPPER(B10))-LEN(SUBSTITUTE(UPPER(B10),"X","")))))),FIND(" ",IF(ISERROR(FIND("X",UPPER(B10))),UPPER(B10),RIGHT(UPPER(B10),LEN(UPPER(B10))-FIND("~",SUBSTITUTE(UPPER(B10),"X","~",LEN(UPPER(B10))-LEN(SUBSTITUTE(UPPER(B10),"X","")))))),1)-1),IF(ISERROR(FIND("X",UPPER(B10))),UPPER(B10),RIGHT(UPPER(B10),LEN(UPPER(B10))-FIND("~",SUBSTITUTE(UPPER(B10),"X","~",LEN(UPPER(B10))-LEN(SUBSTITUTE(UPPER(B10),"X",""))))))),".")>=5,"Wall",""),""),"") | M10: {=_xlfn.IFS(NOT(ISERROR(VLOOKUP(Table5[[#This Row],[Section]],TB_notTB,1,FALSE))),"No",LEFT(Table5[[#This Row],[Section]],3)="ETB","PLS",LEFT(Table5[[#This Row],[Section]],1)="7","PDB",NOT(ISBLANK(Table5[[#This Row],[Section]])),"No")} -> No | N10: SUNDRY-2 | O10: Sundry description - 2
A11: =N18 -> SUNDRY-10 | B11: =O18 -> Sundry description - 10 | C11: N | D11: =P18 -> 0 | E11: =Q18 -> 0 | F11: =R18 -> 0 | G11: =IF(LEFT(Table5[[#This Row],[Section]],3)="ETB","AE3000","") | K11: =_xlfn.IFNA(VLOOKUP(Table5[[#This Row],[Section]],SubSill_Tier,2,FALSE),0) -> 0 | L11: =IFERROR(IF(LEFT(G11,2)="AI",IF(_xlfn.NUMBERVALUE(IFERROR(LEFT(IF(ISERROR(FIND("X",UPPER(B11))),UPPER(B11),RIGHT(UPPER(B11),LEN(UPPER(B11))-FIND("~",SUBSTITUTE(UPPER(B11),"X","~",LEN(UPPER(B11))-LEN(SUBSTITUTE(UPPER(B11),"X","")))))),FIND(" ",IF(ISERROR(FIND("X",UPPER(B11))),UPPER(B11),RIGHT(UPPER(B11),LEN(UPPER(B11))-FIND("~",SUBSTITUTE(UPPER(B11),"X","~",LEN(UPPER(B11))-LEN(SUBSTITUTE(UPPER(B11),"X","")))))),1)-1),IF(ISERROR(FIND("X",UPPER(B11))),UPPER(B11),RIGHT(UPPER(B11),LEN(UPPER(B11))-FIND("~",SUBSTITUTE(UPPER(B11),"X","~",LEN(UPPER(B11))-LEN(SUBSTITUTE(UPPER(B11),"X",""))))))),".")>=5,"Wall",""),""),"") | M11: {=_xlfn.IFS(NOT(ISERROR(VLOOKUP(Table5[[#This Row],[Section]],TB_notTB,1,FALSE))),"No",LEFT(Table5[[#This Row],[Section]],3)="ETB","PLS",LEFT(Table5[[#This Row],[Section]],1)="7","PDB",NOT(ISBLANK(Table5[[#This Row],[Section]])),"No")} -> No | N11: SUNDRY-3 | O11: Sundry description - 3
A12: =N19 -> SUNDRY-11 | B12: =O19 -> Sundry description - 11 | C12: N | D12: =P19 -> 0 | E12: =Q19 -> 0 | F12: =R19 -> 0 | G12: =IF(LEFT(Table5[[#This Row],[Section]],3)="ETB","AE3000","") | K12: =_xlfn.IFNA(VLOOKUP(Table5[[#This Row],[Section]],SubSill_Tier,2,FALSE),0) -> 0 | L12: =IFERROR(IF(LEFT(G12,2)="AI",IF(_xlfn.NUMBERVALUE(IFERROR(LEFT(IF(ISERROR(FIND("X",UPPER(B12))),UPPER(B12),RIGHT(UPPER(B12),LEN(UPPER(B12))-FIND("~",SUBSTITUTE(UPPER(B12),"X","~",LEN(UPPER(B12))-LEN(SUBSTITUTE(UPPER(B12),"X","")))))),FIND(" ",IF(ISERROR(FIND("X",UPPER(B12))),UPPER(B12),RIGHT(UPPER(B12),LEN(UPPER(B12))-FIND("~",SUBSTITUTE(UPPER(B12),"X","~",LEN(UPPER(B12))-LEN(SUBSTITUTE(UPPER(B12),"X","")))))),1)-1),IF(ISERROR(FIND("X",UPPER(B12))),UPPER(B12),RIGHT(UPPER(B12),LEN(UPPER(B12))-FIND("~",SUBSTITUTE(UPPER(B12),"X","~",LEN(UPPER(B12))-LEN(SUBSTITUTE(UPPER(B12),"X",""))))))),".")>=5,"Wall",""),""),"") | M12: {=_xlfn.IFS(NOT(ISERROR(VLOOKUP(Table5[[#This Row],[Section]],TB_notTB,1,FALSE))),"No",LEFT(Table5[[#This Row],[Section]],3)="ETB","PLS",LEFT(Table5[[#This Row],[Section]],1)="7","PDB",NOT(ISBLANK(Table5[[#This Row],[Section]])),"No")} -> No | N12: SUNDRY-4 | O12: Sundry description - 4
A13: =N20 -> SUNDRY-12 | B13: =O20 -> Sundry description - 12 | C13: N | D13: =P20 -> 0 | E13: =Q20 -> 0 | F13: =R20 -> 0 | G13: =IF(LEFT(Table5[[#This Row],[Section]],3)="ETB","AE3000","") | K13: =_xlfn.IFNA(VLOOKUP(Table5[[#This Row],[Section]],SubSill_Tier,2,FALSE),0) -> 0 | L13: =IFERROR(IF(LEFT(G13,2)="AI",IF(_xlfn.NUMBERVALUE(IFERROR(LEFT(IF(ISERROR(FIND("X",UPPER(B13))),UPPER(B13),RIGHT(UPPER(B13),LEN(UPPER(B13))-FIND("~",SUBSTITUTE(UPPER(B13),"X","~",LEN(UPPER(B13))-LEN(SUBSTITUTE(UPPER(B13),"X","")))))),FIND(" ",IF(ISERROR(FIND("X",UPPER(B13))),UPPER(B13),RIGHT(UPPER(B13),LEN(UPPER(B13))-FIND("~",SUBSTITUTE(UPPER(B13),"X","~",LEN(UPPER(B13))-LEN(SUBSTITUTE(UPPER(B13),"X","")))))),1)-1),IF(ISERROR(FIND("X",UPPER(B13))),UPPER(B13),RIGHT(UPPER(B13),LEN(UPPER(B13))-FIND("~",SUBSTITUTE(UPPER(B13),"X","~",LEN(UPPER(B13))-LEN(SUBSTITUTE(UPPER(B13),"X",""))))))),".")>=5,"Wall",""),""),"") | M13: {=_xlfn.IFS(NOT(ISERROR(VLOOKUP(Table5[[#This Row],[Section]],TB_notTB,1,FALSE))),"No",LEFT(Table5[[#This Row],[Section]],3)="ETB","PLS",LEFT(Table5[[#This Row],[Section]],1)="7","PDB",NOT(ISBLANK(Table5[[#This Row],[Section]])),"No")} -> No | N13: SUNDRY-5 | O13: Sundry description - 5
A14: =N21 -> SUNDRY-13 | B14: =O21 -> Sundry description - 13 | C14: N | D14: =P21 -> 0 | E14: =Q21 -> 0 | F14: =R21 -> 0 | G14: =IF(LEFT(Table5[[#This Row],[Section]],3)="ETB","AE3000","") | K14: =_xlfn.IFNA(VLOOKUP(Table5[[#This Row],[Section]],SubSill_Tier,2,FALSE),0) -> 0 | L14: =IFERROR(IF(LEFT(G14,2)="AI",IF(_xlfn.NUMBERVALUE(IFERROR(LEFT(IF(ISERROR(FIND("X",UPPER(B14))),UPPER(B14),RIGHT(UPPER(B14),LEN(UPPER(B14))-FIND("~",SUBSTITUTE(UPPER(B14),"X","~",LEN(UPPER(B14))-LEN(SUBSTITUTE(UPPER(B14),"X","")))))),FIND(" ",IF(ISERROR(FIND("X",UPPER(B14))),UPPER(B14),RIGHT(UPPER(B14),LEN(UPPER(B14))-FIND("~",SUBSTITUTE(UPPER(B14),"X","~",LEN(UPPER(B14))-LEN(SUBSTITUTE(UPPER(B14),"X","")))))),1)-1),IF(ISERROR(FIND("X",UPPER(B14))),UPPER(B14),RIGHT(UPPER(B14),LEN(UPPER(B14))-FIND("~",SUBSTITUTE(UPPER(B14),"X","~",LEN(UPPER(B14))-LEN(SUBSTITUTE(UPPER(B14),"X",""))))))),".")>=5,"Wall",""),""),"") | M14: {=_xlfn.IFS(NOT(ISERROR(VLOOKUP(Table5[[#This Row],[Section]],TB_notTB,1,FALSE))),"No",LEFT(Table5[[#This Row],[Section]],3)="ETB","PLS",LEFT(Table5[[#This Row],[Section]],1)="7","PDB",NOT(ISBLANK(Table5[[#This Row],[Section]])),"No")} -> No | N14: SUNDRY-6 | O14: Sundry description - 6
A15: =N22 -> SUNDRY-14 | B15: =O22 -> Sundry description - 14 | C15: N | D15: =P22 -> 0 | E15: =Q22 -> 0 | F15: =R22 -> 0 | G15: =IF(LEFT(Table5[[#This Row],[Section]],3)="ETB","AE3000","") | K15: =_xlfn.IFNA(VLOOKUP(Table5[[#This Row],[Section]],SubSill_Tier,2,FALSE),0) -> 0 | L15: =IFERROR(IF(LEFT(G15,2)="AI",IF(_xlfn.NUMBERVALUE(IFERROR(LEFT(IF(ISERROR(FIND("X",UPPER(B15))),UPPER(B15),RIGHT(UPPER(B15),LEN(UPPER(B15))-FIND("~",SUBSTITUTE(UPPER(B15),"X","~",LEN(UPPER(B15))-LEN(SUBSTITUTE(UPPER(B15),"X","")))))),FIND(" ",IF(ISERROR(FIND("X",UPPER(B15))),UPPER(B15),RIGHT(UPPER(B15),LEN(UPPER(B15))-FIND("~",SUBSTITUTE(UPPER(B15),"X","~",LEN(UPPER(B15))-LEN(SUBSTITUTE(UPPER(B15),"X","")))))),1)-1),IF(ISERROR(FIND("X",UPPER(B15))),UPPER(B15),RIGHT(UPPER(B15),LEN(UPPER(B15))-FIND("~",SUBSTITUTE(UPPER(B15),"X","~",LEN(UPPER(B15))-LEN(SUBSTITUTE(UPPER(B15),"X",""))))))),".")>=5,"Wall",""),""),"") | M15: {=_xlfn.IFS(NOT(ISERROR(VLOOKUP(Table5[[#This Row],[Section]],TB_notTB,1,FALSE))),"No",LEFT(Table5[[#This Row],[Section]],3)="ETB","PLS",LEFT(Table5[[#This Row],[Section]],1)="7","PDB",NOT(ISBLANK(Table5[[#This Row],[Section]])),"No")} -> No | N15: SUNDRY-7 | O15: Sundry description - 7
A16: =N23 -> SUNDRY-15 | B16: =O23 -> Sundry description - 15 | C16: N | D16: =P23 -> 0 | E16: =Q23 -> 0 | F16: =R23 -> 0 | G16: =IF(LEFT(Table5[[#This Row],[Section]],3)="ETB","AE3000","") | K16: =_xlfn.IFNA(VLOOKUP(Table5[[#This Row],[Section]],SubSill_Tier,2,FALSE),0) -> 0 | L16: =IFERROR(IF(LEFT(G16,2)="AI",IF(_xlfn.NUMBERVALUE(IFERROR(LEFT(IF(ISERROR(FIND("X",UPPER(B16))),UPPER(B16),RIGHT(UPPER(B16),LEN(UPPER(B16))-FIND("~",SUBSTITUTE(UPPER(B16),"X","~",LEN(UPPER(B16))-LEN(SUBSTITUTE(UPPER(B16),"X","")))))),FIND(" ",IF(ISERROR(FIND("X",UPPER(B16))),UPPER(B16),RIGHT(UPPER(B16),LEN(UPPER(B16))-FIND("~",SUBSTITUTE(UPPER(B16),"X","~",LEN(UPPER(B16))-LEN(SUBSTITUTE(UPPER(B16),"X","")))))),1)-1),IF(ISERROR(FIND("X",UPPER(B16))),UPPER(B16),RIGHT(UPPER(B16),LEN(UPPER(B16))-FIND("~",SUBSTITUTE(UPPER(B16),"X","~",LEN(UPPER(B16))-LEN(SUBSTITUTE(UPPER(B16),"X",""))))))),".")>=5,"Wall",""),""),"") | M16: {=_xlfn.IFS(NOT(ISERROR(VLOOKUP(Table5[[#This Row],[Section]],TB_notTB,1,FALSE))),"No",LEFT(Table5[[#This Row],[Section]],3)="ETB","PLS",LEFT(Table5[[#This Row],[Section]],1)="7","PDB",NOT(ISBLANK(Table5[[#This Row],[Section]])),"No")} -> No | N16: SUNDRY-8 | O16: Sundry description - 8
A17: =N24 -> SUNDRY-16 | B17: =O24 -> Sundry description - 16 | C17: N | D17: =P24 -> 0 | E17: =Q24 -> 0 | F17: =R24 -> 0 | G17: =IF(LEFT(Table5[[#This Row],[Section]],3)="ETB","AE3000","") | K17: =_xlfn.IFNA(VLOOKUP(Table5[[#This Row],[Section]],SubSill_Tier,2,FALSE),0) -> 0 | L17: =IFERROR(IF(LEFT(G17,2)="AI",IF(_xlfn.NUMBERVALUE(IFERROR(LEFT(IF(ISERROR(FIND("X",UPPER(B17))),UPPER(B17),RIGHT(UPPER(B17),LEN(UPPER(B17))-FIND("~",SUBSTITUTE(UPPER(B17),"X","~",LEN(UPPER(B17))-LEN(SUBSTITUTE(UPPER(B17),"X","")))))),FIND(" ",IF(ISERROR(FIND("X",UPPER(B17))),UPPER(B17),RIGHT(UPPER(B17),LEN(UPPER(B17))-FIND("~",SUBSTITUTE(UPPER(B17),"X","~",LEN(UPPER(B17))-LEN(SUBSTITUTE(UPPER(B17),"X","")))))),1)-1),IF(ISERROR(FIND("X",UPPER(B17))),UPPER(B17),RIGHT(UPPER(B17),LEN(UPPER(B17))-FIND("~",SUBSTITUTE(UPPER(B17),"X","~",LEN(UPPER(B17))-LEN(SUBSTITUTE(UPPER(B17),"X",""))))))),".")>=5,"Wall",""),""),"") | M17: {=_xlfn.IFS(NOT(ISERROR(VLOOKUP(Table5[[#This Row],[Section]],TB_notTB,1,FALSE))),"No",LEFT(Table5[[#This Row],[Section]],3)="ETB","PLS",LEFT(Table5[[#This Row],[Section]],1)="7","PDB",NOT(ISBLANK(Table5[[#This Row],[Section]])),"No")} -> No | N17: SUNDRY-9 | O17: Sundry description - 9
A18: =N25 -> SUNDRY-17 | B18: =O25 -> Sundry description - 17 | C18: N | D18: =P25 -> 0 | E18: =Q25 -> 0 | F18: =R25 -> 0 | G18: =IF(LEFT(Table5[[#This Row],[Section]],3)="ETB","AE3000","") | K18: =_xlfn.IFNA(VLOOKUP(Table5[[#This Row],[Section]],SubSill_Tier,2,FALSE),0) -> 0 | L18: =IFERROR(IF(LEFT(G18,2)="AI",IF(_xlfn.NUMBERVALUE(IFERROR(LEFT(IF(ISERROR(FIND("X",UPPER(B18))),UPPER(B18),RIGHT(UPPER(B18),LEN(UPPER(B18))-FIND("~",SUBSTITUTE(UPPER(B18),"X","~",LEN(UPPER(B18))-LEN(SUBSTITUTE(UPPER(B18),"X","")))))),FIND(" ",IF(ISERROR(FIND("X",UPPER(B18))),UPPER(B18),RIGHT(UPPER(B18),LEN(UPPER(B18))-FIND("~",SUBSTITUTE(UPPER(B18),"X","~",LEN(UPPER(B18))-LEN(SUBSTITUTE(UPPER(B18),"X","")))))),1)-1),IF(ISERROR(FIND("X",UPPER(B18))),UPPER(B18),RIGHT(UPPER(B18),LEN(UPPER(B18))-FIND("~",SUBSTITUTE(UPPER(B18),"X","~",LEN(UPPER(B18))-LEN(SUBSTITUTE(UPPER(B18),"X",""))))))),".")>=5,"Wall",""),""),"") | M18: {=_xlfn.IFS(NOT(ISERROR(VLOOKUP(Table5[[#This Row],[Section]],TB_notTB,1,FALSE))),"No",LEFT(Table5[[#This Row],[Section]],3)="ETB","PLS",LEFT(Table5[[#This Row],[Section]],1)="7","PDB",NOT(ISBLANK(Table5[[#This Row],[Section]])),"No")} -> No | N18: SUNDRY-10 | O18: Sundry description - 10
A19: =N26 -> SUNDRY-18 | B19: =O26 -> Sundry description - 18 | C19: N | D19: =P26 -> 0 | E19: =Q26 -> 0 | F19: =R26 -> 0 | G19: =IF(LEFT(Table5[[#This Row],[Section]],3)="ETB","AE3000","") | K19: =_xlfn.IFNA(VLOOKUP(Table5[[#This Row],[Section]],SubSill_Tier,2,FALSE),0) -> 0 | L19: =IFERROR(IF(LEFT(G19,2)="AI",IF(_xlfn.NUMBERVALUE(IFERROR(LEFT(IF(ISERROR(FIND("X",UPPER(B19))),UPPER(B19),RIGHT(UPPER(B19),LEN(UPPER(B19))-FIND("~",SUBSTITUTE(UPPER(B19),"X","~",LEN(UPPER(B19))-LEN(SUBSTITUTE(UPPER(B19),"X","")))))),FIND(" ",IF(ISERROR(FIND("X",UPPER(B19))),UPPER(B19),RIGHT(UPPER(B19),LEN(UPPER(B19))-FIND("~",SUBSTITUTE(UPPER(B19),"X","~",LEN(UPPER(B19))-LEN(SUBSTITUTE(UPPER(B19),"X","")))))),1)-1),IF(ISERROR(FIND("X",UPPER(B19))),UPPER(B19),RIGHT(UPPER(B19),LEN(UPPER(B19))-FIND("~",SUBSTITUTE(UPPER(B19),"X","~",LEN(UPPER(B19))-LEN(SUBSTITUTE(UPPER(B19),"X",""))))))),".")>=5,"Wall",""),""),"") | M19: {=_xlfn.IFS(NOT(ISERROR(VLOOKUP(Table5[[#This Row],[Section]],TB_notTB,1,FALSE))),"No",LEFT(Table5[[#This Row],[Section]],3)="ETB","PLS",LEFT(Table5[[#This Row],[Section]],1)="7","PDB",NOT(ISBLANK(Table5[[#This Row],[Section]])),"No")} -> No | N19: SUNDRY-11 | O19: Sundry description - 11
A20: =N27 -> SUNDRY-19 | B20: =O27 -> Sundry description - 19 | C20: N | D20: =P27 -> 0 | E20: =Q27 -> 0 | F20: =R27 -> 0 | G20: =IF(LEFT(Table5[[#This Row],[Section]],3)="ETB","AE3000","") | K20: =_xlfn.IFNA(VLOOKUP(Table5[[#This Row],[Section]],SubSill_Tier,2,FALSE),0) -> 0 | L20: =IFERROR(IF(LEFT(G20,2)="AI",IF(_xlfn.NUMBERVALUE(IFERROR(LEFT(IF(ISERROR(FIND("X",UPPER(B20))),UPPER(B20),RIGHT(UPPER(B20),LEN(UPPER(B20))-FIND("~",SUBSTITUTE(UPPER(B20),"X","~",LEN(UPPER(B20))-LEN(SUBSTITUTE(UPPER(B20),"X","")))))),FIND(" ",IF(ISERROR(FIND("X",UPPER(B20))),UPPER(B20),RIGHT(UPPER(B20),LEN(UPPER(B20))-FIND("~",SUBSTITUTE(UPPER(B20),"X","~",LEN(UPPER(B20))-LEN(SUBSTITUTE(UPPER(B20),"X","")))))),1)-1),IF(ISERROR(FIND("X",UPPER(B20))),UPPER(B20),RIGHT(UPPER(B20),LEN(UPPER(B20))-FIND("~",SUBSTITUTE(UPPER(B20),"X","~",LEN(UPPER(B20))-LEN(SUBSTITUTE(UPPER(B20),"X",""))))))),".")>=5,"Wall",""),""),"") | M20: {=_xlfn.IFS(NOT(ISERROR(VLOOKUP(Table5[[#This Row],[Section]],TB_notTB,1,FALSE))),"No",LEFT(Table5[[#This Row],[Section]],3)="ETB","PLS",LEFT(Table5[[#This Row],[Section]],1)="7","PDB",NOT(ISBLANK(Table5[[#This Row],[Section]])),"No")} -> No | N20: SUNDRY-12 | O20: Sundry description - 12
A21: =N28 -> SUNDRY-20 | B21: =O28 -> Sundry description - 20 | C21: N | D21: =P28 -> 0 | E21: =Q28 -> 0 | F21: =R28 -> 0 | G21: =IF(LEFT(Table5[[#This Row],[Section]],3)="ETB","AE3000","") | K21: =_xlfn.IFNA(VLOOKUP(Table5[[#This Row],[Section]],SubSill_Tier,2,FALSE),0) -> 0 | L21: =IFERROR(IF(LEFT(G21,2)="AI",IF(_xlfn.NUMBERVALUE(IFERROR(LEFT(IF(ISERROR(FIND("X",UPPER(B21))),UPPER(B21),RIGHT(UPPER(B21),LEN(UPPER(B21))-FIND("~",SUBSTITUTE(UPPER(B21),"X","~",LEN(UPPER(B21))-LEN(SUBSTITUTE(UPPER(B21),"X","")))))),FIND(" ",IF(ISERROR(FIND("X",UPPER(B21))),UPPER(B21),RIGHT(UPPER(B21),LEN(UPPER(B21))-FIND("~",SUBSTITUTE(UPPER(B21),"X","~",LEN(UPPER(B21))-LEN(SUBSTITUTE(UPPER(B21),"X","")))))),1)-1),IF(ISERROR(FIND("X",UPPER(B21))),UPPER(B21),RIGHT(UPPER(B21),LEN(UPPER(B21))-FIND("~",SUBSTITUTE(UPPER(B21),"X","~",LEN(UPPER(B21))-LEN(SUBSTITUTE(UPPER(B21),"X",""))))))),".")>=5,"Wall",""),""),"") | M21: {=_xlfn.IFS(NOT(ISERROR(VLOOKUP(Table5[[#This Row],[Section]],TB_notTB,1,FALSE))),"No",LEFT(Table5[[#This Row],[Section]],3)="ETB","PLS",LEFT(Table5[[#This Row],[Section]],1)="7","PDB",NOT(ISBLANK(Table5[[#This Row],[Section]])),"No")} -> No | N21: SUNDRY-13 | O21: Sundry description - 13
A22: =N29 -> SUNDRY-21 | B22: =O29 -> Sundry description - 21 | C22: N | D22: 0 | E22: 0 | F22: 0 | G22: =IF(LEFT(Table5[[#This Row],[Section]],3)="ETB","AE3000","") | K22: =_xlfn.IFNA(VLOOKUP(Table5[[#This Row],[Section]],SubSill_Tier,2,FALSE),0) -> 0 | L22: =IFERROR(IF(LEFT(G22,2)="AI",IF(_xlfn.NUMBERVALUE(IFERROR(LEFT(IF(ISERROR(FIND("X",UPPER(B22))),UPPER(B22),RIGHT(UPPER(B22),LEN(UPPER(B22))-FIND("~",SUBSTITUTE(UPPER(B22),"X","~",LEN(UPPER(B22))-LEN(SUBSTITUTE(UPPER(B22),"X","")))))),FIND(" ",IF(ISERROR(FIND("X",UPPER(B22))),UPPER(B22),RIGHT(UPPER(B22),LEN(UPPER(B22))-FIND("~",SUBSTITUTE(UPPER(B22),"X","~",LEN(UPPER(B22))-LEN(SUBSTITUTE(UPPER(B22),"X","")))))),1)-1),IF(ISERROR(FIND("X",UPPER(B22))),UPPER(B22),RIGHT(UPPER(B22),LEN(UPPER(B22))-FIND("~",SUBSTITUTE(UPPER(B22),"X","~",LEN(UPPER(B22))-LEN(SUBSTITUTE(UPPER(B22),"X",""))))))),".")>=5,"Wall",""),""),"") | M22: {=_xlfn.IFS(NOT(ISERROR(VLOOKUP(Table5[[#This Row],[Section]],TB_notTB,1,FALSE))),"No",LEFT(Table5[[#This Row],[Section]],3)="ETB","PLS",LEFT(Table5[[#This Row],[Section]],1)="7","PDB",NOT(ISBLANK(Table5[[#This Row],[Section]])),"No")} -> No | N22: SUNDRY-14 | O22: Sundry description - 14
A23: =N30 -> SUNDRY-22 | B23: =O30 -> Sundry description - 22 | C23: N | D23: 0 | E23: 0 | F23: 0 | G23: =IF(LEFT(Table5[[#This Row],[Section]],3)="ETB","AE3000","") | K23: =_xlfn.IFNA(VLOOKUP(Table5[[#This Row],[Section]],SubSill_Tier,2,FALSE),0) -> 0 | L23: =IFERROR(IF(LEFT(G23,2)="AI",IF(_xlfn.NUMBERVALUE(IFERROR(LEFT(IF(ISERROR(FIND("X",UPPER(B23))),UPPER(B23),RIGHT(UPPER(B23),LEN(UPPER(B23))-FIND("~",SUBSTITUTE(UPPER(B23),"X","~",LEN(UPPER(B23))-LEN(SUBSTITUTE(UPPER(B23),"X","")))))),FIND(" ",IF(ISERROR(FIND("X",UPPER(B23))),UPPER(B23),RIGHT(UPPER(B23),LEN(UPPER(B23))-FIND("~",SUBSTITUTE(UPPER(B23),"X","~",LEN(UPPER(B23))-LEN(SUBSTITUTE(UPPER(B23),"X","")))))),1)-1),IF(ISERROR(FIND("X",UPPER(B23))),UPPER(B23),RIGHT(UPPER(B23),LEN(UPPER(B23))-FIND("~",SUBSTITUTE(UPPER(B23),"X","~",LEN(UPPER(B23))-LEN(SUBSTITUTE(UPPER(B23),"X",""))))))),".")>=5,"Wall",""),""),"") | M23: {=_xlfn.IFS(NOT(ISERROR(VLOOKUP(Table5[[#This Row],[Section]],TB_notTB,1,FALSE))),"No",LEFT(Table5[[#This Row],[Section]],3)="ETB","PLS",LEFT(Table5[[#This Row],[Section]],1)="7","PDB",NOT(ISBLANK(Table5[[#This Row],[Section]])),"No")} -> No | N23: SUNDRY-15 | O23: Sundry description - 15
A24: =N31 -> SUNDRY-23 | B24: =O31 -> Sundry description - 23 | C24: N | D24: 0 | E24: 0 | F24: 0 | G24: =IF(LEFT(Table5[[#This Row],[Section]],3)="ETB","AE3000","") | K24: =_xlfn.IFNA(VLOOKUP(Table5[[#This Row],[Section]],SubSill_Tier,2,FALSE),0) -> 0 | L24: =IFERROR(IF(LEFT(G24,2)="AI",IF(_xlfn.NUMBERVALUE(IFERROR(LEFT(IF(ISERROR(FIND("X",UPPER(B24))),UPPER(B24),RIGHT(UPPER(B24),LEN(UPPER(B24))-FIND("~",SUBSTITUTE(UPPER(B24),"X","~",LEN(UPPER(B24))-LEN(SUBSTITUTE(UPPER(B24),"X","")))))),FIND(" ",IF(ISERROR(FIND("X",UPPER(B24))),UPPER(B24),RIGHT(UPPER(B24),LEN(UPPER(B24))-FIND("~",SUBSTITUTE(UPPER(B24),"X","~",LEN(UPPER(B24))-LEN(SUBSTITUTE(UPPER(B24),"X","")))))),1)-1),IF(ISERROR(FIND("X",UPPER(B24))),UPPER(B24),RIGHT(UPPER(B24),LEN(UPPER(B24))-FIND("~",SUBSTITUTE(UPPER(B24),"X","~",LEN(UPPER(B24))-LEN(SUBSTITUTE(UPPER(B24),"X",""))))))),".")>=5,"Wall",""),""),"") | M24: {=_xlfn.IFS(NOT(ISERROR(VLOOKUP(Table5[[#This Row],[Section]],TB_notTB,1,FALSE))),"No",LEFT(Table5[[#This Row],[Section]],3)="ETB","PLS",LEFT(Table5[[#This Row],[Section]],1)="7","PDB",NOT(ISBLANK(Table5[[#This Row],[Section]])),"No")} -> No | N24: SUNDRY-16 | O24: Sundry description - 16
A25: =N32 -> SUNDRY-24 | B25: =O32 -> Sundry description - 24 | C25: N | D25: 0 | E25: 0 | F25: 0 | G25: =IF(LEFT(Table5[[#This Row],[Section]],3)="ETB","AE3000","") | K25: =_xlfn.IFNA(VLOOKUP(Table5[[#This Row],[Section]],SubSill_Tier,2,FALSE),0) -> 0 | L25: =IFERROR(IF(LEFT(G25,2)="AI",IF(_xlfn.NUMBERVALUE(IFERROR(LEFT(IF(ISERROR(FIND("X",UPPER(B25))),UPPER(B25),RIGHT(UPPER(B25),LEN(UPPER(B25))-FIND("~",SUBSTITUTE(UPPER(B25),"X","~",LEN(UPPER(B25))-LEN(SUBSTITUTE(UPPER(B25),"X","")))))),FIND(" ",IF(ISERROR(FIND("X",UPPER(B25))),UPPER(B25),RIGHT(UPPER(B25),LEN(UPPER(B25))-FIND("~",SUBSTITUTE(UPPER(B25),"X","~",LEN(UPPER(B25))-LEN(SUBSTITUTE(UPPER(B25),"X","")))))),1)-1),IF(ISERROR(FIND("X",UPPER(B25))),UPPER(B25),RIGHT(UPPER(B25),LEN(UPPER(B25))-FIND("~",SUBSTITUTE(UPPER(B25),"X","~",LEN(UPPER(B25))-LEN(SUBSTITUTE(UPPER(B25),"X",""))))))),".")>=5,"Wall",""),""),"") | M25: {=_xlfn.IFS(NOT(ISERROR(VLOOKUP(Table5[[#This Row],[Section]],TB_notTB,1,FALSE))),"No",LEFT(Table5[[#This Row],[Section]],3)="ETB","PLS",LEFT(Table5[[#This Row],[Section]],1)="7","PDB",NOT(ISBLANK(Table5[[#This Row],[Section]])),"No")} -> No | N25: SUNDRY-17 | O25: Sundry description - 17
A26: =N33 -> SUNDRY-25 | B26: =O33 -> Sundry description - 25 | C26: N | D26: 0 | E26: 0 | F26: 0 | G26: =IF(LEFT(Table5[[#This Row],[Section]],3)="ETB","AE3000","") | K26: =_xlfn.IFNA(VLOOKUP(Table5[[#This Row],[Section]],SubSill_Tier,2,FALSE),0) -> 0 | L26: =IFERROR(IF(LEFT(G26,2)="AI",IF(_xlfn.NUMBERVALUE(IFERROR(LEFT(IF(ISERROR(FIND("X",UPPER(B26))),UPPER(B26),RIGHT(UPPER(B26),LEN(UPPER(B26))-FIND("~",SUBSTITUTE(UPPER(B26),"X","~",LEN(UPPER(B26))-LEN(SUBSTITUTE(UPPER(B26),"X","")))))),FIND(" ",IF(ISERROR(FIND("X",UPPER(B26))),UPPER(B26),RIGHT(UPPER(B26),LEN(UPPER(B26))-FIND("~",SUBSTITUTE(UPPER(B26),"X","~",LEN(UPPER(B26))-LEN(SUBSTITUTE(UPPER(B26),"X","")))))),1)-1),IF(ISERROR(FIND("X",UPPER(B26))),UPPER(B26),RIGHT(UPPER(B26),LEN(UPPER(B26))-FIND("~",SUBSTITUTE(UPPER(B26),"X","~",LEN(UPPER(B26))-LEN(SUBSTITUTE(UPPER(B26),"X",""))))))),".")>=5,"Wall",""),""),"") | M26: {=_xlfn.IFS(NOT(ISERROR(VLOOKUP(Table5[[#This Row],[Section]],TB_notTB,1,FALSE))),"No",LEFT(Table5[[#This Row],[Section]],3)="ETB","PLS",LEFT(Table5[[#This Row],[Section]],1)="7","PDB",NOT(ISBLANK(Table5[[#This Row],[Section]])),"No")} -> No | N26: SUNDRY-18 | O26: Sundry description - 18
A27: =N34 -> SUNDRY-26 | B27: =O34 -> Sundry description - 26 | C27: N | D27: 0 | E27: 0 | F27: 0 | G27: =IF(LEFT(Table5[[#This Row],[Section]],3)="ETB","AE3000","") | K27: =_xlfn.IFNA(VLOOKUP(Table5[[#This Row],[Section]],SubSill_Tier,2,FALSE),0) -> 0 | L27: =IFERROR(IF(LEFT(G27,2)="AI",IF(_xlfn.NUMBERVALUE(IFERROR(LEFT(IF(ISERROR(FIND("X",UPPER(B27))),UPPER(B27),RIGHT(UPPER(B27),LEN(UPPER(B27))-FIND("~",SUBSTITUTE(UPPER(B27),"X","~",LEN(UPPER(B27))-LEN(SUBSTITUTE(UPPER(B27),"X","")))))),FIND(" ",IF(ISERROR(FIND("X",UPPER(B27))),UPPER(B27),RIGHT(UPPER(B27),LEN(UPPER(B27))-FIND("~",SUBSTITUTE(UPPER(B27),"X","~",LEN(UPPER(B27))-LEN(SUBSTITUTE(UPPER(B27),"X","")))))),1)-1),IF(ISERROR(FIND("X",UPPER(B27))),UPPER(B27),RIGHT(UPPER(B27),LEN(UPPER(B27))-FIND("~",SUBSTITUTE(UPPER(B27),"X","~",LEN(UPPER(B27))-LEN(SUBSTITUTE(UPPER(B27),"X",""))))))),".")>=5,"Wall",""),""),"") | M27: {=_xlfn.IFS(NOT(ISERROR(VLOOKUP(Table5[[#This Row],[Section]],TB_notTB,1,FALSE))),"No",LEFT(Table5[[#This Row],[Section]],3)="ETB","PLS",LEFT(Table5[[#This Row],[Section]],1)="7","PDB",NOT(ISBLANK(Table5[[#This Row],[Section]])),"No")} -> No | N27: SUNDRY-19 | O27: Sundry description - 19
A28: =N35 -> SUNDRY-27 | B28: =O35 -> Sundry description - 27 | C28: N | D28: 0 | E28: 0 | F28: 0 | G28: =IF(LEFT(Table5[[#This Row],[Section]],3)="ETB","AE3000","") | K28: =_xlfn.IFNA(VLOOKUP(Table5[[#This Row],[Section]],SubSill_Tier,2,FALSE),0) -> 0 | L28: =IFERROR(IF(LEFT(G28,2)="AI",IF(_xlfn.NUMBERVALUE(IFERROR(LEFT(IF(ISERROR(FIND("X",UPPER(B28))),UPPER(B28),RIGHT(UPPER(B28),LEN(UPPER(B28))-FIND("~",SUBSTITUTE(UPPER(B28),"X","~",LEN(UPPER(B28))-LEN(SUBSTITUTE(UPPER(B28),"X","")))))),FIND(" ",IF(ISERROR(FIND("X",UPPER(B28))),UPPER(B28),RIGHT(UPPER(B28),LEN(UPPER(B28))-FIND("~",SUBSTITUTE(UPPER(B28),"X","~",LEN(UPPER(B28))-LEN(SUBSTITUTE(UPPER(B28),"X","")))))),1)-1),IF(ISERROR(FIND("X",UPPER(B28))),UPPER(B28),RIGHT(UPPER(B28),LEN(UPPER(B28))-FIND("~",SUBSTITUTE(UPPER(B28),"X","~",LEN(UPPER(B28))-LEN(SUBSTITUTE(UPPER(B28),"X",""))))))),".")>=5,"Wall",""),""),"") | M28: {=_xlfn.IFS(NOT(ISERROR(VLOOKUP(Table5[[#This Row],[Section]],TB_notTB,1,FALSE))),"No",LEFT(Table5[[#This Row],[Section]],3)="ETB","PLS",LEFT(Table5[[#This Row],[Section]],1)="7","PDB",NOT(ISBLANK(Table5[[#This Row],[Section]])),"No")} -> No | N28: SUNDRY-20 | O28: Sundry description - 20
A29: =N36 -> SUNDRY-28 | B29: =O36 -> Sundry description - 28 | C29: N | D29: 0 | E29: 0 | F29: 0 | G29: =IF(LEFT(Table5[[#This Row],[Section]],3)="ETB","AE3000","") | K29: =_xlfn.IFNA(VLOOKUP(Table5[[#This Row],[Section]],SubSill_Tier,2,FALSE),0) -> 0 | L29: =IFERROR(IF(LEFT(G29,2)="AI",IF(_xlfn.NUMBERVALUE(IFERROR(LEFT(IF(ISERROR(FIND("X",UPPER(B29))),UPPER(B29),RIGHT(UPPER(B29),LEN(UPPER(B29))-FIND("~",SUBSTITUTE(UPPER(B29),"X","~",LEN(UPPER(B29))-LEN(SUBSTITUTE(UPPER(B29),"X","")))))),FIND(" ",IF(ISERROR(FIND("X",UPPER(B29))),UPPER(B29),RIGHT(UPPER(B29),LEN(UPPER(B29))-FIND("~",SUBSTITUTE(UPPER(B29),"X","~",LEN(UPPER(B29))-LEN(SUBSTITUTE(UPPER(B29),"X","")))))),1)-1),IF(ISERROR(FIND("X",UPPER(B29))),UPPER(B29),RIGHT(UPPER(B29),LEN(UPPER(B29))-FIND("~",SUBSTITUTE(UPPER(B29),"X","~",LEN(UPPER(B29))-LEN(SUBSTITUTE(UPPER(B29),"X",""))))))),".")>=5,"Wall",""),""),"") | M29: {=_xlfn.IFS(NOT(ISERROR(VLOOKUP(Table5[[#This Row],[Section]],TB_notTB,1,FALSE))),"No",LEFT(Table5[[#This Row],[Section]],3)="ETB","PLS",LEFT(Table5[[#This Row],[Section]],1)="7","PDB",NOT(ISBLANK(Table5[[#This Row],[Section]])),"No")} -> No | N29: SUNDRY-21 | O29: Sundry description - 21
A30: =N37 -> SUNDRY-29 | B30: =O37 -> Sundry description - 29 | C30: N | D30: 0 | E30: 0 | F30: 0 | G30: =IF(LEFT(Table5[[#This Row],[Section]],3)="ETB","AE3000","") | K30: =_xlfn.IFNA(VLOOKUP(Table5[[#This Row],[Section]],SubSill_Tier,2,FALSE),0) -> 0 | L30: =IFERROR(IF(LEFT(G30,2)="AI",IF(_xlfn.NUMBERVALUE(IFERROR(LEFT(IF(ISERROR(FIND("X",UPPER(B30))),UPPER(B30),RIGHT(UPPER(B30),LEN(UPPER(B30))-FIND("~",SUBSTITUTE(UPPER(B30),"X","~",LEN(UPPER(B30))-LEN(SUBSTITUTE(UPPER(B30),"X","")))))),FIND(" ",IF(ISERROR(FIND("X",UPPER(B30))),UPPER(B30),RIGHT(UPPER(B30),LEN(UPPER(B30))-FIND("~",SUBSTITUTE(UPPER(B30),"X","~",LEN(UPPER(B30))-LEN(SUBSTITUTE(UPPER(B30),"X","")))))),1)-1),IF(ISERROR(FIND("X",UPPER(B30))),UPPER(B30),RIGHT(UPPER(B30),LEN(UPPER(B30))-FIND("~",SUBSTITUTE(UPPER(B30),"X","~",LEN(UPPER(B30))-LEN(SUBSTITUTE(UPPER(B30),"X",""))))))),".")>=5,"Wall",""),""),"") | M30: {=_xlfn.IFS(NOT(ISERROR(VLOOKUP(Table5[[#This Row],[Section]],TB_notTB,1,FALSE))),"No",LEFT(Table5[[#This Row],[Section]],3)="ETB","PLS",LEFT(Table5[[#This Row],[Section]],1)="7","PDB",NOT(ISBLANK(Table5[[#This Row],[Section]])),"No")} -> No | N30: SUNDRY-22 | O30: Sundry description - 22
A31: =N38 -> SUNDRY-30 | B31: =O38 -> Sundry description - 30 | C31: N | D31: 0 | E31: 0 | F31: 0 | G31: =IF(LEFT(Table5[[#This Row],[Section]],3)="ETB","AE3000","") | K31: =_xlfn.IFNA(VLOOKUP(Table5[[#This Row],[Section]],SubSill_Tier,2,FALSE),0) -> 0 | L31: =IFERROR(IF(LEFT(G31,2)="AI",IF(_xlfn.NUMBERVALUE(IFERROR(LEFT(IF(ISERROR(FIND("X",UPPER(B31))),UPPER(B31),RIGHT(UPPER(B31),LEN(UPPER(B31))-FIND("~",SUBSTITUTE(UPPER(B31),"X","~",LEN(UPPER(B31))-LEN(SUBSTITUTE(UPPER(B31),"X","")))))),FIND(" ",IF(ISERROR(FIND("X",UPPER(B31))),UPPER(B31),RIGHT(UPPER(B31),LEN(UPPER(B31))-FIND("~",SUBSTITUTE(UPPER(B31),"X","~",LEN(UPPER(B31))-LEN(SUBSTITUTE(UPPER(B31),"X","")))))),1)-1),IF(ISERROR(FIND("X",UPPER(B31))),UPPER(B31),RIGHT(UPPER(B31),LEN(UPPER(B31))-FIND("~",SUBSTITUTE(UPPER(B31),"X","~",LEN(UPPER(B31))-LEN(SUBSTITUTE(UPPER(B31),"X",""))))))),".")>=5,"Wall",""),""),"") | M31: {=_xlfn.IFS(NOT(ISERROR(VLOOKUP(Table5[[#This Row],[Section]],TB_notTB,1,FALSE))),"No",LEFT(Table5[[#This Row],[Section]],3)="ETB","PLS",LEFT(Table5[[#This Row],[Section]],1)="7","PDB",NOT(ISBLANK(Table5[[#This Row],[Section]])),"No")} -> No | N31: SUNDRY-23 | O31: Sundry description - 23
A32: =N39 -> SUNDRY-31 | B32: =O39 -> Sundry description - 31 | C32: N | D32: 0 | E32: 0 | F32: 0 | G32: =IF(LEFT(Table5[[#This Row],[Section]],3)="ETB","AE3000","") | K32: =_xlfn.IFNA(VLOOKUP(Table5[[#This Row],[Section]],SubSill_Tier,2,FALSE),0) -> 0 | L32: =IFERROR(IF(LEFT(G32,2)="AI",IF(_xlfn.NUMBERVALUE(IFERROR(LEFT(IF(ISERROR(FIND("X",UPPER(B32))),UPPER(B32),RIGHT(UPPER(B32),LEN(UPPER(B32))-FIND("~",SUBSTITUTE(UPPER(B32),"X","~",LEN(UPPER(B32))-LEN(SUBSTITUTE(UPPER(B32),"X","")))))),FIND(" ",IF(ISERROR(FIND("X",UPPER(B32))),UPPER(B32),RIGHT(UPPER(B32),LEN(UPPER(B32))-FIND("~",SUBSTITUTE(UPPER(B32),"X","~",LEN(UPPER(B32))-LEN(SUBSTITUTE(UPPER(B32),"X","")))))),1)-1),IF(ISERROR(FIND("X",UPPER(B32))),UPPER(B32),RIGHT(UPPER(B32),LEN(UPPER(B32))-FIND("~",SUBSTITUTE(UPPER(B32),"X","~",LEN(UPPER(B32))-LEN(SUBSTITUTE(UPPER(B32),"X",""))))))),".")>=5,"Wall",""),""),"") | M32: {=_xlfn.IFS(NOT(ISERROR(VLOOKUP(Table5[[#This Row],[Section]],TB_notTB,1,FALSE))),"No",LEFT(Table5[[#This Row],[Section]],3)="ETB","PLS",LEFT(Table5[[#This Row],[Section]],1)="7","PDB",NOT(ISBLANK(Table5[[#This Row],[Section]])),"No")} -> No | N32: SUNDRY-24 | O32: Sundry description - 24
A33: =N40 -> SUNDRY-32 | B33: =O40 -> Sundry description - 32 | C33: N | D33: 0 | E33: 0 | F33: 0 | G33: =IF(LEFT(Table5[[#This Row],[Section]],3)="ETB","AE3000","") | K33: =_xlfn.IFNA(VLOOKUP(Table5[[#This Row],[Section]],SubSill_Tier,2,FALSE),0) -> 0 | L33: =IFERROR(IF(LEFT(G33,2)="AI",IF(_xlfn.NUMBERVALUE(IFERROR(LEFT(IF(ISERROR(FIND("X",UPPER(B33))),UPPER(B33),RIGHT(UPPER(B33),LEN(UPPER(B33))-FIND("~",SUBSTITUTE(UPPER(B33),"X","~",LEN(UPPER(B33))-LEN(SUBSTITUTE(UPPER(B33),"X","")))))),FIND(" ",IF(ISERROR(FIND("X",UPPER(B33))),UPPER(B33),RIGHT(UPPER(B33),LEN(UPPER(B33))-FIND("~",SUBSTITUTE(UPPER(B33),"X","~",LEN(UPPER(B33))-LEN(SUBSTITUTE(UPPER(B33),"X","")))))),1)-1),IF(ISERROR(FIND("X",UPPER(B33))),UPPER(B33),RIGHT(UPPER(B33),LEN(UPPER(B33))-FIND("~",SUBSTITUTE(UPPER(B33),"X","~",LEN(UPPER(B33))-LEN(SUBSTITUTE(UPPER(B33),"X",""))))))),".")>=5,"Wall",""),""),"") | M33: {=_xlfn.IFS(NOT(ISERROR(VLOOKUP(Table5[[#This Row],[Section]],TB_notTB,1,FALSE))),"No",LEFT(Table5[[#This Row],[Section]],3)="ETB","PLS",LEFT(Table5[[#This Row],[Section]],1)="7","PDB",NOT(ISBLANK(Table5[[#This Row],[Section]])),"No")} -> No | N33: SUNDRY-25 | O33: Sundry description - 25
... A76: =N83 -> SUNDRY-75 | B76: =O83 -> Sundry description - 75 | C76: N | D76: 0 | E76: 0 | F76: 0 | G76: =IF(LEFT(Table5[[#This Row],[Section]],3)="ETB","AE3000","") | K76: =_xlfn.IFNA(VLOOKUP(Table5[[#This Row],[Section]],SubSill_Tier,2,FALSE),0) -> 0 | L76: =IFERROR(IF(LEFT(G76,2)="AI",IF(_xlfn.NUMBERVALUE(IFERROR(LEFT(IF(ISERROR(FIND("X",UPPER(B76))),UPPER(B76),RIGHT(UPPER(B76),LEN(UPPER(B76))-FIND("~",SUBSTITUTE(UPPER(B76),"X","~",LEN(UPPER(B76))-LEN(SUBSTITUTE(UPPER(B76),"X","")))))),FIND(" ",IF(ISERROR(FIND("X",UPPER(B76))),UPPER(B76),RIGHT(UPPER(B76),LEN(UPPER(B76))-FIND("~",SUBSTITUTE(UPPER(B76),"X","~",LEN(UPPER(B76))-LEN(SUBSTITUTE(UPPER(B76),"X","")))))),1)-1),IF(ISERROR(FIND("X",UPPER(B76))),UPPER(B76),RIGHT(UPPER(B76),LEN(UPPER(B76))-FIND("~",SUBSTITUTE(UPPER(B76),"X","~",LEN(UPPER(B76))-LEN(SUBSTITUTE(UPPER(B76),"X",""))))))),".")>=5,"Wall",""),""),"") | M76: {=_xlfn.IFS(NOT(ISERROR(VLOOKUP(Table5[[#This Row],[Section]],TB_notTB,1,FALSE))),"No",LEFT(Table5[[#This Row],[Section]],3)="ETB","PLS",LEFT(Table5[[#This Row],[Section]],1)="7","PDB",NOT(ISBLANK(Table5[[#This Row],[Section]])),"No")} -> No | N76: SUNDRY-68 | O76: Sundry description - 68
A77: 735663 | B77: C9367U U-MAX 66MM RAIL | C77: N | D77: 1.147 | E77: 428 | F77: 428 | G77: AE3615 | H77: 100012122131221014 | I77: EDGE MAX Sliding Door Single & DG | J77: BU | K77: =_xlfn.IFNA(VLOOKUP(Table5[[#This Row],[Section]],SubSill_Tier,2,FALSE),0) -> 0 | L77: =IFERROR(IF(LEFT(G77,2)="AI",IF(_xlfn.NUMBERVALUE(IFERROR(LEFT(IF(ISERROR(FIND("X",UPPER(B77))),UPPER(B77),RIGHT(UPPER(B77),LEN(UPPER(B77))-FIND("~",SUBSTITUTE(UPPER(B77),"X","~",LEN(UPPER(B77))-LEN(SUBSTITUTE(UPPER(B77),"X","")))))),FIND(" ",IF(ISERROR(FIND("X",UPPER(B77))),UPPER(B77),RIGHT(UPPER(B77),LEN(UPPER(B77))-FIND("~",SUBSTITUTE(UPPER(B77),"X","~",LEN(UPPER(B77))-LEN(SUBSTITUTE(UPPER(B77),"X","")))))),1)-1),IF(ISERROR(FIND("X",UPPER(B77))),UPPER(B77),RIGHT(UPPER(B77),LEN(UPPER(B77))-FIND("~",SUBSTITUTE(UPPER(B77),"X","~",LEN(UPPER(B77))-LEN(SUBSTITUTE(UPPER(B77),"X",""))))))),".")>=5,"Wall",""),""),"") | M77: {=_xlfn.IFS(NOT(ISERROR(VLOOKUP(Table5[[#This Row],[Section]],TB_notTB,1,FALSE))),"No",LEFT(Table5[[#This Row],[Section]],3)="ETB","PLS",LEFT(Table5[[#This Row],[Section]],1)="7","PDB",NOT(ISBLANK(Table5[[#This Row],[Section]])),"No")} -> PDB | N77: SUNDRY-69 | O77: Sundry description - 69
A78: 735664 | B78: C9367U U-MAX 66MM RAIL | C78: N | D78: 1.147 | E78: 428 | F78: 428 | G78: AE3615 | H78: 100012122131221014 | I78: EDGE MAX Sliding Door Single & DG | J78: BU | K78: =_xlfn.IFNA(VLOOKUP(Table5[[#This Row],[Section]],SubSill_Tier,2,FALSE),0) -> 0 | L78: =IFERROR(IF(LEFT(G78,2)="AI",IF(_xlfn.NUMBERVALUE(IFERROR(LEFT(IF(ISERROR(FIND("X",UPPER(B78))),UPPER(B78),RIGHT(UPPER(B78),LEN(UPPER(B78))-FIND("~",SUBSTITUTE(UPPER(B78),"X","~",LEN(UPPER(B78))-LEN(SUBSTITUTE(UPPER(B78),"X","")))))),FIND(" ",IF(ISERROR(FIND("X",UPPER(B78))),UPPER(B78),RIGHT(UPPER(B78),LEN(UPPER(B78))-FIND("~",SUBSTITUTE(UPPER(B78),"X","~",LEN(UPPER(B78))-LEN(SUBSTITUTE(UPPER(B78),"X","")))))),1)-1),IF(ISERROR(FIND("X",UPPER(B78))),UPPER(B78),RIGHT(UPPER(B78),LEN(UPPER(B78))-FIND("~",SUBSTITUTE(UPPER(B78),"X","~",LEN(UPPER(B78))-LEN(SUBSTITUTE(UPPER(B78),"X",""))))))),".")>=5,"Wall",""),""),"") | M78: {=_xlfn.IFS(NOT(ISERROR(VLOOKUP(Table5[[#This Row],[Section]],TB_notTB,1,FALSE))),"No",LEFT(Table5[[#This Row],[Section]],3)="ETB","PLS",LEFT(Table5[[#This Row],[Section]],1)="7","PDB",NOT(ISBLANK(Table5[[#This Row],[Section]])),"No")} -> PDB | N78: SUNDRY-70 | O78: Sundry description - 70
A79: 735665 | B79: C5308U U-MAX 150 SPANDREL INFIL SUBSILL-SLOT | C79: N | D79: 2.323 | E79: 807 | F79: 807 | G79: AE3695 | H79: 100012122331223001 | I79: EDGE 150mm Sub Framing | J79: BU | K79: =_xlfn.IFNA(VLOOKUP(Table5[[#This Row],[Section]],SubSill_Tier,2,FALSE),0) -> 0 | L79: =IFERROR(IF(LEFT(G79,2)="AI",IF(_xlfn.NUMBERVALUE(IFERROR(LEFT(IF(ISERROR(FIND("X",UPPER(B79))),UPPER(B79),RIGHT(UPPER(B79),LEN(UPPER(B79))-FIND("~",SUBSTITUTE(UPPER(B79),"X","~",LEN(UPPER(B79))-LEN(SUBSTITUTE(UPPER(B79),"X","")))))),FIND(" ",IF(ISERROR(FIND("X",UPPER(B79))),UPPER(B79),RIGHT(UPPER(B79),LEN(UPPER(B79))-FIND("~",SUBSTITUTE(UPPER(B79),"X","~",LEN(UPPER(B79))-LEN(SUBSTITUTE(UPPER(B79),"X","")))))),1)-1),IF(ISERROR(FIND("X",UPPER(B79))),UPPER(B79),RIGHT(UPPER(B79),LEN(UPPER(B79))-FIND("~",SUBSTITUTE(UPPER(B79),"X","~",LEN(UPPER(B79))-LEN(SUBSTITUTE(UPPER(B79),"X",""))))))),".")>=5,"Wall",""),""),"") | M79: {=_xlfn.IFS(NOT(ISERROR(VLOOKUP(Table5[[#This Row],[Section]],TB_notTB,1,FALSE))),"No",LEFT(Table5[[#This Row],[Section]],3)="ETB","PLS",LEFT(Table5[[#This Row],[Section]],1)="7","PDB",NOT(ISBLANK(Table5[[#This Row],[Section]])),"No")} -> PDB | N79: SUNDRY-71 | O79: Sundry description - 71
A80: 735666 | B80: C5308U U-MAX 150 SPANDREL INFIL SUBSILL-SLOT | C80: N | D80: 2.323 | E80: 807 | F80: 807 | G80: AE3695 | H80: 100012122331223001 | I80: EDGE 150mm Sub Framing | J80: BU | K80: =_xlfn.IFNA(VLOOKUP(Table5[[#This Row],[Section]],SubSill_Tier,2,FALSE),0) -> 0 | L80: =IFERROR(IF(LEFT(G80,2)="AI",IF(_xlfn.NUMBERVALUE(IFERROR(LEFT(IF(ISERROR(FIND("X",UPPER(B80))),UPPER(B80),RIGHT(UPPER(B80),LEN(UPPER(B80))-FIND("~",SUBSTITUTE(UPPER(B80),"X","~",LEN(UPPER(B80))-LEN(SUBSTITUTE(UPPER(B80),"X","")))))),FIND(" ",IF(ISERROR(FIND("X",UPPER(B80))),UPPER(B80),RIGHT(UPPER(B80),LEN(UPPER(B80))-FIND("~",SUBSTITUTE(UPPER(B80),"X","~",LEN(UPPER(B80))-LEN(SUBSTITUTE(UPPER(B80),"X","")))))),1)-1),IF(ISERROR(FIND("X",UPPER(B80))),UPPER(B80),RIGHT(UPPER(B80),LEN(UPPER(B80))-FIND("~",SUBSTITUTE(UPPER(B80),"X","~",LEN(UPPER(B80))-LEN(SUBSTITUTE(UPPER(B80),"X",""))))))),".")>=5,"Wall",""),""),"") | M80: {=_xlfn.IFS(NOT(ISERROR(VLOOKUP(Table5[[#This Row],[Section]],TB_notTB,1,FALSE))),"No",LEFT(Table5[[#This Row],[Section]],3)="ETB","PLS",LEFT(Table5[[#This Row],[Section]],1)="7","PDB",NOT(ISBLANK(Table5[[#This Row],[Section]])),"No")} -> PDB | N80: SUNDRY-72 | O80: Sundry description - 72
A81: 735667 | B81: C5310U U-MAX 150 SPANDREL SUBHEAD | C81: N | D81: 2.435 | E81: 729 | F81: 729 | G81: AE3695 | H81: 100012122331223001 | I81: EDGE 150mm Sub Framing | J81: BU | K81: =_xlfn.IFNA(VLOOKUP(Table5[[#This Row],[Section]],SubSill_Tier,2,FALSE),0) -> 0 | L81: =IFERROR(IF(LEFT(G81,2)="AI",IF(_xlfn.NUMBERVALUE(IFERROR(LEFT(IF(ISERROR(FIND("X",UPPER(B81))),UPPER(B81),RIGHT(UPPER(B81),LEN(UPPER(B81))-FIND("~",SUBSTITUTE(UPPER(B81),"X","~",LEN(UPPER(B81))-LEN(SUBSTITUTE(UPPER(B81),"X","")))))),FIND(" ",IF(ISERROR(FIND("X",UPPER(B81))),UPPER(B81),RIGHT(UPPER(B81),LEN(UPPER(B81))-FIND("~",SUBSTITUTE(UPPER(B81),"X","~",LEN(UPPER(B81))-LEN(SUBSTITUTE(UPPER(B81),"X","")))))),1)-1),IF(ISERROR(FIND("X",UPPER(B81))),UPPER(B81),RIGHT(UPPER(B81),LEN(UPPER(B81))-FIND("~",SUBSTITUTE(UPPER(B81),"X","~",LEN(UPPER(B81))-LEN(SUBSTITUTE(UPPER(B81),"X",""))))))),".")>=5,"Wall",""),""),"") | M81: {=_xlfn.IFS(NOT(ISERROR(VLOOKUP(Table5[[#This Row],[Section]],TB_notTB,1,FALSE))),"No",LEFT(Table5[[#This Row],[Section]],3)="ETB","PLS",LEFT(Table5[[#This Row],[Section]],1)="7","PDB",NOT(ISBLANK(Table5[[#This Row],[Section]])),"No")} -> PDB | N81: SUNDRY-73 | O81: Sundry description - 73
A82: 735668 | B82: C5312U U-MAX 150 ODG HD SHALLOW MULLION | C82: N | D82: 2.499 | E82: 763 | F82: 763 | G82: AE3580 | H82: 100012122131221007 | I82: EDGE MAX 150 Offset DG 34mm P | J82: BU | K82: =_xlfn.IFNA(VLOOKUP(Table5[[#This Row],[Section]],SubSill_Tier,2,FALSE),0) -> 0 | L82: =IFERROR(IF(LEFT(G82,2)="AI",IF(_xlfn.NUMBERVALUE(IFERROR(LEFT(IF(ISERROR(FIND("X",UPPER(B82))),UPPER(B82),RIGHT(UPPER(B82),LEN(UPPER(B82))-FIND("~",SUBSTITUTE(UPPER(B82),"X","~",LEN(UPPER(B82))-LEN(SUBSTITUTE(UPPER(B82),"X","")))))),FIND(" ",IF(ISERROR(FIND("X",UPPER(B82))),UPPER(B82),RIGHT(UPPER(B82),LEN(UPPER(B82))-FIND("~",SUBSTITUTE(UPPER(B82),"X","~",LEN(UPPER(B82))-LEN(SUBSTITUTE(UPPER(B82),"X","")))))),1)-1),IF(ISERROR(FIND("X",UPPER(B82))),UPPER(B82),RIGHT(UPPER(B82),LEN(UPPER(B82))-FIND("~",SUBSTITUTE(UPPER(B82),"X","~",LEN(UPPER(B82))-LEN(SUBSTITUTE(UPPER(B82),"X",""))))))),".")>=5,"Wall",""),""),"") | M82: {=_xlfn.IFS(NOT(ISERROR(VLOOKUP(Table5[[#This Row],[Section]],TB_notTB,1,FALSE))),"No",LEFT(Table5[[#This Row],[Section]],3)="ETB","PLS",LEFT(Table5[[#This Row],[Section]],1)="7","PDB",NOT(ISBLANK(Table5[[#This Row],[Section]])),"No")} -> PDB | N82: SUNDRY-74 | O82: Sundry description - 74
A83: 735669 | B83: C8125U U-MAX CDG MULTILOCK ADAPTOR | C83: N | D83: 0.488 | E83: 223 | F83: 223 | G83: AE3610 | H83: 100012122131221013 | I83: EDGE MAX Inset & Overlap Sashes | J83: BU | K83: =_xlfn.IFNA(VLOOKUP(Table5[[#This Row],[Section]],SubSill_Tier,2,FALSE),0) -> 0 | L83: =IFERROR(IF(LEFT(G83,2)="AI",IF(_xlfn.NUMBERVALUE(IFERROR(LEFT(IF(ISERROR(FIND("X",UPPER(B83))),UPPER(B83),RIGHT(UPPER(B83),LEN(UPPER(B83))-FIND("~",SUBSTITUTE(UPPER(B83),"X","~",LEN(UPPER(B83))-LEN(SUBSTITUTE(UPPER(B83),"X","")))))),FIND(" ",IF(ISERROR(FIND("X",UPPER(B83))),UPPER(B83),RIGHT(UPPER(B83),LEN(UPPER(B83))-FIND("~",SUBSTITUTE(UPPER(B83),"X","~",LEN(UPPER(B83))-LEN(SUBSTITUTE(UPPER(B83),"X","")))))),1)-1),IF(ISERROR(FIND("X",UPPER(B83))),UPPER(B83),RIGHT(UPPER(B83),LEN(UPPER(B83))-FIND("~",SUBSTITUTE(UPPER(B83),"X","~",LEN(UPPER(B83))-LEN(SUBSTITUTE(UPPER(B83),"X",""))))))),".")>=5,"Wall",""),""),"") | M83: {=_xlfn.IFS(NOT(ISERROR(VLOOKUP(Table5[[#This Row],[Section]],TB_notTB,1,FALSE))),"No",LEFT(Table5[[#This Row],[Section]],3)="ETB","PLS",LEFT(Table5[[#This Row],[Section]],1)="7","PDB",NOT(ISBLANK(Table5[[#This Row],[Section]])),"No")} -> PDB | N83: SUNDRY-75 | O83: Sundry description - 75
A84: 735670 | B84: C8126U U-MAX FDG MULTILOCK ADAPTOR | C84: N | D84: 0.6 | E84: 275 | F84: 275 | G84: AE3610 | H84: 100012122131221013 | I84: EDGE MAX Inset & Overlap Sashes | J84: BU | K84: =_xlfn.IFNA(VLOOKUP(Table5[[#This Row],[Section]],SubSill_Tier,2,FALSE),0) -> 0 | L84: =IFERROR(IF(LEFT(G84,2)="AI",IF(_xlfn.NUMBERVALUE(IFERROR(LEFT(IF(ISERROR(FIND("X",UPPER(B84))),UPPER(B84),RIGHT(UPPER(B84),LEN(UPPER(B84))-FIND("~",SUBSTITUTE(UPPER(B84),"X","~",LEN(UPPER(B84))-LEN(SUBSTITUTE(UPPER(B84),"X","")))))),FIND(" ",IF(ISERROR(FIND("X",UPPER(B84))),UPPER(B84),RIGHT(UPPER(B84),LEN(UPPER(B84))-FIND("~",SUBSTITUTE(UPPER(B84),"X","~",LEN(UPPER(B84))-LEN(SUBSTITUTE(UPPER(B84),"X","")))))),1)-1),IF(ISERROR(FIND("X",UPPER(B84))),UPPER(B84),RIGHT(UPPER(B84),LEN(UPPER(B84))-FIND("~",SUBSTITUTE(UPPER(B84),"X","~",LEN(UPPER(B84))-LEN(SUBSTITUTE(UPPER(B84),"X",""))))))),".")>=5,"Wall",""),""),"") | M84: {=_xlfn.IFS(NOT(ISERROR(VLOOKUP(Table5[[#This Row],[Section]],TB_notTB,1,FALSE))),"No",LEFT(Table5[[#This Row],[Section]],3)="ETB","PLS",LEFT(Table5[[#This Row],[Section]],1)="7","PDB",NOT(ISBLANK(Table5[[#This Row],[Section]])),"No")} -> PDB
A85: 735671 | B85: C8141U U-MAX 100X60 CDG DRAINED TRANSOM | C85: N | D85: 2.354 | E85: 507 | F85: 507 | G85: AE3545 | H85: 100012122131221000 | I85: EDGE MAX 100 Centre DG 34mm P | J85: BU | K85: =_xlfn.IFNA(VLOOKUP(Table5[[#This Row],[Section]],SubSill_Tier,2,FALSE),0) -> 0 | L85: =IFERROR(IF(LEFT(G85,2)="AI",IF(_xlfn.NUMBERVALUE(IFERROR(LEFT(IF(ISERROR(FIND("X",UPPER(B85))),UPPER(B85),RIGHT(UPPER(B85),LEN(UPPER(B85))-FIND("~",SUBSTITUTE(UPPER(B85),"X","~",LEN(UPPER(B85))-LEN(SUBSTITUTE(UPPER(B85),"X","")))))),FIND(" ",IF(ISERROR(FIND("X",UPPER(B85))),UPPER(B85),RIGHT(UPPER(B85),LEN(UPPER(B85))-FIND("~",SUBSTITUTE(UPPER(B85),"X","~",LEN(UPPER(B85))-LEN(SUBSTITUTE(UPPER(B85),"X","")))))),1)-1),IF(ISERROR(FIND("X",UPPER(B85))),UPPER(B85),RIGHT(UPPER(B85),LEN(UPPER(B85))-FIND("~",SUBSTITUTE(UPPER(B85),"X","~",LEN(UPPER(B85))-LEN(SUBSTITUTE(UPPER(B85),"X",""))))))),".")>=5,"Wall",""),""),"") | M85: {=_xlfn.IFS(NOT(ISERROR(VLOOKUP(Table5[[#This Row],[Section]],TB_notTB,1,FALSE))),"No",LEFT(Table5[[#This Row],[Section]],3)="ETB","PLS",LEFT(Table5[[#This Row],[Section]],1)="7","PDB",NOT(ISBLANK(Table5[[#This Row],[Section]])),"No")} -> PDB
A86: 735672 | B86: C8143U U-MAX 100X60 FDG DRAINED TRANSOM | C86: N | D86: 2.444 | E86: 507 | F86: 507 | G86: AE3550 | H86: 100012122131221001 | I86: EDGE MAX 100 Front DG 34mm P | J86: BU | K86: =_xlfn.IFNA(VLOOKUP(Table5[[#This Row],[Section]],SubSill_Tier,2,FALSE),0) -> 0 | L86: =IFERROR(IF(LEFT(G86,2)="AI",IF(_xlfn.NUMBERVALUE(IFERROR(LEFT(IF(ISERROR(FIND("X",UPPER(B86))),UPPER(B86),RIGHT(UPPER(B86),LEN(UPPER(B86))-FIND("~",SUBSTITUTE(UPPER(B86),"X","~",LEN(UPPER(B86))-LEN(SUBSTITUTE(UPPER(B86),"X","")))))),FIND(" ",IF(ISERROR(FIND("X",UPPER(B86))),UPPER(B86),RIGHT(UPPER(B86),LEN(UPPER(B86))-FIND("~",SUBSTITUTE(UPPER(B86),"X","~",LEN(UPPER(B86))-LEN(SUBSTITUTE(UPPER(B86),"X","")))))),1)-1),IF(ISERROR(FIND("X",UPPER(B86))),UPPER(B86),RIGHT(UPPER(B86),LEN(UPPER(B86))-FIND("~",SUBSTITUTE(UPPER(B86),"X","~",LEN(UPPER(B86))-LEN(SUBSTITUTE(UPPER(B86),"X",""))))))),".")>=5,"Wall",""),""),"") | M86: {=_xlfn.IFS(NOT(ISERROR(VLOOKUP(Table5[[#This Row],[Section]],TB_notTB,1,FALSE))),"No",LEFT(Table5[[#This Row],[Section]],3)="ETB","PLS",LEFT(Table5[[#This Row],[Section]],1)="7","PDB",NOT(ISBLANK(Table5[[#This Row],[Section]])),"No")} -> PDB
A87: 735673 | B87: C8191U U-MAX CW142 PLANT ON DOOR STOP | C87: N | D87: 0.871 | E87: 269 | F87: 269 | G87: AE3730 | H87: 100012122431224003 | I87: EDGE U-MAX CW142 Curtain W(142.5mm Base) | J87: BU | K87: =_xlfn.IFNA(VLOOKUP(Table5[[#This Row],[Section]],SubSill_Tier,2,FALSE),0) -> 0 | L87: =IFERROR(IF(LEFT(G87,2)="AI",IF(_xlfn.NUMBERVALUE(IFERROR(LEFT(IF(ISERROR(FIND("X",UPPER(B87))),UPPER(B87),RIGHT(UPPER(B87),LEN(UPPER(B87))-FIND("~",SUBSTITUTE(UPPER(B87),"X","~",LEN(UPPER(B87))-LEN(SUBSTITUTE(UPPER(B87),"X","")))))),FIND(" ",IF(ISERROR(FIND("X",UPPER(B87))),UPPER(B87),RIGHT(UPPER(B87),LEN(UPPER(B87))-FIND("~",SUBSTITUTE(UPPER(B87),"X","~",LEN(UPPER(B87))-LEN(SUBSTITUTE(UPPER(B87),"X","")))))),1)-1),IF(ISERROR(FIND("X",UPPER(B87))),UPPER(B87),RIGHT(UPPER(B87),LEN(UPPER(B87))-FIND("~",SUBSTITUTE(UPPER(B87),"X","~",LEN(UPPER(B87))-LEN(SUBSTITUTE(UPPER(B87),"X",""))))))),".")>=5,"Wall",""),""),"") | M87: {=_xlfn.IFS(NOT(ISERROR(VLOOKUP(Table5[[#This Row],[Section]],TB_notTB,1,FALSE))),"No",LEFT(Table5[[#This Row],[Section]],3)="ETB","PLS",LEFT(Table5[[#This Row],[Section]],1)="7","PDB",NOT(ISBLANK(Table5[[#This Row],[Section]])),"No")} -> PDB
A88: 735674 | B88: C8370U U-MAX 150FDG-40 FRAME | C88: N | D88: 2.314 | E88: 772 | F88: 772 | G88: AE3650 | H88: 100012122231222005 | I88: EDGE U-MAX 150 Front DG 40mm P | J88: BU | K88: =_xlfn.IFNA(VLOOKUP(Table5[[#This Row],[Section]],SubSill_Tier,2,FALSE),0) -> 0 | L88: =IFERROR(IF(LEFT(G88,2)="AI",IF(_xlfn.NUMBERVALUE(IFERROR(LEFT(IF(ISERROR(FIND("X",UPPER(B88))),UPPER(B88),RIGHT(UPPER(B88),LEN(UPPER(B88))-FIND("~",SUBSTITUTE(UPPER(B88),"X","~",LEN(UPPER(B88))-LEN(SUBSTITUTE(UPPER(B88),"X","")))))),FIND(" ",IF(ISERROR(FIND("X",UPPER(B88))),UPPER(B88),RIGHT(UPPER(B88),LEN(UPPER(B88))-FIND("~",SUBSTITUTE(UPPER(B88),"X","~",LEN(UPPER(B88))-LEN(SUBSTITUTE(UPPER(B88),"X","")))))),1)-1),IF(ISERROR(FIND("X",UPPER(B88))),UPPER(B88),RIGHT(UPPER(B88),LEN(UPPER(B88))-FIND("~",SUBSTITUTE(UPPER(B88),"X","~",LEN(UPPER(B88))-LEN(SUBSTITUTE(UPPER(B88),"X",""))))))),".")>=5,"Wall",""),""),"") | M88: {=_xlfn.IFS(NOT(ISERROR(VLOOKUP(Table5[[#This Row],[Section]],TB_notTB,1,FALSE))),"No",LEFT(Table5[[#This Row],[Section]],3)="ETB","PLS",LEFT(Table5[[#This Row],[Section]],1)="7","PDB",NOT(ISBLANK(Table5[[#This Row],[Section]])),"No")} -> PDB
A89: 735675 | B89: C8371U U-MAX 150FDG-40 EXT SILL | C89: N | D89: 2.674 | E89: 619 | F89: 619 | G89: AE3650 | H89: 100012122231222005 | I89: EDGE U-MAX 150 Front DG 40mm P | J89: BU | K89: =_xlfn.IFNA(VLOOKUP(Table5[[#This Row],[Section]],SubSill_Tier,2,FALSE),0) -> 0 | L89: =IFERROR(IF(LEFT(G89,2)="AI",IF(_xlfn.NUMBERVALUE(IFERROR(LEFT(IF(ISERROR(FIND("X",UPPER(B89))),UPPER(B89),RIGHT(UPPER(B89),LEN(UPPER(B89))-FIND("~",SUBSTITUTE(UPPER(B89),"X","~",LEN(UPPER(B89))-LEN(SUBSTITUTE(UPPER(B89),"X","")))))),FIND(" ",IF(ISERROR(FIND("X",UPPER(B89))),UPPER(B89),RIGHT(UPPER(B89),LEN(UPPER(B89))-FIND("~",SUBSTITUTE(UPPER(B89),"X","~",LEN(UPPER(B89))-LEN(SUBSTITUTE(UPPER(B89),"X","")))))),1)-1),IF(ISERROR(FIND("X",UPPER(B89))),UPPER(B89),RIGHT(UPPER(B89),LEN(UPPER(B89))-FIND("~",SUBSTITUTE(UPPER(B89),"X","~",LEN(UPPER(B89))-LEN(SUBSTITUTE(UPPER(B89),"X",""))))))),".")>=5,"Wall",""),""),"") | M89: {=_xlfn.IFS(NOT(ISERROR(VLOOKUP(Table5[[#This Row],[Section]],TB_notTB,1,FALSE))),"No",LEFT(Table5[[#This Row],[Section]],3)="ETB","PLS",LEFT(Table5[[#This Row],[Section]],1)="7","PDB",NOT(ISBLANK(Table5[[#This Row],[Section]])),"No")} -> PDB
A90: 735676 | B90: C8374U U-MAX 150FDG-40 POCKETED FILLER | C90: N | D90: 1.291 | E90: 472 | F90: 472 | G90: AE3650 | H90: 100012122231222005 | I90: EDGE U-MAX 150 Front DG 40mm P | J90: BU | K90: =_xlfn.IFNA(VLOOKUP(Table5[[#This Row],[Section]],SubSill_Tier,2,FALSE),0) -> 0 | L90: =IFERROR(IF(LEFT(G90,2)="AI",IF(_xlfn.NUMBERVALUE(IFERROR(LEFT(IF(ISERROR(FIND("X",UPPER(B90))),UPPER(B90),RIGHT(UPPER(B90),LEN(UPPER(B90))-FIND("~",SUBSTITUTE(UPPER(B90),"X","~",LEN(UPPER(B90))-LEN(SUBSTITUTE(UPPER(B90),"X","")))))),FIND(" ",IF(ISERROR(FIND("X",UPPER(B90))),UPPER(B90),RIGHT(UPPER(B90),LEN(UPPER(B90))-FIND("~",SUBSTITUTE(UPPER(B90),"X","~",LEN(UPPER(B90))-LEN(SUBSTITUTE(UPPER(B90),"X","")))))),1)-1),IF(ISERROR(FIND("X",UPPER(B90))),UPPER(B90),RIGHT(UPPER(B90),LEN(UPPER(B90))-FIND("~",SUBSTITUTE(UPPER(B90),"X","~",LEN(UPPER(B90))-LEN(SUBSTITUTE(UPPER(B90),"X",""))))))),".")>=5,"Wall",""),""),"") | M90: {=_xlfn.IFS(NOT(ISERROR(VLOOKUP(Table5[[#This Row],[Section]],TB_notTB,1,FALSE))),"No",LEFT(Table5[[#This Row],[Section]],3)="ETB","PLS",LEFT(Table5[[#This Row],[Section]],1)="7","PDB",NOT(ISBLANK(Table5[[#This Row],[Section]])),"No")} -> PDB
A91: 735677 | B91: C8376U U-MAX 150FDG-40 MALE MULLION | C91: N | D91: 2.318 | E91: 714 | F91: 714 | G91: AE3650 | H91: 100012122231222005 | I91: EDGE U-MAX 150 Front DG 40mm P | J91: BU | K91: =_xlfn.IFNA(VLOOKUP(Table5[[#This Row],[Section]],SubSill_Tier,2,FALSE),0) -> 0 | L91: =IFERROR(IF(LEFT(G91,2)="AI",IF(_xlfn.NUMBERVALUE(IFERROR(LEFT(IF(ISERROR(FIND("X",UPPER(B91))),UPPER(B91),RIGHT(UPPER(B91),LEN(UPPER(B91))-FIND("~",SUBSTITUTE(UPPER(B91),"X","~",LEN(UPPER(B91))-LEN(SUBSTITUTE(UPPER(B91),"X","")))))),FIND(" ",IF(ISERROR(FIND("X",UPPER(B91))),UPPER(B91),RIGHT(UPPER(B91),LEN(UPPER(B91))-FIND("~",SUBSTITUTE(UPPER(B91),"X","~",LEN(UPPER(B91))-LEN(SUBSTITUTE(UPPER(B91),"X","")))))),1)-1),IF(ISERROR(FIND("X",UPPER(B91))),UPPER(B91),RIGHT(UPPER(B91),LEN(UPPER(B91))-FIND("~",SUBSTITUTE(UPPER(B91),"X","~",LEN(UPPER(B91))-LEN(SUBSTITUTE(UPPER(B91),"X",""))))))),".")>=5,"Wall",""),""),"") | M91: {=_xlfn.IFS(NOT(ISERROR(VLOOKUP(Table5[[#This Row],[Section]],TB_notTB,1,FALSE))),"No",LEFT(Table5[[#This Row],[Section]],3)="ETB","PLS",LEFT(Table5[[#This Row],[Section]],1)="7","PDB",NOT(ISBLANK(Table5[[#This Row],[Section]])),"No")} -> PDB
A92: 735678 | B92: C8377U U-MAX 150FDG-40 FEMALE MULLION | C92: N | D92: 2.146 | E92: 685 | F92: 685 | G92: AE3650 | H92: 100012122231222005 | I92: EDGE U-MAX 150 Front DG 40mm P | J92: BU | K92: =_xlfn.IFNA(VLOOKUP(Table5[[#This Row],[Section]],SubSill_Tier,2,FALSE),0) -> 0 | L92: =IFERROR(IF(LEFT(G92,2)="AI",IF(_xlfn.NUMBERVALUE(IFERROR(LEFT(IF(ISERROR(FIND("X",UPPER(B92))),UPPER(B92),RIGHT(UPPER(B92),LEN(UPPER(B92))-FIND("~",SUBSTITUTE(UPPER(B92),"X","~",LEN(UPPER(B92))-LEN(SUBSTITUTE(UPPER(B92),"X","")))))),FIND(" ",IF(ISERROR(FIND("X",UPPER(B92))),UPPER(B92),RIGHT(UPPER(B92),LEN(UPPER(B92))-FIND("~",SUBSTITUTE(UPPER(B92),"X","~",LEN(UPPER(B92))-LEN(SUBSTITUTE(UPPER(B92),"X","")))))),1)-1),IF(ISERROR(FIND("X",UPPER(B92))),UPPER(B92),RIGHT(UPPER(B92),LEN(UPPER(B92))-FIND("~",SUBSTITUTE(UPPER(B92),"X","~",LEN(UPPER(B92))-LEN(SUBSTITUTE(UPPER(B92),"X",""))))))),".")>=5,"Wall",""),""),"") | M92: {=_xlfn.IFS(NOT(ISERROR(VLOOKUP(Table5[[#This Row],[Section]],TB_notTB,1,FALSE))),"No",LEFT(Table5[[#This Row],[Section]],3)="ETB","PLS",LEFT(Table5[[#This Row],[Section]],1)="7","PDB",NOT(ISBLANK(Table5[[#This Row],[Section]])),"No")} -> PDB
A93: 735679 | B93: C8378U U-MAX FDG-40 POCKETED FILLER | C93: N | D93: 0.415 | E93: 175 | F93: 175 | G93: AE3650 | H93: 100012122231222005 | I93: EDGE U-MAX 150 Front DG 40mm P | J93: BU | K93: =_xlfn.IFNA(VLOOKUP(Table5[[#This Row],[Section]],SubSill_Tier,2,FALSE),0) -> 0 | L93: =IFERROR(IF(LEFT(G93,2)="AI",IF(_xlfn.NUMBERVALUE(IFERROR(LEFT(IF(ISERROR(FIND("X",UPPER(B93))),UPPER(B93),RIGHT(UPPER(B93),LEN(UPPER(B93))-FIND("~",SUBSTITUTE(UPPER(B93),"X","~",LEN(UPPER(B93))-LEN(SUBSTITUTE(UPPER(B93),"X","")))))),FIND(" ",IF(ISERROR(FIND("X",UPPER(B93))),UPPER(B93),RIGHT(UPPER(B93),LEN(UPPER(B93))-FIND("~",SUBSTITUTE(UPPER(B93),"X","~",LEN(UPPER(B93))-LEN(SUBSTITUTE(UPPER(B93),"X","")))))),1)-1),IF(ISERROR(FIND("X",UPPER(B93))),UPPER(B93),RIGHT(UPPER(B93),LEN(UPPER(B93))-FIND("~",SUBSTITUTE(UPPER(B93),"X","~",LEN(UPPER(B93))-LEN(SUBSTITUTE(UPPER(B93),"X",""))))))),".")>=5,"Wall",""),""),"") | M93: {=_xlfn.IFS(NOT(ISERROR(VLOOKUP(Table5[[#This Row],[Section]],TB_notTB,1,FALSE))),"No",LEFT(Table5[[#This Row],[Section]],3)="ETB","PLS",LEFT(Table5[[#This Row],[Section]],1)="7","PDB",NOT(ISBLANK(Table5[[#This Row],[Section]])),"No")} -> PDB
A94: 735680 | B94: C9180U U-MAX BIFOLD HEAD | C94: N | D94: 3.727 | E94: 807 | F94: 807 | G94: AE3595 | H94: 100012122131221010 | I94: EDGE MAX 50mm Bifold Door | J94: BU | K94: =_xlfn.IFNA(VLOOKUP(Table5[[#This Row],[Section]],SubSill_Tier,2,FALSE),0) -> 0 | L94: =IFERROR(IF(LEFT(G94,2)="AI",IF(_xlfn.NUMBERVALUE(IFERROR(LEFT(IF(ISERROR(FIND("X",UPPER(B94))),UPPER(B94),RIGHT(UPPER(B94),LEN(UPPER(B94))-FIND("~",SUBSTITUTE(UPPER(B94),"X","~",LEN(UPPER(B94))-LEN(SUBSTITUTE(UPPER(B94),"X","")))))),FIND(" ",IF(ISERROR(FIND("X",UPPER(B94))),UPPER(B94),RIGHT(UPPER(B94),LEN(UPPER(B94))-FIND("~",SUBSTITUTE(UPPER(B94),"X","~",LEN(UPPER(B94))-LEN(SUBSTITUTE(UPPER(B94),"X","")))))),1)-1),IF(ISERROR(FIND("X",UPPER(B94))),UPPER(B94),RIGHT(UPPER(B94),LEN(UPPER(B94))-FIND("~",SUBSTITUTE(UPPER(B94),"X","~",LEN(UPPER(B94))-LEN(SUBSTITUTE(UPPER(B94),"X",""))))))),".")>=5,"Wall",""),""),"") | M94: {=_xlfn.IFS(NOT(ISERROR(VLOOKUP(Table5[[#This Row],[Section]],TB_notTB,1,FALSE))),"No",LEFT(Table5[[#This Row],[Section]],3)="ETB","PLS",LEFT(Table5[[#This Row],[Section]],1)="7","PDB",NOT(ISBLANK(Table5[[#This Row],[Section]])),"No")} -> PDB
A95: 735681 | B95: C9181U U-MAX BIFOLD WEATHERED SILL-SLOT | C95: N | D95: 1.691 | E95: 500 | F95: 500 | G95: AE3595 | H95: 100012122131221010 | I95: EDGE MAX 50mm Bifold Door | J95: BU | K95: =_xlfn.IFNA(VLOOKUP(Table5[[#This Row],[Section]],SubSill_Tier,2,FALSE),0) -> 0 | L95: =IFERROR(IF(LEFT(G95,2)="AI",IF(_xlfn.NUMBERVALUE(IFERROR(LEFT(IF(ISERROR(FIND("X",UPPER(B95))),UPPER(B95),RIGHT(UPPER(B95),LEN(UPPER(B95))-FIND("~",SUBSTITUTE(UPPER(B95),"X","~",LEN(UPPER(B95))-LEN(SUBSTITUTE(UPPER(B95),"X","")))))),FIND(" ",IF(ISERROR(FIND("X",UPPER(B95))),UPPER(B95),RIGHT(UPPER(B95),LEN(UPPER(B95))-FIND("~",SUBSTITUTE(UPPER(B95),"X","~",LEN(UPPER(B95))-LEN(SUBSTITUTE(UPPER(B95),"X","")))))),1)-1),IF(ISERROR(FIND("X",UPPER(B95))),UPPER(B95),RIGHT(UPPER(B95),LEN(UPPER(B95))-FIND("~",SUBSTITUTE(UPPER(B95),"X","~",LEN(UPPER(B95))-LEN(SUBSTITUTE(UPPER(B95),"X",""))))))),".")>=5,"Wall",""),""),"") | M95: {=_xlfn.IFS(NOT(ISERROR(VLOOKUP(Table5[[#This Row],[Section]],TB_notTB,1,FALSE))),"No",LEFT(Table5[[#This Row],[Section]],3)="ETB","PLS",LEFT(Table5[[#This Row],[Section]],1)="7","PDB",NOT(ISBLANK(Table5[[#This Row],[Section]])),"No")} -> PDB
... A552: 737980 | B552: EXC SUB-HEAD/SUB-JAMB - 6" WALL | C552: Y | D552: 2.977 | E552: 763 | F552: 509 | G552: AE3710 | H552: 100012122331223004 | I552: EDGE U-MAX Sub Framing | J552: BU | K552: =_xlfn.IFNA(VLOOKUP(Table5[[#This Row],[Section]],SubSill_Tier,2,FALSE),0) -> 0 | L552: =IFERROR(IF(LEFT(G552,2)="AI",IF(_xlfn.NUMBERVALUE(IFERROR(LEFT(IF(ISERROR(FIND("X",UPPER(B552))),UPPER(B552),RIGHT(UPPER(B552),LEN(UPPER(B552))-FIND("~",SUBSTITUTE(UPPER(B552),"X","~",LEN(UPPER(B552))-LEN(SUBSTITUTE(UPPER(B552),"X","")))))),FIND(" ",IF(ISERROR(FIND("X",UPPER(B552))),UPPER(B552),RIGHT(UPPER(B552),LEN(UPPER(B552))-FIND("~",SUBSTITUTE(UPPER(B552),"X","~",LEN(UPPER(B552))-LEN(SUBSTITUTE(UPPER(B552),"X","")))))),1)-1),IF(ISERROR(FIND("X",UPPER(B552))),UPPER(B552),RIGHT(UPPER(B552),LEN(UPPER(B552))-FIND("~",SUBSTITUTE(UPPER(B552),"X","~",LEN(UPPER(B552))-LEN(SUBSTITUTE(UPPER(B552),"X",""))))))),".")>=5,"Wall",""),""),"") | M552: {=_xlfn.IFS(NOT(ISERROR(VLOOKUP(Table5[[#This Row],[Section]],TB_notTB,1,FALSE))),"No",LEFT(Table5[[#This Row],[Section]],3)="ETB","PLS",LEFT(Table5[[#This Row],[Section]],1)="7","PDB",NOT(ISBLANK(Table5[[#This Row],[Section]])),"No")} -> PDB
A553: E00104 | C553: N | D553: 1.067 | E553: 308 | F553: 308 | G553: AE1230 | H553: 100012120031200020 | I553: AGS443 Awning Window | J553: AB_S9 | K553: =_xlfn.IFNA(VLOOKUP(Table5[[#This Row],[Section]],SubSill_Tier,2,FALSE),0) -> 0 | L553: =IFERROR(IF(LEFT(G553,2)="AI",IF(_xlfn.NUMBERVALUE(IFERROR(LEFT(IF(ISERROR(FIND("X",UPPER(B553))),UPPER(B553),RIGHT(UPPER(B553),LEN(UPPER(B553))-FIND("~",SUBSTITUTE(UPPER(B553),"X","~",LEN(UPPER(B553))-LEN(SUBSTITUTE(UPPER(B553),"X","")))))),FIND(" ",IF(ISERROR(FIND("X",UPPER(B553))),UPPER(B553),RIGHT(UPPER(B553),LEN(UPPER(B553))-FIND("~",SUBSTITUTE(UPPER(B553),"X","~",LEN(UPPER(B553))-LEN(SUBSTITUTE(UPPER(B553),"X","")))))),1)-1),IF(ISERROR(FIND("X",UPPER(B553))),UPPER(B553),RIGHT(UPPER(B553),LEN(UPPER(B553))-FIND("~",SUBSTITUTE(UPPER(B553),"X","~",LEN(UPPER(B553))-LEN(SUBSTITUTE(UPPER(B553),"X",""))))))),".")>=5,"Wall",""),""),"") | M553: {=_xlfn.IFS(NOT(ISERROR(VLOOKUP(Table5[[#This Row],[Section]],TB_notTB,1,FALSE))),"No",LEFT(Table5[[#This Row],[Section]],3)="ETB","PLS",LEFT(Table5[[#This Row],[Section]],1)="7","PDB",NOT(ISBLANK(Table5[[#This Row],[Section]])),"No")} -> No
A554: E00105 | C554: N | D554: 0.356 | E554: 100 | F554: 100 | G554: AE1140 | H554: 100012120031200074 | I554: Glazing Channels & Adaptors | J554: AB_S9 | K554: =_xlfn.IFNA(VLOOKUP(Table5[[#This Row],[Section]],SubSill_Tier,2,FALSE),0) -> 0 | L554: =IFERROR(IF(LEFT(G554,2)="AI",IF(_xlfn.NUMBERVALUE(IFERROR(LEFT(IF(ISERROR(FIND("X",UPPER(B554))),UPPER(B554),RIGHT(UPPER(B554),LEN(UPPER(B554))-FIND("~",SUBSTITUTE(UPPER(B554),"X","~",LEN(UPPER(B554))-LEN(SUBSTITUTE(UPPER(B554),"X","")))))),FIND(" ",IF(ISERROR(FIND("X",UPPER(B554))),UPPER(B554),RIGHT(UPPER(B554),LEN(UPPER(B554))-FIND("~",SUBSTITUTE(UPPER(B554),"X","~",LEN(UPPER(B554))-LEN(SUBSTITUTE(UPPER(B554),"X","")))))),1)-1),IF(ISERROR(FIND("X",UPPER(B554))),UPPER(B554),RIGHT(UPPER(B554),LEN(UPPER(B554))-FIND("~",SUBSTITUTE(UPPER(B554),"X","~",LEN(UPPER(B554))-LEN(SUBSTITUTE(UPPER(B554),"X",""))))))),".")>=5,"Wall",""),""),"") | M554: {=_xlfn.IFS(NOT(ISERROR(VLOOKUP(Table5[[#This Row],[Section]],TB_notTB,1,FALSE))),"No",LEFT(Table5[[#This Row],[Section]],3)="ETB","PLS",LEFT(Table5[[#This Row],[Section]],1)="7","PDB",NOT(ISBLANK(Table5[[#This Row],[Section]])),"No")} -> No
A555: E00110 | C555: N | D555: 1.274 | E555: 293 | F555: 293 | G555: AE1230 | H555: 100012120031200020 | I555: AGS443 Awning Window | J555: AB_S9 | K555: =_xlfn.IFNA(VLOOKUP(Table5[[#This Row],[Section]],SubSill_Tier,2,FALSE),0) -> 0 | L555: =IFERROR(IF(LEFT(G555,2)="AI",IF(_xlfn.NUMBERVALUE(IFERROR(LEFT(IF(ISERROR(FIND("X",UPPER(B555))),UPPER(B555),RIGHT(UPPER(B555),LEN(UPPER(B555))-FIND("~",SUBSTITUTE(UPPER(B555),"X","~",LEN(UPPER(B555))-LEN(SUBSTITUTE(UPPER(B555),"X","")))))),FIND(" ",IF(ISERROR(FIND("X",UPPER(B555))),UPPER(B555),RIGHT(UPPER(B555),LEN(UPPER(B555))-FIND("~",SUBSTITUTE(UPPER(B555),"X","~",LEN(UPPER(B555))-LEN(SUBSTITUTE(UPPER(B555),"X","")))))),1)-1),IF(ISERROR(FIND("X",UPPER(B555))),UPPER(B555),RIGHT(UPPER(B555),LEN(UPPER(B555))-FIND("~",SUBSTITUTE(UPPER(B555),"X","~",LEN(UPPER(B555))-LEN(SUBSTITUTE(UPPER(B555),"X",""))))))),".")>=5,"Wall",""),""),"") | M555: {=_xlfn.IFS(NOT(ISERROR(VLOOKUP(Table5[[#This Row],[Section]],TB_notTB,1,FALSE))),"No",LEFT(Table5[[#This Row],[Section]],3)="ETB","PLS",LEFT(Table5[[#This Row],[Section]],1)="7","PDB",NOT(ISBLANK(Table5[[#This Row],[Section]])),"No")} -> No
A556: E00142 | B556: Crescent Mould 19x4.75 | C556: N | D556: 0.143 | E556: 100 | F556: 100 | G556: AI1180 | H556: 100012130031300034 | I556: Moulds & Trims | J556: IO_S3 | K556: =_xlfn.IFNA(VLOOKUP(Table5[[#This Row],[Section]],SubSill_Tier,2,FALSE),0) -> 0 | L556: =IFERROR(IF(LEFT(G556,2)="AI",IF(_xlfn.NUMBERVALUE(IFERROR(LEFT(IF(ISERROR(FIND("X",UPPER(B556))),UPPER(B556),RIGHT(UPPER(B556),LEN(UPPER(B556))-FIND("~",SUBSTITUTE(UPPER(B556),"X","~",LEN(UPPER(B556))-LEN(SUBSTITUTE(UPPER(B556),"X","")))))),FIND(" ",IF(ISERROR(FIND("X",UPPER(B556))),UPPER(B556),RIGHT(UPPER(B556),LEN(UPPER(B556))-FIND("~",SUBSTITUTE(UPPER(B556),"X","~",LEN(UPPER(B556))-LEN(SUBSTITUTE(UPPER(B556),"X","")))))),1)-1),IF(ISERROR(FIND("X",UPPER(B556))),UPPER(B556),RIGHT(UPPER(B556),LEN(UPPER(B556))-FIND("~",SUBSTITUTE(UPPER(B556),"X","~",LEN(UPPER(B556))-LEN(SUBSTITUTE(UPPER(B556),"X",""))))))),".")>=5,"Wall",""),""),"") | M556: {=_xlfn.IFS(NOT(ISERROR(VLOOKUP(Table5[[#This Row],[Section]],TB_notTB,1,FALSE))),"No",LEFT(Table5[[#This Row],[Section]],3)="ETB","PLS",LEFT(Table5[[#This Row],[Section]],1)="7","PDB",NOT(ISBLANK(Table5[[#This Row],[Section]])),"No")} -> No
A557: E00146 | B557: J-Trim Drip Mould 23.8x12.7 | C557: N | D557: 0.156 | E557: 100 | F557: 100 | G557: AI1180 | H557: 100012130031300034 | I557: Moulds & Trims | J557: IO_S3 | K557: =_xlfn.IFNA(VLOOKUP(Table5[[#This Row],[Section]],SubSill_Tier,2,FALSE),0) -> 0 | L557: =IFERROR(IF(LEFT(G557,2)="AI",IF(_xlfn.NUMBERVALUE(IFERROR(LEFT(IF(ISERROR(FIND("X",UPPER(B557))),UPPER(B557),RIGHT(UPPER(B557),LEN(UPPER(B557))-FIND("~",SUBSTITUTE(UPPER(B557),"X","~",LEN(UPPER(B557))-LEN(SUBSTITUTE(UPPER(B557),"X","")))))),FIND(" ",IF(ISERROR(FIND("X",UPPER(B557))),UPPER(B557),RIGHT(UPPER(B557),LEN(UPPER(B557))-FIND("~",SUBSTITUTE(UPPER(B557),"X","~",LEN(UPPER(B557))-LEN(SUBSTITUTE(UPPER(B557),"X","")))))),1)-1),IF(ISERROR(FIND("X",UPPER(B557))),UPPER(B557),RIGHT(UPPER(B557),LEN(UPPER(B557))-FIND("~",SUBSTITUTE(UPPER(B557),"X","~",LEN(UPPER(B557))-LEN(SUBSTITUTE(UPPER(B557),"X",""))))))),".")>=5,"Wall",""),""),"") -> Wall | M557: {=_xlfn.IFS(NOT(ISERROR(VLOOKUP(Table5[[#This Row],[Section]],TB_notTB,1,FALSE))),"No",LEFT(Table5[[#This Row],[Section]],3)="ETB","PLS",LEFT(Table5[[#This Row],[Section]],1)="7","PDB",NOT(ISBLANK(Table5[[#This Row],[Section]])),"No")} -> No
A558: E00161 | B558: Stair Tread Edge 38.1x4 | C558: N | D558: 0.325 | E558: 100 | F558: 100 | G558: AI1180 | H558: 100012130031300034 | I558: Moulds & Trims | J558: IO_S3 | K558: =_xlfn.IFNA(VLOOKUP(Table5[[#This Row],[Section]],SubSill_Tier,2,FALSE),0) -> 0 | L558: =IFERROR(IF(LEFT(G558,2)="AI",IF(_xlfn.NUMBERVALUE(IFERROR(LEFT(IF(ISERROR(FIND("X",UPPER(B558))),UPPER(B558),RIGHT(UPPER(B558),LEN(UPPER(B558))-FIND("~",SUBSTITUTE(UPPER(B558),"X","~",LEN(UPPER(B558))-LEN(SUBSTITUTE(UPPER(B558),"X","")))))),FIND(" ",IF(ISERROR(FIND("X",UPPER(B558))),UPPER(B558),RIGHT(UPPER(B558),LEN(UPPER(B558))-FIND("~",SUBSTITUTE(UPPER(B558),"X","~",LEN(UPPER(B558))-LEN(SUBSTITUTE(UPPER(B558),"X","")))))),1)-1),IF(ISERROR(FIND("X",UPPER(B558))),UPPER(B558),RIGHT(UPPER(B558),LEN(UPPER(B558))-FIND("~",SUBSTITUTE(UPPER(B558),"X","~",LEN(UPPER(B558))-LEN(SUBSTITUTE(UPPER(B558),"X",""))))))),".")>=5,"Wall",""),""),"") | M558: {=_xlfn.IFS(NOT(ISERROR(VLOOKUP(Table5[[#This Row],[Section]],TB_notTB,1,FALSE))),"No",LEFT(Table5[[#This Row],[Section]],3)="ETB","PLS",LEFT(Table5[[#This Row],[Section]],1)="7","PDB",NOT(ISBLANK(Table5[[#This Row],[Section]])),"No")} -> No
A559: E00172 | C559: N | D559: 0.108 | E559: 100 | F559: 100 | G559: AI1510 | H559: 100012130031300021 | I559: Other Industrial - 1 | J559: AB_S3 | K559: =_xlfn.IFNA(VLOOKUP(Table5[[#This Row],[Section]],SubSill_Tier,2,FALSE),0) -> 0 | L559: =IFERROR(IF(LEFT(G559,2)="AI",IF(_xlfn.NUMBERVALUE(IFERROR(LEFT(IF(ISERROR(FIND("X",UPPER(B559))),UPPER(B559),RIGHT(UPPER(B559),LEN(UPPER(B559))-FIND("~",SUBSTITUTE(UPPER(B559),"X","~",LEN(UPPER(B559))-LEN(SUBSTITUTE(UPPER(B559),"X","")))))),FIND(" ",IF(ISERROR(FIND("X",UPPER(B559))),UPPER(B559),RIGHT(UPPER(B559),LEN(UPPER(B559))-FIND("~",SUBSTITUTE(UPPER(B559),"X","~",LEN(UPPER(B559))-LEN(SUBSTITUTE(UPPER(B559),"X","")))))),1)-1),IF(ISERROR(FIND("X",UPPER(B559))),UPPER(B559),RIGHT(UPPER(B559),LEN(UPPER(B559))-FIND("~",SUBSTITUTE(UPPER(B559),"X","~",LEN(UPPER(B559))-LEN(SUBSTITUTE(UPPER(B559),"X",""))))))),".")>=5,"Wall",""),""),"") | M559: {=_xlfn.IFS(NOT(ISERROR(VLOOKUP(Table5[[#This Row],[Section]],TB_notTB,1,FALSE))),"No",LEFT(Table5[[#This Row],[Section]],3)="ETB","PLS",LEFT(Table5[[#This Row],[Section]],1)="7","PDB",NOT(ISBLANK(Table5[[#This Row],[Section]])),"No")} -> No
A560: E00209 | B560: Flat Bar 12.7x3.2(FR) | C560: N | D560: 0.103 | E560: 100 | F560: 100 | G560: AI1080 | H560: 100012130031300015 | I560: Flat Bar | J560: IG_S1 | K560: =_xlfn.IFNA(VLOOKUP(Table5[[#This Row],[Section]],SubSill_Tier,2,FALSE),0) -> 0 | L560: =IFERROR(IF(LEFT(G560,2)="AI",IF(_xlfn.NUMBERVALUE(IFERROR(LEFT(IF(ISERROR(FIND("X",UPPER(B560))),UPPER(B560),RIGHT(UPPER(B560),LEN(UPPER(B560))-FIND("~",SUBSTITUTE(UPPER(B560),"X","~",LEN(UPPER(B560))-LEN(SUBSTITUTE(UPPER(B560),"X","")))))),FIND(" ",IF(ISERROR(FIND("X",UPPER(B560))),UPPER(B560),RIGHT(UPPER(B560),LEN(UPPER(B560))-FIND("~",SUBSTITUTE(UPPER(B560),"X","~",LEN(UPPER(B560))-LEN(SUBSTITUTE(UPPER(B560),"X","")))))),1)-1),IF(ISERROR(FIND("X",UPPER(B560))),UPPER(B560),RIGHT(UPPER(B560),LEN(UPPER(B560))-FIND("~",SUBSTITUTE(UPPER(B560),"X","~",LEN(UPPER(B560))-LEN(SUBSTITUTE(UPPER(B560),"X",""))))))),".")>=5,"Wall",""),""),"") | M560: {=_xlfn.IFS(NOT(ISERROR(VLOOKUP(Table5[[#This Row],[Section]],TB_notTB,1,FALSE))),"No",LEFT(Table5[[#This Row],[Section]],3)="ETB","PLS",LEFT(Table5[[#This Row],[Section]],1)="7","PDB",NOT(ISBLANK(Table5[[#This Row],[Section]])),"No")} -> No
A561: E00211 | B561: Tube Fluted 25.15x1.5 | C561: N | D561: 0.349 | E561: 100 | F561: 100 | G561: AI1120 | H561: 100012130031300010 | I561: Round Tubes | J561: IG_S1 | K561: =_xlfn.IFNA(VLOOKUP(Table5[[#This Row],[Section]],SubSill_Tier,2,FALSE),0) -> 0 | L561: =IFERROR(IF(LEFT(G561,2)="AI",IF(_xlfn.NUMBERVALUE(IFERROR(LEFT(IF(ISERROR(FIND("X",UPPER(B561))),UPPER(B561),RIGHT(UPPER(B561),LEN(UPPER(B561))-FIND("~",SUBSTITUTE(UPPER(B561),"X","~",LEN(UPPER(B561))-LEN(SUBSTITUTE(UPPER(B561),"X","")))))),FIND(" ",IF(ISERROR(FIND("X",UPPER(B561))),UPPER(B561),RIGHT(UPPER(B561),LEN(UPPER(B561))-FIND("~",SUBSTITUTE(UPPER(B561),"X","~",LEN(UPPER(B561))-LEN(SUBSTITUTE(UPPER(B561),"X","")))))),1)-1),IF(ISERROR(FIND("X",UPPER(B561))),UPPER(B561),RIGHT(UPPER(B561),LEN(UPPER(B561))-FIND("~",SUBSTITUTE(UPPER(B561),"X","~",LEN(UPPER(B561))-LEN(SUBSTITUTE(UPPER(B561),"X",""))))))),".")>=5,"Wall",""),""),"") | M561: {=_xlfn.IFS(NOT(ISERROR(VLOOKUP(Table5[[#This Row],[Section]],TB_notTB,1,FALSE))),"No",LEFT(Table5[[#This Row],[Section]],3)="ETB","PLS",LEFT(Table5[[#This Row],[Section]],1)="7","PDB",NOT(ISBLANK(Table5[[#This Row],[Section]])),"No")} -> No
A562: E00363 | B562: Square Hollow 19x1.6(R1=1.6) | C562: N | D562: 0.291 | E562: 100 | F562: 100 | G562: AI1110 | H562: 100012130031300019 | I562: Square Hollows | J562: IG_S1 | K562: =_xlfn.IFNA(VLOOKUP(Table5[[#This Row],[Section]],SubSill_Tier,2,FALSE),0) -> 0 | L562: =IFERROR(IF(LEFT(G562,2)="AI",IF(_xlfn.NUMBERVALUE(IFERROR(LEFT(IF(ISERROR(FIND("X",UPPER(B562))),UPPER(B562),RIGHT(UPPER(B562),LEN(UPPER(B562))-FIND("~",SUBSTITUTE(UPPER(B562),"X","~",LEN(UPPER(B562))-LEN(SUBSTITUTE(UPPER(B562),"X","")))))),FIND(" ",IF(ISERROR(FIND("X",UPPER(B562))),UPPER(B562),RIGHT(UPPER(B562),LEN(UPPER(B562))-FIND("~",SUBSTITUTE(UPPER(B562),"X","~",LEN(UPPER(B562))-LEN(SUBSTITUTE(UPPER(B562),"X","")))))),1)-1),IF(ISERROR(FIND("X",UPPER(B562))),UPPER(B562),RIGHT(UPPER(B562),LEN(UPPER(B562))-FIND("~",SUBSTITUTE(UPPER(B562),"X","~",LEN(UPPER(B562))-LEN(SUBSTITUTE(UPPER(B562),"X",""))))))),".")>=5,"Wall",""),""),"") | M562: {=_xlfn.IFS(NOT(ISERROR(VLOOKUP(Table5[[#This Row],[Section]],TB_notTB,1,FALSE))),"No",LEFT(Table5[[#This Row],[Section]],3)="ETB","PLS",LEFT(Table5[[#This Row],[Section]],1)="7","PDB",NOT(ISBLANK(Table5[[#This Row],[Section]])),"No")} -> No
A563: E00421 | C563: N | D563: 2.125 | E563: 251 | F563: 251 | G563: AI1070 | H563: 100012130031300016 | I563: Tee Sections | J563: AB_S1 | K563: =_xlfn.IFNA(VLOOKUP(Table5[[#This Row],[Section]],SubSill_Tier,2,FALSE),0) -> 0 | L563: =IFERROR(IF(LEFT(G563,2)="AI",IF(_xlfn.NUMBERVALUE(IFERROR(LEFT(IF(ISERROR(FIND("X",UPPER(B563))),UPPER(B563),RIGHT(UPPER(B563),LEN(UPPER(B563))-FIND("~",SUBSTITUTE(UPPER(B563),"X","~",LEN(UPPER(B563))-LEN(SUBSTITUTE(UPPER(B563),"X","")))))),FIND(" ",IF(ISERROR(FIND("X",UPPER(B563))),UPPER(B563),RIGHT(UPPER(B563),LEN(UPPER(B563))-FIND("~",SUBSTITUTE(UPPER(B563),"X","~",LEN(UPPER(B563))-LEN(SUBSTITUTE(UPPER(B563),"X","")))))),1)-1),IF(ISERROR(FIND("X",UPPER(B563))),UPPER(B563),RIGHT(UPPER(B563),LEN(UPPER(B563))-FIND("~",SUBSTITUTE(UPPER(B563),"X","~",LEN(UPPER(B563))-LEN(SUBSTITUTE(UPPER(B563),"X",""))))))),".")>=5,"Wall",""),""),"") | M563: {=_xlfn.IFS(NOT(ISERROR(VLOOKUP(Table5[[#This Row],[Section]],TB_notTB,1,FALSE))),"No",LEFT(Table5[[#This Row],[Section]],3)="ETB","PLS",LEFT(Table5[[#This Row],[Section]],1)="7","PDB",NOT(ISBLANK(Table5[[#This Row],[Section]])),"No")} -> No
A564: E00456 | C564: N | D564: 0.916 | E564: 153 | F564: 153 | G564: AI1050 | H564: 100012130031300013 | I564: Angles | J564: AB_S1 | K564: =_xlfn.IFNA(VLOOKUP(Table5[[#This Row],[Section]],SubSill_Tier,2,FALSE),0) -> 0 | L564: =IFERROR(IF(LEFT(G564,2)="AI",IF(_xlfn.NUMBERVALUE(IFERROR(LEFT(IF(ISERROR(FIND("X",UPPER(B564))),UPPER(B564),RIGHT(UPPER(B564),LEN(UPPER(B564))-FIND("~",SUBSTITUTE(UPPER(B564),"X","~",LEN(UPPER(B564))-LEN(SUBSTITUTE(UPPER(B564),"X","")))))),FIND(" ",IF(ISERROR(FIND("X",UPPER(B564))),UPPER(B564),RIGHT(UPPER(B564),LEN(UPPER(B564))-FIND("~",SUBSTITUTE(UPPER(B564),"X","~",LEN(UPPER(B564))-LEN(SUBSTITUTE(UPPER(B564),"X","")))))),1)-1),IF(ISERROR(FIND("X",UPPER(B564))),UPPER(B564),RIGHT(UPPER(B564),LEN(UPPER(B564))-FIND("~",SUBSTITUTE(UPPER(B564),"X","~",LEN(UPPER(B564))-LEN(SUBSTITUTE(UPPER(B564),"X",""))))))),".")>=5,"Wall",""),""),"") | M564: {=_xlfn.IFS(NOT(ISERROR(VLOOKUP(Table5[[#This Row],[Section]],TB_notTB,1,FALSE))),"No",LEFT(Table5[[#This Row],[Section]],3)="ETB","PLS",LEFT(Table5[[#This Row],[Section]],1)="7","PDB",NOT(ISBLANK(Table5[[#This Row],[Section]])),"No")} -> No
A565: E00470 | B565: Stair Tread Bull Nose 46X15.1 | C565: N | D565: 0.433 | E565: 122 | F565: 100 | G565: AI1180 | H565: 100012130031300034 | I565: Moulds & Trims | J565: IO_S3 | K565: =_xlfn.IFNA(VLOOKUP(Table5[[#This Row],[Section]],SubSill_Tier,2,FALSE),0) -> 0 | L565: =IFERROR(IF(LEFT(G565,2)="AI",IF(_xlfn.NUMBERVALUE(IFERROR(LEFT(IF(ISERROR(FIND("X",UPPER(B565))),UPPER(B565),RIGHT(UPPER(B565),LEN(UPPER(B565))-FIND("~",SUBSTITUTE(UPPER(B565),"X","~",LEN(UPPER(B565))-LEN(SUBSTITUTE(UPPER(B565),"X","")))))),FIND(" ",IF(ISERROR(FIND("X",UPPER(B565))),UPPER(B565),RIGHT(UPPER(B565),LEN(UPPER(B565))-FIND("~",SUBSTITUTE(UPPER(B565),"X","~",LEN(UPPER(B565))-LEN(SUBSTITUTE(UPPER(B565),"X","")))))),1)-1),IF(ISERROR(FIND("X",UPPER(B565))),UPPER(B565),RIGHT(UPPER(B565),LEN(UPPER(B565))-FIND("~",SUBSTITUTE(UPPER(B565),"X","~",LEN(UPPER(B565))-LEN(SUBSTITUTE(UPPER(B565),"X",""))))))),".")>=5,"Wall",""),""),"") -> Wall | M565: {=_xlfn.IFS(NOT(ISERROR(VLOOKUP(Table5[[#This Row],[Section]],TB_notTB,1,FALSE))),"No",LEFT(Table5[[#This Row],[Section]],3)="ETB","PLS",LEFT(Table5[[#This Row],[Section]],1)="7","PDB",NOT(ISBLANK(Table5[[#This Row],[Section]])),"No")} -> No
A566: E00551 | B566: Channel 31.75x25.4x3.2 | C566: N | D566: 0.657 | E566: 159 | F566: 159 | G566: AI1060 | H566: 100012130031300014 | I566: Channels | J566: AB_S1 | K566: =_xlfn.IFNA(VLOOKUP(Table5[[#This Row],[Section]],SubSill_Tier,2,FALSE),0) -> 0 | L566: =IFERROR(IF(LEFT(G566,2)="AI",IF(_xlfn.NUMBERVALUE(IFERROR(LEFT(IF(ISERROR(FIND("X",UPPER(B566))),UPPER(B566),RIGHT(UPPER(B566),LEN(UPPER(B566))-FIND("~",SUBSTITUTE(UPPER(B566),"X","~",LEN(UPPER(B566))-LEN(SUBSTITUTE(UPPER(B566),"X","")))))),FIND(" ",IF(ISERROR(FIND("X",UPPER(B566))),UPPER(B566),RIGHT(UPPER(B566),LEN(UPPER(B566))-FIND("~",SUBSTITUTE(UPPER(B566),"X","~",LEN(UPPER(B566))-LEN(SUBSTITUTE(UPPER(B566),"X","")))))),1)-1),IF(ISERROR(FIND("X",UPPER(B566))),UPPER(B566),RIGHT(UPPER(B566),LEN(UPPER(B566))-FIND("~",SUBSTITUTE(UPPER(B566),"X","~",LEN(UPPER(B566))-LEN(SUBSTITUTE(UPPER(B566),"X",""))))))),".")>=5,"Wall",""),""),"") | M566: {=_xlfn.IFS(NOT(ISERROR(VLOOKUP(Table5[[#This Row],[Section]],TB_notTB,1,FALSE))),"No",LEFT(Table5[[#This Row],[Section]],3)="ETB","PLS",LEFT(Table5[[#This Row],[Section]],1)="7","PDB",NOT(ISBLANK(Table5[[#This Row],[Section]])),"No")} -> No
A567: E00642 | C567: N | D567: 0.639 | E567: 296 | F567: 296 | G567: AI1290 | H567: 100012130031300021 | I567: Other Industrial - 1 | J567: AB_S3 | K567: =_xlfn.IFNA(VLOOKUP(Table5[[#This Row],[Section]],SubSill_Tier,2,FALSE),0) -> 0 | L567: =IFERROR(IF(LEFT(G567,2)="AI",IF(_xlfn.NUMBERVALUE(IFERROR(LEFT(IF(ISERROR(FIND("X",UPPER(B567))),UPPER(B567),RIGHT(UPPER(B567),LEN(UPPER(B567))-FIND("~",SUBSTITUTE(UPPER(B567),"X","~",LEN(UPPER(B567))-LEN(SUBSTITUTE(UPPER(B567),"X","")))))),FIND(" ",IF(ISERROR(FIND("X",UPPER(B567))),UPPER(B567),RIGHT(UPPER(B567),LEN(UPPER(B567))-FIND("~",SUBSTITUTE(UPPER(B567),"X","~",LEN(UPPER(B567))-LEN(SUBSTITUTE(UPPER(B567),"X","")))))),1)-1),IF(ISERROR(FIND("X",UPPER(B567))),UPPER(B567),RIGHT(UPPER(B567),LEN(UPPER(B567))-FIND("~",SUBSTITUTE(UPPER(B567),"X","~",LEN(UPPER(B567))-LEN(SUBSTITUTE(UPPER(B567),"X",""))))))),".")>=5,"Wall",""),""),"") | M567: {=_xlfn.IFS(NOT(ISERROR(VLOOKUP(Table5[[#This Row],[Section]],TB_notTB,1,FALSE))),"No",LEFT(Table5[[#This Row],[Section]],3)="ETB","PLS",LEFT(Table5[[#This Row],[Section]],1)="7","PDB",NOT(ISBLANK(Table5[[#This Row],[Section]])),"No")} -> No
A568: E00645 | C568: N | D568: 2.73 | E568: 286 | F568: 286 | G568: AI1060 | H568: 100012130031300014 | I568: Channels | J568: AB_S1 | K568: =_xlfn.IFNA(VLOOKUP(Table5[[#This Row],[Section]],SubSill_Tier,2,FALSE),0) -> 0 | L568: =IFERROR(IF(LEFT(G568,2)="AI",IF(_xlfn.NUMBERVALUE(IFERROR(LEFT(IF(ISERROR(FIND("X",UPPER(B568))),UPPER(B568),RIGHT(UPPER(B568),LEN(UPPER(B568))-FIND("~",SUBSTITUTE(UPPER(B568),"X","~",LEN(UPPER(B568))-LEN(SUBSTITUTE(UPPER(B568),"X","")))))),FIND(" ",IF(ISERROR(FIND("X",UPPER(B568))),UPPER(B568),RIGHT(UPPER(B568),LEN(UPPER(B568))-FIND("~",SUBSTITUTE(UPPER(B568),"X","~",LEN(UPPER(B568))-LEN(SUBSTITUTE(UPPER(B568),"X","")))))),1)-1),IF(ISERROR(FIND("X",UPPER(B568))),UPPER(B568),RIGHT(UPPER(B568),LEN(UPPER(B568))-FIND("~",SUBSTITUTE(UPPER(B568),"X","~",LEN(UPPER(B568))-LEN(SUBSTITUTE(UPPER(B568),"X",""))))))),".")>=5,"Wall",""),""),"") | M568: {=_xlfn.IFS(NOT(ISERROR(VLOOKUP(Table5[[#This Row],[Section]],TB_notTB,1,FALSE))),"No",LEFT(Table5[[#This Row],[Section]],3)="ETB","PLS",LEFT(Table5[[#This Row],[Section]],1)="7","PDB",NOT(ISBLANK(Table5[[#This Row],[Section]])),"No")} -> No
A569: E00741 | B569: Tophat 65x25.4x2.4 | C569: N | D569: 0.743 | E569: 221 | F569: 221 | G569: AI1290 | H569: 100012130031300021 | I569: Other Industrial - 1 | J569: AB_S3 | K569: =_xlfn.IFNA(VLOOKUP(Table5[[#This Row],[Section]],SubSill_Tier,2,FALSE),0) -> 0 | L569: =IFERROR(IF(LEFT(G569,2)="AI",IF(_xlfn.NUMBERVALUE(IFERROR(LEFT(IF(ISERROR(FIND("X",UPPER(B569))),UPPER(B569),RIGHT(UPPER(B569),LEN(UPPER(B569))-FIND("~",SUBSTITUTE(UPPER(B569),"X","~",LEN(UPPER(B569))-LEN(SUBSTITUTE(UPPER(B569),"X","")))))),FIND(" ",IF(ISERROR(FIND("X",UPPER(B569))),UPPER(B569),RIGHT(UPPER(B569),LEN(UPPER(B569))-FIND("~",SUBSTITUTE(UPPER(B569),"X","~",LEN(UPPER(B569))-LEN(SUBSTITUTE(UPPER(B569),"X","")))))),1)-1),IF(ISERROR(FIND("X",UPPER(B569))),UPPER(B569),RIGHT(UPPER(B569),LEN(UPPER(B569))-FIND("~",SUBSTITUTE(UPPER(B569),"X","~",LEN(UPPER(B569))-LEN(SUBSTITUTE(UPPER(B569),"X",""))))))),".")>=5,"Wall",""),""),"") | M569: {=_xlfn.IFS(NOT(ISERROR(VLOOKUP(Table5[[#This Row],[Section]],TB_notTB,1,FALSE))),"No",LEFT(Table5[[#This Row],[Section]],3)="ETB","PLS",LEFT(Table5[[#This Row],[Section]],1)="7","PDB",NOT(ISBLANK(Table5[[#This Row],[Section]])),"No")} -> No
A570: E00748 | C570: N | D570: 2.568 | E570: 251 | F570: 251 | G570: AI1050 | H570: 100012130031300013 | I570: Angles | J570: AB_S1 | K570: =_xlfn.IFNA(VLOOKUP(Table5[[#This Row],[Section]],SubSill_Tier,2,FALSE),0) -> 0 | L570: =IFERROR(IF(LEFT(G570,2)="AI",IF(_xlfn.NUMBERVALUE(IFERROR(LEFT(IF(ISERROR(FIND("X",UPPER(B570))),UPPER(B570),RIGHT(UPPER(B570),LEN(UPPER(B570))-FIND("~",SUBSTITUTE(UPPER(B570),"X","~",LEN(UPPER(B570))-LEN(SUBSTITUTE(UPPER(B570),"X","")))))),FIND(" ",IF(ISERROR(FIND("X",UPPER(B570))),UPPER(B570),RIGHT(UPPER(B570),LEN(UPPER(B570))-FIND("~",SUBSTITUTE(UPPER(B570),"X","~",LEN(UPPER(B570))-LEN(SUBSTITUTE(UPPER(B570),"X","")))))),1)-1),IF(ISERROR(FIND("X",UPPER(B570))),UPPER(B570),RIGHT(UPPER(B570),LEN(UPPER(B570))-FIND("~",SUBSTITUTE(UPPER(B570),"X","~",LEN(UPPER(B570))-LEN(SUBSTITUTE(UPPER(B570),"X",""))))))),".")>=5,"Wall",""),""),"") | M570: {=_xlfn.IFS(NOT(ISERROR(VLOOKUP(Table5[[#This Row],[Section]],TB_notTB,1,FALSE))),"No",LEFT(Table5[[#This Row],[Section]],3)="ETB","PLS",LEFT(Table5[[#This Row],[Section]],1)="7","PDB",NOT(ISBLANK(Table5[[#This Row],[Section]])),"No")} -> No
A571: E00751 | B571: ZED 25.40 x19 x19x2.4 | C571: N | D571: 0.385 | E571: 120 | F571: 120 | G571: AI1170 | H571: 100012130031300021 | I571: Other Industrial - 1 | J571: AB_S3 | K571: =_xlfn.IFNA(VLOOKUP(Table5[[#This Row],[Section]],SubSill_Tier,2,FALSE),0) -> 0 | L571: =IFERROR(IF(LEFT(G571,2)="AI",IF(_xlfn.NUMBERVALUE(IFERROR(LEFT(IF(ISERROR(FIND("X",UPPER(B571))),UPPER(B571),RIGHT(UPPER(B571),LEN(UPPER(B571))-FIND("~",SUBSTITUTE(UPPER(B571),"X","~",LEN(UPPER(B571))-LEN(SUBSTITUTE(UPPER(B571),"X","")))))),FIND(" ",IF(ISERROR(FIND("X",UPPER(B571))),UPPER(B571),RIGHT(UPPER(B571),LEN(UPPER(B571))-FIND("~",SUBSTITUTE(UPPER(B571),"X","~",LEN(UPPER(B571))-LEN(SUBSTITUTE(UPPER(B571),"X","")))))),1)-1),IF(ISERROR(FIND("X",UPPER(B571))),UPPER(B571),RIGHT(UPPER(B571),LEN(UPPER(B571))-FIND("~",SUBSTITUTE(UPPER(B571),"X","~",LEN(UPPER(B571))-LEN(SUBSTITUTE(UPPER(B571),"X",""))))))),".")>=5,"Wall",""),""),"") | M571: {=_xlfn.IFS(NOT(ISERROR(VLOOKUP(Table5[[#This Row],[Section]],TB_notTB,1,FALSE))),"No",LEFT(Table5[[#This Row],[Section]],3)="ETB","PLS",LEFT(Table5[[#This Row],[Section]],1)="7","PDB",NOT(ISBLANK(Table5[[#This Row],[Section]])),"No")} -> No
A572: E00752 | B572: Zed 25.4x31.75x25.4x3.2 Rad | C572: N | D572: 0.667 | E572: 156 | F572: 156 | G572: AI1180 | H572: 100012130031300034 | I572: Moulds & Trims | J572: IO_S3 | K572: =_xlfn.IFNA(VLOOKUP(Table5[[#This Row],[Section]],SubSill_Tier,2,FALSE),0) -> 0 | L572: =IFERROR(IF(LEFT(G572,2)="AI",IF(_xlfn.NUMBERVALUE(IFERROR(LEFT(IF(ISERROR(FIND("X",UPPER(B572))),UPPER(B572),RIGHT(UPPER(B572),LEN(UPPER(B572))-FIND("~",SUBSTITUTE(UPPER(B572),"X","~",LEN(UPPER(B572))-LEN(SUBSTITUTE(UPPER(B572),"X","")))))),FIND(" ",IF(ISERROR(FIND("X",UPPER(B572))),UPPER(B572),RIGHT(UPPER(B572),LEN(UPPER(B572))-FIND("~",SUBSTITUTE(UPPER(B572),"X","~",LEN(UPPER(B572))-LEN(SUBSTITUTE(UPPER(B572),"X","")))))),1)-1),IF(ISERROR(FIND("X",UPPER(B572))),UPPER(B572),RIGHT(UPPER(B572),LEN(UPPER(B572))-FIND("~",SUBSTITUTE(UPPER(B572),"X","~",LEN(UPPER(B572))-LEN(SUBSTITUTE(UPPER(B572),"X",""))))))),".")>=5,"Wall",""),""),"") | M572: {=_xlfn.IFS(NOT(ISERROR(VLOOKUP(Table5[[#This Row],[Section]],TB_notTB,1,FALSE))),"No",LEFT(Table5[[#This Row],[Section]],3)="ETB","PLS",LEFT(Table5[[#This Row],[Section]],1)="7","PDB",NOT(ISBLANK(Table5[[#This Row],[Section]])),"No")} -> No
A573: E00793 | B573: I Beam 88.9x38.1x4.75x6.35(R1=6.35) | C573: N | D573: 2.376 | E573: 310 | F573: 310 | G573: AI1530 | H573: 100012130031300033 | I573: I Beams | J573: IO_S3 | K573: =_xlfn.IFNA(VLOOKUP(Table5[[#This Row],[Section]],SubSill_Tier,2,FALSE),0) -> 0 | L573: =IFERROR(IF(LEFT(G573,2)="AI",IF(_xlfn.NUMBERVALUE(IFERROR(LEFT(IF(ISERROR(FIND("X",UPPER(B573))),UPPER(B573),RIGHT(UPPER(B573),LEN(UPPER(B573))-FIND("~",SUBSTITUTE(UPPER(B573),"X","~",LEN(UPPER(B573))-LEN(SUBSTITUTE(UPPER(B573),"X","")))))),FIND(" ",IF(ISERROR(FIND("X",UPPER(B573))),UPPER(B573),RIGHT(UPPER(B573),LEN(UPPER(B573))-FIND("~",SUBSTITUTE(UPPER(B573),"X","~",LEN(UPPER(B573))-LEN(SUBSTITUTE(UPPER(B573),"X","")))))),1)-1),IF(ISERROR(FIND("X",UPPER(B573))),UPPER(B573),RIGHT(UPPER(B573),LEN(UPPER(B573))-FIND("~",SUBSTITUTE(UPPER(B573),"X","~",LEN(UPPER(B573))-LEN(SUBSTITUTE(UPPER(B573),"X",""))))))),".")>=5,"Wall",""),""),"") | M573: {=_xlfn.IFS(NOT(ISERROR(VLOOKUP(Table5[[#This Row],[Section]],TB_notTB,1,FALSE))),"No",LEFT(Table5[[#This Row],[Section]],3)="ETB","PLS",LEFT(Table5[[#This Row],[Section]],1)="7","PDB",NOT(ISBLANK(Table5[[#This Row],[Section]])),"No")} -> No
A574: E00798 | B574: I Beam 127x50.8x4.75x6.53(R1=7) | C574: N | D574: 3.322 | E574: 436 | F574: 436 | G574: AI1530 | H574: 100012130031300033 | I574: I Beams | J574: IO_S4 | K574: =_xlfn.IFNA(VLOOKUP(Table5[[#This Row],[Section]],SubSill_Tier,2,FALSE),0) -> 0 | L574: =IFERROR(IF(LEFT(G574,2)="AI",IF(_xlfn.NUMBERVALUE(IFERROR(LEFT(IF(ISERROR(FIND("X",UPPER(B574))),UPPER(B574),RIGHT(UPPER(B574),LEN(UPPER(B574))-FIND("~",SUBSTITUTE(UPPER(B574),"X","~",LEN(UPPER(B574))-LEN(SUBSTITUTE(UPPER(B574),"X","")))))),FIND(" ",IF(ISERROR(FIND("X",UPPER(B574))),UPPER(B574),RIGHT(UPPER(B574),LEN(UPPER(B574))-FIND("~",SUBSTITUTE(UPPER(B574),"X","~",LEN(UPPER(B574))-LEN(SUBSTITUTE(UPPER(B574),"X","")))))),1)-1),IF(ISERROR(FIND("X",UPPER(B574))),UPPER(B574),RIGHT(UPPER(B574),LEN(UPPER(B574))-FIND("~",SUBSTITUTE(UPPER(B574),"X","~",LEN(UPPER(B574))-LEN(SUBSTITUTE(UPPER(B574),"X",""))))))),".")>=5,"Wall",""),""),"") | M574: {=_xlfn.IFS(NOT(ISERROR(VLOOKUP(Table5[[#This Row],[Section]],TB_notTB,1,FALSE))),"No",LEFT(Table5[[#This Row],[Section]],3)="ETB","PLS",LEFT(Table5[[#This Row],[Section]],1)="7","PDB",NOT(ISBLANK(Table5[[#This Row],[Section]])),"No")} -> No
A575: E00801 | B575: Tee 76.2x76.2x6.35(R1=7.6) | C575: N | D575: 2.57 | E575: 297 | F575: 297 | G575: AI1070 | H575: 100012130031300016 | I575: Tee Sections | J575: IG_S1 | K575: =_xlfn.IFNA(VLOOKUP(Table5[[#This Row],[Section]],SubSill_Tier,2,FALSE),0) -> 0 | L575: =IFERROR(IF(LEFT(G575,2)="AI",IF(_xlfn.NUMBERVALUE(IFERROR(LEFT(IF(ISERROR(FIND("X",UPPER(B575))),UPPER(B575),RIGHT(UPPER(B575),LEN(UPPER(B575))-FIND("~",SUBSTITUTE(UPPER(B575),"X","~",LEN(UPPER(B575))-LEN(SUBSTITUTE(UPPER(B575),"X","")))))),FIND(" ",IF(ISERROR(FIND("X",UPPER(B575))),UPPER(B575),RIGHT(UPPER(B575),LEN(UPPER(B575))-FIND("~",SUBSTITUTE(UPPER(B575),"X","~",LEN(UPPER(B575))-LEN(SUBSTITUTE(UPPER(B575),"X","")))))),1)-1),IF(ISERROR(FIND("X",UPPER(B575))),UPPER(B575),RIGHT(UPPER(B575),LEN(UPPER(B575))-FIND("~",SUBSTITUTE(UPPER(B575),"X","~",LEN(UPPER(B575))-LEN(SUBSTITUTE(UPPER(B575),"X",""))))))),".")>=5,"Wall",""),""),"") | M575: {=_xlfn.IFS(NOT(ISERROR(VLOOKUP(Table5[[#This Row],[Section]],TB_notTB,1,FALSE))),"No",LEFT(Table5[[#This Row],[Section]],3)="ETB","PLS",LEFT(Table5[[#This Row],[Section]],1)="7","PDB",NOT(ISBLANK(Table5[[#This Row],[Section]])),"No")} -> No
A576: E00804 | C576: N | D576: 3.02 | E576: 348 | F576: 348 | G576: AI1070 | H576: 100012130031300016 | I576: Tee Sections | J576: AB_S2 | K576: =_xlfn.IFNA(VLOOKUP(Table5[[#This Row],[Section]],SubSill_Tier,2,FALSE),0) -> 0 | L576: =IFERROR(IF(LEFT(G576,2)="AI",IF(_xlfn.NUMBERVALUE(IFERROR(LEFT(IF(ISERROR(FIND("X",UPPER(B576))),UPPER(B576),RIGHT(UPPER(B576),LEN(UPPER(B576))-FIND("~",SUBSTITUTE(UPPER(B576),"X","~",LEN(UPPER(B576))-LEN(SUBSTITUTE(UPPER(B576),"X","")))))),FIND(" ",IF(ISERROR(FIND("X",UPPER(B576))),UPPER(B576),RIGHT(UPPER(B576),LEN(UPPER(B576))-FIND("~",SUBSTITUTE(UPPER(B576),"X","~",LEN(UPPER(B576))-LEN(SUBSTITUTE(UPPER(B576),"X","")))))),1)-1),IF(ISERROR(FIND("X",UPPER(B576))),UPPER(B576),RIGHT(UPPER(B576),LEN(UPPER(B576))-FIND("~",SUBSTITUTE(UPPER(B576),"X","~",LEN(UPPER(B576))-LEN(SUBSTITUTE(UPPER(B576),"X",""))))))),".")>=5,"Wall",""),""),"") | M576: {=_xlfn.IFS(NOT(ISERROR(VLOOKUP(Table5[[#This Row],[Section]],TB_notTB,1,FALSE))),"No",LEFT(Table5[[#This Row],[Section]],3)="ETB","PLS",LEFT(Table5[[#This Row],[Section]],1)="7","PDB",NOT(ISBLANK(Table5[[#This Row],[Section]])),"No")} -> No
A577: E00841 | B577: Rub Rail Double 109.5x19x1.6 | C577: N | D577: 0.693 | E577: 325 | F577: 325 | G577: AI1250 | H577: 100012130931309000 | I577: Transport Sections | J577: IO_S3 | K577: =_xlfn.IFNA(VLOOKUP(Table5[[#This Row],[Section]],SubSill_Tier,2,FALSE),0) -> 0 | L577: =IFERROR(IF(LEFT(G577,2)="AI",IF(_xlfn.NUMBERVALUE(IFERROR(LEFT(IF(ISERROR(FIND("X",UPPER(B577))),UPPER(B577),RIGHT(UPPER(B577),LEN(UPPER(B577))-FIND("~",SUBSTITUTE(UPPER(B577),"X","~",LEN(UPPER(B577))-LEN(SUBSTITUTE(UPPER(B577),"X","")))))),FIND(" ",IF(ISERROR(FIND("X",UPPER(B577))),UPPER(B577),RIGHT(UPPER(B577),LEN(UPPER(B577))-FIND("~",SUBSTITUTE(UPPER(B577),"X","~",LEN(UPPER(B577))-LEN(SUBSTITUTE(UPPER(B577),"X","")))))),1)-1),IF(ISERROR(FIND("X",UPPER(B577))),UPPER(B577),RIGHT(UPPER(B577),LEN(UPPER(B577))-FIND("~",SUBSTITUTE(UPPER(B577),"X","~",LEN(UPPER(B577))-LEN(SUBSTITUTE(UPPER(B577),"X",""))))))),".")>=5,"Wall",""),""),"") | M577: {=_xlfn.IFS(NOT(ISERROR(VLOOKUP(Table5[[#This Row],[Section]],TB_notTB,1,FALSE))),"No",LEFT(Table5[[#This Row],[Section]],3)="ETB","PLS",LEFT(Table5[[#This Row],[Section]],1)="7","PDB",NOT(ISBLANK(Table5[[#This Row],[Section]])),"No")} -> No
A578: E00843 | C578: N | D578: 3.266 | E578: 273 | F578: 273 | G578: AI1080 | H578: 100012130031300015 | I578: Flat Bar | J578: AB_S2 | K578: =_xlfn.IFNA(VLOOKUP(Table5[[#This Row],[Section]],SubSill_Tier,2,FALSE),0) -> 0 | L578: =IFERROR(IF(LEFT(G578,2)="AI",IF(_xlfn.NUMBERVALUE(IFERROR(LEFT(IF(ISERROR(FIND("X",UPPER(B578))),UPPER(B578),RIGHT(UPPER(B578),LEN(UPPER(B578))-FIND("~",SUBSTITUTE(UPPER(B578),"X","~",LEN(UPPER(B578))-LEN(SUBSTITUTE(UPPER(B578),"X","")))))),FIND(" ",IF(ISERROR(FIND("X",UPPER(B578))),UPPER(B578),RIGHT(UPPER(B578),LEN(UPPER(B578))-FIND("~",SUBSTITUTE(UPPER(B578),"X","~",LEN(UPPER(B578))-LEN(SUBSTITUTE(UPPER(B578),"X","")))))),1)-1),IF(ISERROR(FIND("X",UPPER(B578))),UPPER(B578),RIGHT(UPPER(B578),LEN(UPPER(B578))-FIND("~",SUBSTITUTE(UPPER(B578),"X","~",LEN(UPPER(B578))-LEN(SUBSTITUTE(UPPER(B578),"X",""))))))),".")>=5,"Wall",""),""),"") | M578: {=_xlfn.IFS(NOT(ISERROR(VLOOKUP(Table5[[#This Row],[Section]],TB_notTB,1,FALSE))),"No",LEFT(Table5[[#This Row],[Section]],3)="ETB","PLS",LEFT(Table5[[#This Row],[Section]],1)="7","PDB",NOT(ISBLANK(Table5[[#This Row],[Section]])),"No")} -> No
A579: E00919 | B579: Flat Bar 114.3x9.55 | C579: N | D579: 2.948 | E579: 248 | F579: 248 | G579: AI1080 | H579: 100012130031300015 | I579: Flat Bar | J579: IG_S1 | K579: =_xlfn.IFNA(VLOOKUP(Table5[[#This Row],[Section]],SubSill_Tier,2,FALSE),0) -> 0 | L579: =IFERROR(IF(LEFT(G579,2)="AI",IF(_xlfn.NUMBERVALUE(IFERROR(LEFT(IF(ISERROR(FIND("X",UPPER(B579))),UPPER(B579),RIGHT(UPPER(B579),LEN(UPPER(B579))-FIND("~",SUBSTITUTE(UPPER(B579),"X","~",LEN(UPPER(B579))-LEN(SUBSTITUTE(UPPER(B579),"X","")))))),FIND(" ",IF(ISERROR(FIND("X",UPPER(B579))),UPPER(B579),RIGHT(UPPER(B579),LEN(UPPER(B579))-FIND("~",SUBSTITUTE(UPPER(B579),"X","~",LEN(UPPER(B579))-LEN(SUBSTITUTE(UPPER(B579),"X","")))))),1)-1),IF(ISERROR(FIND("X",UPPER(B579))),UPPER(B579),RIGHT(UPPER(B579),LEN(UPPER(B579))-FIND("~",SUBSTITUTE(UPPER(B579),"X","~",LEN(UPPER(B579))-LEN(SUBSTITUTE(UPPER(B579),"X",""))))))),".")>=5,"Wall",""),""),"") -> Wall | M579: {=_xlfn.IFS(NOT(ISERROR(VLOOKUP(Table5[[#This Row],[Section]],TB_notTB,1,FALSE))),"No",LEFT(Table5[[#This Row],[Section]],3)="ETB","PLS",LEFT(Table5[[#This Row],[Section]],1)="7","PDB",NOT(ISBLANK(Table5[[#This Row],[Section]])),"No")} -> No
A580: E01000 | B580: Square Solid 25.4 | C580: N | D580: 1.742 | E580: 102 | F580: 102 | G580: AI1100 | H580: 100012130031300017 | I580: Squares Solid | J580: IG_S1 | K580: =_xlfn.IFNA(VLOOKUP(Table5[[#This Row],[Section]],SubSill_Tier,2,FALSE),0) -> 0 | L580: =IFERROR(IF(LEFT(G580,2)="AI",IF(_xlfn.NUMBERVALUE(IFERROR(LEFT(IF(ISERROR(FIND("X",UPPER(B580))),UPPER(B580),RIGHT(UPPER(B580),LEN(UPPER(B580))-FIND("~",SUBSTITUTE(UPPER(B580),"X","~",LEN(UPPER(B580))-LEN(SUBSTITUTE(UPPER(B580),"X","")))))),FIND(" ",IF(ISERROR(FIND("X",UPPER(B580))),UPPER(B580),RIGHT(UPPER(B580),LEN(UPPER(B580))-FIND("~",SUBSTITUTE(UPPER(B580),"X","~",LEN(UPPER(B580))-LEN(SUBSTITUTE(UPPER(B580),"X","")))))),1)-1),IF(ISERROR(FIND("X",UPPER(B580))),UPPER(B580),RIGHT(UPPER(B580),LEN(UPPER(B580))-FIND("~",SUBSTITUTE(UPPER(B580),"X","~",LEN(UPPER(B580))-LEN(SUBSTITUTE(UPPER(B580),"X",""))))))),".")>=5,"Wall",""),""),"") | M580: {=_xlfn.IFS(NOT(ISERROR(VLOOKUP(Table5[[#This Row],[Section]],TB_notTB,1,FALSE))),"No",LEFT(Table5[[#This Row],[Section]],3)="ETB","PLS",LEFT(Table5[[#This Row],[Section]],1)="7","PDB",NOT(ISBLANK(Table5[[#This Row],[Section]])),"No")} -> No
A581: E01007 | B581: Tee 25.4x50.8x4 | C581: N | D581: 0.78 | E581: 152 | F581: 152 | G581: AI1070 | H581: 100012130031300016 | I581: Tee Sections | J581: IG_S1 | K581: =_xlfn.IFNA(VLOOKUP(Table5[[#This Row],[Section]],SubSill_Tier,2,FALSE),0) -> 0 | L581: =IFERROR(IF(LEFT(G581,2)="AI",IF(_xlfn.NUMBERVALUE(IFERROR(LEFT(IF(ISERROR(FIND("X",UPPER(B581))),UPPER(B581),RIGHT(UPPER(B581),LEN(UPPER(B581))-FIND("~",SUBSTITUTE(UPPER(B581),"X","~",LEN(UPPER(B581))-LEN(SUBSTITUTE(UPPER(B581),"X","")))))),FIND(" ",IF(ISERROR(FIND("X",UPPER(B581))),UPPER(B581),RIGHT(UPPER(B581),LEN(UPPER(B581))-FIND("~",SUBSTITUTE(UPPER(B581),"X","~",LEN(UPPER(B581))-LEN(SUBSTITUTE(UPPER(B581),"X","")))))),1)-1),IF(ISERROR(FIND("X",UPPER(B581))),UPPER(B581),RIGHT(UPPER(B581),LEN(UPPER(B581))-FIND("~",SUBSTITUTE(UPPER(B581),"X","~",LEN(UPPER(B581))-LEN(SUBSTITUTE(UPPER(B581),"X",""))))))),".")>=5,"Wall",""),""),"") | M581: {=_xlfn.IFS(NOT(ISERROR(VLOOKUP(Table5[[#This Row],[Section]],TB_notTB,1,FALSE))),"No",LEFT(Table5[[#This Row],[Section]],3)="ETB","PLS",LEFT(Table5[[#This Row],[Section]],1)="7","PDB",NOT(ISBLANK(Table5[[#This Row],[Section]])),"No")} -> No
A582: E01039 | B582: Channel 76.2x25.4x3.2 | C582: N | D582: 1.04 | E582: 247 | F582: 247 | G582: AI1060 | H582: 100012130031300014 | I582: Channels | J582: AB_S1 | K582: =_xlfn.IFNA(VLOOKUP(Table5[[#This Row],[Section]],SubSill_Tier,2,FALSE),0) -> 0 | L582: =IFERROR(IF(LEFT(G582,2)="AI",IF(_xlfn.NUMBERVALUE(IFERROR(LEFT(IF(ISERROR(FIND("X",UPPER(B582))),UPPER(B582),RIGHT(UPPER(B582),LEN(UPPER(B582))-FIND("~",SUBSTITUTE(UPPER(B582),"X","~",LEN(UPPER(B582))-LEN(SUBSTITUTE(UPPER(B582),"X","")))))),FIND(" ",IF(ISERROR(FIND("X",UPPER(B582))),UPPER(B582),RIGHT(UPPER(B582),LEN(UPPER(B582))-FIND("~",SUBSTITUTE(UPPER(B582),"X","~",LEN(UPPER(B582))-LEN(SUBSTITUTE(UPPER(B582),"X","")))))),1)-1),IF(ISERROR(FIND("X",UPPER(B582))),UPPER(B582),RIGHT(UPPER(B582),LEN(UPPER(B582))-FIND("~",SUBSTITUTE(UPPER(B582),"X","~",LEN(UPPER(B582))-LEN(SUBSTITUTE(UPPER(B582),"X",""))))))),".")>=5,"Wall",""),""),"") | M582: {=_xlfn.IFS(NOT(ISERROR(VLOOKUP(Table5[[#This Row],[Section]],TB_notTB,1,FALSE))),"No",LEFT(Table5[[#This Row],[Section]],3)="ETB","PLS",LEFT(Table5[[#This Row],[Section]],1)="7","PDB",NOT(ISBLANK(Table5[[#This Row],[Section]])),"No")} -> No
A583: E01055 | B583: Flat Bar 31.75x12.7 | C583: N | D583: 1.088 | E583: 100 | F583: 100 | G583: AI1080 | H583: 100012130031300015 | I583: Flat Bar | J583: IG_S1 | K583: =_xlfn.IFNA(VLOOKUP(Table5[[#This Row],[Section]],SubSill_Tier,2,FALSE),0) -> 0 | L583: =IFERROR(IF(LEFT(G583,2)="AI",IF(_xlfn.NUMBERVALUE(IFERROR(LEFT(IF(ISERROR(FIND("X",UPPER(B583))),UPPER(B583),RIGHT(UPPER(B583),LEN(UPPER(B583))-FIND("~",SUBSTITUTE(UPPER(B583),"X","~",LEN(UPPER(B583))-LEN(SUBSTITUTE(UPPER(B583),"X","")))))),FIND(" ",IF(ISERROR(FIND("X",UPPER(B583))),UPPER(B583),RIGHT(UPPER(B583),LEN(UPPER(B583))-FIND("~",SUBSTITUTE(UPPER(B583),"X","~",LEN(UPPER(B583))-LEN(SUBSTITUTE(UPPER(B583),"X","")))))),1)-1),IF(ISERROR(FIND("X",UPPER(B583))),UPPER(B583),RIGHT(UPPER(B583),LEN(UPPER(B583))-FIND("~",SUBSTITUTE(UPPER(B583),"X","~",LEN(UPPER(B583))-LEN(SUBSTITUTE(UPPER(B583),"X",""))))))),".")>=5,"Wall",""),""),"") -> Wall | M583: {=_xlfn.IFS(NOT(ISERROR(VLOOKUP(Table5[[#This Row],[Section]],TB_notTB,1,FALSE))),"No",LEFT(Table5[[#This Row],[Section]],3)="ETB","PLS",LEFT(Table5[[#This Row],[Section]],1)="7","PDB",NOT(ISBLANK(Table5[[#This Row],[Section]])),"No")} -> No
A584: E01104 | C584: N | D584: 0.653 | E584: 159 | F584: 159 | G584: AI1510 | H584: 100012130031300021 | I584: Other Industrial - 1 | J584: AB_S3 | K584: =_xlfn.IFNA(VLOOKUP(Table5[[#This Row],[Section]],SubSill_Tier,2,FALSE),0) -> 0 | L584: =IFERROR(IF(LEFT(G584,2)="AI",IF(_xlfn.NUMBERVALUE(IFERROR(LEFT(IF(ISERROR(FIND("X",UPPER(B584))),UPPER(B584),RIGHT(UPPER(B584),LEN(UPPER(B584))-FIND("~",SUBSTITUTE(UPPER(B584),"X","~",LEN(UPPER(B584))-LEN(SUBSTITUTE(UPPER(B584),"X","")))))),FIND(" ",IF(ISERROR(FIND("X",UPPER(B584))),UPPER(B584),RIGHT(UPPER(B584),LEN(UPPER(B584))-FIND("~",SUBSTITUTE(UPPER(B584),"X","~",LEN(UPPER(B584))-LEN(SUBSTITUTE(UPPER(B584),"X","")))))),1)-1),IF(ISERROR(FIND("X",UPPER(B584))),UPPER(B584),RIGHT(UPPER(B584),LEN(UPPER(B584))-FIND("~",SUBSTITUTE(UPPER(B584),"X","~",LEN(UPPER(B584))-LEN(SUBSTITUTE(UPPER(B584),"X",""))))))),".")>=5,"Wall",""),""),"") | M584: {=_xlfn.IFS(NOT(ISERROR(VLOOKUP(Table5[[#This Row],[Section]],TB_notTB,1,FALSE))),"No",LEFT(Table5[[#This Row],[Section]],3)="ETB","PLS",LEFT(Table5[[#This Row],[Section]],1)="7","PDB",NOT(ISBLANK(Table5[[#This Row],[Section]])),"No")} -> No
A585: E01143 | B585: Flat Bar 50.8x7.9 | C585: N | D585: 1.086 | E585: 118 | F585: 118 | G585: AI1080 | H585: 100012130031300015 | I585: Flat Bar | J585: IG_S1 | K585: =_xlfn.IFNA(VLOOKUP(Table5[[#This Row],[Section]],SubSill_Tier,2,FALSE),0) -> 0 | L585: =IFERROR(IF(LEFT(G585,2)="AI",IF(_xlfn.NUMBERVALUE(IFERROR(LEFT(IF(ISERROR(FIND("X",UPPER(B585))),UPPER(B585),RIGHT(UPPER(B585),LEN(UPPER(B585))-FIND("~",SUBSTITUTE(UPPER(B585),"X","~",LEN(UPPER(B585))-LEN(SUBSTITUTE(UPPER(B585),"X","")))))),FIND(" ",IF(ISERROR(FIND("X",UPPER(B585))),UPPER(B585),RIGHT(UPPER(B585),LEN(UPPER(B585))-FIND("~",SUBSTITUTE(UPPER(B585),"X","~",LEN(UPPER(B585))-LEN(SUBSTITUTE(UPPER(B585),"X","")))))),1)-1),IF(ISERROR(FIND("X",UPPER(B585))),UPPER(B585),RIGHT(UPPER(B585),LEN(UPPER(B585))-FIND("~",SUBSTITUTE(UPPER(B585),"X","~",LEN(UPPER(B585))-LEN(SUBSTITUTE(UPPER(B585),"X",""))))))),".")>=5,"Wall",""),""),"") -> Wall | M585: {=_xlfn.IFS(NOT(ISERROR(VLOOKUP(Table5[[#This Row],[Section]],TB_notTB,1,FALSE))),"No",LEFT(Table5[[#This Row],[Section]],3)="ETB","PLS",LEFT(Table5[[#This Row],[Section]],1)="7","PDB",NOT(ISBLANK(Table5[[#This Row],[Section]])),"No")} -> No
A586: E01358 | C586: N | D586: 1.496 | E586: 356 | F586: 356 | G586: AI1050 | H586: 100012130031300013 | I586: Angles | J586: AB_S1 | K586: =_xlfn.IFNA(VLOOKUP(Table5[[#This Row],[Section]],SubSill_Tier,2,FALSE),0) -> 0 | L586: =IFERROR(IF(LEFT(G586,2)="AI",IF(_xlfn.NUMBERVALUE(IFERROR(LEFT(IF(ISERROR(FIND("X",UPPER(B586))),UPPER(B586),RIGHT(UPPER(B586),LEN(UPPER(B586))-FIND("~",SUBSTITUTE(UPPER(B586),"X","~",LEN(UPPER(B586))-LEN(SUBSTITUTE(UPPER(B586),"X","")))))),FIND(" ",IF(ISERROR(FIND("X",UPPER(B586))),UPPER(B586),RIGHT(UPPER(B586),LEN(UPPER(B586))-FIND("~",SUBSTITUTE(UPPER(B586),"X","~",LEN(UPPER(B586))-LEN(SUBSTITUTE(UPPER(B586),"X","")))))),1)-1),IF(ISERROR(FIND("X",UPPER(B586))),UPPER(B586),RIGHT(UPPER(B586),LEN(UPPER(B586))-FIND("~",SUBSTITUTE(UPPER(B586),"X","~",LEN(UPPER(B586))-LEN(SUBSTITUTE(UPPER(B586),"X",""))))))),".")>=5,"Wall",""),""),"") | M586: {=_xlfn.IFS(NOT(ISERROR(VLOOKUP(Table5[[#This Row],[Section]],TB_notTB,1,FALSE))),"No",LEFT(Table5[[#This Row],[Section]],3)="ETB","PLS",LEFT(Table5[[#This Row],[Section]],1)="7","PDB",NOT(ISBLANK(Table5[[#This Row],[Section]])),"No")} -> No
A587: E01365 | C587: N | D587: 0.761 | E587: 178 | F587: 178 | G587: AI1110 | H587: 100012130031300019 | I587: Square Hollows | J587: AB_S1 | K587: =_xlfn.IFNA(VLOOKUP(Table5[[#This Row],[Section]],SubSill_Tier,2,FALSE),0) -> 0 | L587: =IFERROR(IF(LEFT(G587,2)="AI",IF(_xlfn.NUMBERVALUE(IFERROR(LEFT(IF(ISERROR(FIND("X",UPPER(B587))),UPPER(B587),RIGHT(UPPER(B587),LEN(UPPER(B587))-FIND("~",SUBSTITUTE(UPPER(B587),"X","~",LEN(UPPER(B587))-LEN(SUBSTITUTE(UPPER(B587),"X","")))))),FIND(" ",IF(ISERROR(FIND("X",UPPER(B587))),UPPER(B587),RIGHT(UPPER(B587),LEN(UPPER(B587))-FIND("~",SUBSTITUTE(UPPER(B587),"X","~",LEN(UPPER(B587))-LEN(SUBSTITUTE(UPPER(B587),"X","")))))),1)-1),IF(ISERROR(FIND("X",UPPER(B587))),UPPER(B587),RIGHT(UPPER(B587),LEN(UPPER(B587))-FIND("~",SUBSTITUTE(UPPER(B587),"X","~",LEN(UPPER(B587))-LEN(SUBSTITUTE(UPPER(B587),"X",""))))))),".")>=5,"Wall",""),""),"") | M587: {=_xlfn.IFS(NOT(ISERROR(VLOOKUP(Table5[[#This Row],[Section]],TB_notTB,1,FALSE))),"No",LEFT(Table5[[#This Row],[Section]],3)="ETB","PLS",LEFT(Table5[[#This Row],[Section]],1)="7","PDB",NOT(ISBLANK(Table5[[#This Row],[Section]])),"No")} -> No
A588: E01367 | C588: N | D588: 0.292 | E588: 100 | F588: 100 | G588: AI1510 | H588: 100012130031300021 | I588: Other Industrial - 1 | J588: AB_S3 | K588: =_xlfn.IFNA(VLOOKUP(Table5[[#This Row],[Section]],SubSill_Tier,2,FALSE),0) -> 0 | L588: =IFERROR(IF(LEFT(G588,2)="AI",IF(_xlfn.NUMBERVALUE(IFERROR(LEFT(IF(ISERROR(FIND("X",UPPER(B588))),UPPER(B588),RIGHT(UPPER(B588),LEN(UPPER(B588))-FIND("~",SUBSTITUTE(UPPER(B588),"X","~",LEN(UPPER(B588))-LEN(SUBSTITUTE(UPPER(B588),"X","")))))),FIND(" ",IF(ISERROR(FIND("X",UPPER(B588))),UPPER(B588),RIGHT(UPPER(B588),LEN(UPPER(B588))-FIND("~",SUBSTITUTE(UPPER(B588),"X","~",LEN(UPPER(B588))-LEN(SUBSTITUTE(UPPER(B588),"X","")))))),1)-1),IF(ISERROR(FIND("X",UPPER(B588))),UPPER(B588),RIGHT(UPPER(B588),LEN(UPPER(B588))-FIND("~",SUBSTITUTE(UPPER(B588),"X","~",LEN(UPPER(B588))-LEN(SUBSTITUTE(UPPER(B588),"X",""))))))),".")>=5,"Wall",""),""),"") | M588: {=_xlfn.IFS(NOT(ISERROR(VLOOKUP(Table5[[#This Row],[Section]],TB_notTB,1,FALSE))),"No",LEFT(Table5[[#This Row],[Section]],3)="ETB","PLS",LEFT(Table5[[#This Row],[Section]],1)="7","PDB",NOT(ISBLANK(Table5[[#This Row],[Section]])),"No")} -> No
A589: E01384 | B589: RHS 38.1x25.4x2.54(R2=1.57) | C589: N | D589: 0.806 | E589: 127 | F589: 127 | G589: AI1090 | H589: 100012130031300018 | I589: Rectangular Hollows | J589: IG_S1 | K589: =_xlfn.IFNA(VLOOKUP(Table5[[#This Row],[Section]],SubSill_Tier,2,FALSE),0) -> 0 | L589: =IFERROR(IF(LEFT(G589,2)="AI",IF(_xlfn.NUMBERVALUE(IFERROR(LEFT(IF(ISERROR(FIND("X",UPPER(B589))),UPPER(B589),RIGHT(UPPER(B589),LEN(UPPER(B589))-FIND("~",SUBSTITUTE(UPPER(B589),"X","~",LEN(UPPER(B589))-LEN(SUBSTITUTE(UPPER(B589),"X","")))))),FIND(" ",IF(ISERROR(FIND("X",UPPER(B589))),UPPER(B589),RIGHT(UPPER(B589),LEN(UPPER(B589))-FIND("~",SUBSTITUTE(UPPER(B589),"X","~",LEN(UPPER(B589))-LEN(SUBSTITUTE(UPPER(B589),"X","")))))),1)-1),IF(ISERROR(FIND("X",UPPER(B589))),UPPER(B589),RIGHT(UPPER(B589),LEN(UPPER(B589))-FIND("~",SUBSTITUTE(UPPER(B589),"X","~",LEN(UPPER(B589))-LEN(SUBSTITUTE(UPPER(B589),"X",""))))))),".")>=5,"Wall",""),""),"") | M589: {=_xlfn.IFS(NOT(ISERROR(VLOOKUP(Table5[[#This Row],[Section]],TB_notTB,1,FALSE))),"No",LEFT(Table5[[#This Row],[Section]],3)="ETB","PLS",LEFT(Table5[[#This Row],[Section]],1)="7","PDB",NOT(ISBLANK(Table5[[#This Row],[Section]])),"No")} -> No
A590: E01424 | C590: N | D590: 0.103 | E590: 100 | F590: 100 | G590: AE1140 | H590: 100012120031200074 | I590: Glazing Channels & Adaptors | J590: BX_S9 | K590: =_xlfn.IFNA(VLOOKUP(Table5[[#This Row],[Section]],SubSill_Tier,2,FALSE),0) -> 0 | L590: =IFERROR(IF(LEFT(G590,2)="AI",IF(_xlfn.NUMBERVALUE(IFERROR(LEFT(IF(ISERROR(FIND("X",UPPER(B590))),UPPER(B590),RIGHT(UPPER(B590),LEN(UPPER(B590))-FIND("~",SUBSTITUTE(UPPER(B590),"X","~",LEN(UPPER(B590))-LEN(SUBSTITUTE(UPPER(B590),"X","")))))),FIND(" ",IF(ISERROR(FIND("X",UPPER(B590))),UPPER(B590),RIGHT(UPPER(B590),LEN(UPPER(B590))-FIND("~",SUBSTITUTE(UPPER(B590),"X","~",LEN(UPPER(B590))-LEN(SUBSTITUTE(UPPER(B590),"X","")))))),1)-1),IF(ISERROR(FIND("X",UPPER(B590))),UPPER(B590),RIGHT(UPPER(B590),LEN(UPPER(B590))-FIND("~",SUBSTITUTE(UPPER(B590),"X","~",LEN(UPPER(B590))-LEN(SUBSTITUTE(UPPER(B590),"X",""))))))),".")>=5,"Wall",""),""),"") | M590: {=_xlfn.IFS(NOT(ISERROR(VLOOKUP(Table5[[#This Row],[Section]],TB_notTB,1,FALSE))),"No",LEFT(Table5[[#This Row],[Section]],3)="ETB","PLS",LEFT(Table5[[#This Row],[Section]],1)="7","PDB",NOT(ISBLANK(Table5[[#This Row],[Section]])),"No")} -> No
A591: E01434 | C591: N | D591: 0.097 | E591: 100 | F591: 100 | G591: AI1170 | H591: 100012130031300021 | I591: Other Industrial - 1 | J591: AB_S3 | K591: =_xlfn.IFNA(VLOOKUP(Table5[[#This Row],[Section]],SubSill_Tier,2,FALSE),0) -> 0 | L591: =IFERROR(IF(LEFT(G591,2)="AI",IF(_xlfn.NUMBERVALUE(IFERROR(LEFT(IF(ISERROR(FIND("X",UPPER(B591))),UPPER(B591),RIGHT(UPPER(B591),LEN(UPPER(B591))-FIND("~",SUBSTITUTE(UPPER(B591),"X","~",LEN(UPPER(B591))-LEN(SUBSTITUTE(UPPER(B591),"X","")))))),FIND(" ",IF(ISERROR(FIND("X",UPPER(B591))),UPPER(B591),RIGHT(UPPER(B591),LEN(UPPER(B591))-FIND("~",SUBSTITUTE(UPPER(B591),"X","~",LEN(UPPER(B591))-LEN(SUBSTITUTE(UPPER(B591),"X","")))))),1)-1),IF(ISERROR(FIND("X",UPPER(B591))),UPPER(B591),RIGHT(UPPER(B591),LEN(UPPER(B591))-FIND("~",SUBSTITUTE(UPPER(B591),"X","~",LEN(UPPER(B591))-LEN(SUBSTITUTE(UPPER(B591),"X",""))))))),".")>=5,"Wall",""),""),"") | M591: {=_xlfn.IFS(NOT(ISERROR(VLOOKUP(Table5[[#This Row],[Section]],TB_notTB,1,FALSE))),"No",LEFT(Table5[[#This Row],[Section]],3)="ETB","PLS",LEFT(Table5[[#This Row],[Section]],1)="7","PDB",NOT(ISBLANK(Table5[[#This Row],[Section]])),"No")} -> No
A592: E01448 | C592: N | D592: 0.268 | E592: 108 | F592: 108 | G592: AI1060 | H592: 100012130031300014 | I592: Channels | J592: AB_S1 | K592: =_xlfn.IFNA(VLOOKUP(Table5[[#This Row],[Section]],SubSill_Tier,2,FALSE),0) -> 0 | L592: =IFERROR(IF(LEFT(G592,2)="AI",IF(_xlfn.NUMBERVALUE(IFERROR(LEFT(IF(ISERROR(FIND("X",UPPER(B592))),UPPER(B592),RIGHT(UPPER(B592),LEN(UPPER(B592))-FIND("~",SUBSTITUTE(UPPER(B592),"X","~",LEN(UPPER(B592))-LEN(SUBSTITUTE(UPPER(B592),"X","")))))),FIND(" ",IF(ISERROR(FIND("X",UPPER(B592))),UPPER(B592),RIGHT(UPPER(B592),LEN(UPPER(B592))-FIND("~",SUBSTITUTE(UPPER(B592),"X","~",LEN(UPPER(B592))-LEN(SUBSTITUTE(UPPER(B592),"X","")))))),1)-1),IF(ISERROR(FIND("X",UPPER(B592))),UPPER(B592),RIGHT(UPPER(B592),LEN(UPPER(B592))-FIND("~",SUBSTITUTE(UPPER(B592),"X","~",LEN(UPPER(B592))-LEN(SUBSTITUTE(UPPER(B592),"X",""))))))),".")>=5,"Wall",""),""),"") | M592: {=_xlfn.IFS(NOT(ISERROR(VLOOKUP(Table5[[#This Row],[Section]],TB_notTB,1,FALSE))),"No",LEFT(Table5[[#This Row],[Section]],3)="ETB","PLS",LEFT(Table5[[#This Row],[Section]],1)="7","PDB",NOT(ISBLANK(Table5[[#This Row],[Section]])),"No")} -> No
A593: E01450 | B593: Table Edge F | C593: N | D593: 0.085 | E593: 100 | F593: 100 | G593: AI1170 | H593: 100012130031300021 | I593: Other Industrial - 1 | J593: AB_S3 | K593: =_xlfn.IFNA(VLOOKUP(Table5[[#This Row],[Section]],SubSill_Tier,2,FALSE),0) -> 0 | L593: =IFERROR(IF(LEFT(G593,2)="AI",IF(_xlfn.NUMBERVALUE(IFERROR(LEFT(IF(ISERROR(FIND("X",UPPER(B593))),UPPER(B593),RIGHT(UPPER(B593),LEN(UPPER(B593))-FIND("~",SUBSTITUTE(UPPER(B593),"X","~",LEN(UPPER(B593))-LEN(SUBSTITUTE(UPPER(B593),"X","")))))),FIND(" ",IF(ISERROR(FIND("X",UPPER(B593))),UPPER(B593),RIGHT(UPPER(B593),LEN(UPPER(B593))-FIND("~",SUBSTITUTE(UPPER(B593),"X","~",LEN(UPPER(B593))-LEN(SUBSTITUTE(UPPER(B593),"X","")))))),1)-1),IF(ISERROR(FIND("X",UPPER(B593))),UPPER(B593),RIGHT(UPPER(B593),LEN(UPPER(B593))-FIND("~",SUBSTITUTE(UPPER(B593),"X","~",LEN(UPPER(B593))-LEN(SUBSTITUTE(UPPER(B593),"X",""))))))),".")>=5,"Wall",""),""),"") | M593: {=_xlfn.IFS(NOT(ISERROR(VLOOKUP(Table5[[#This Row],[Section]],TB_notTB,1,FALSE))),"No",LEFT(Table5[[#This Row],[Section]],3)="ETB","PLS",LEFT(Table5[[#This Row],[Section]],1)="7","PDB",NOT(ISBLANK(Table5[[#This Row],[Section]])),"No")} -> No
A594: E01453 | B594: Tee 19.05x19.05x1.6 | C594: N | D594: 0.155 | E594: 100 | F594: 100 | G594: AI1070 | H594: 100012130031300016 | I594: Tee Sections | J594: IG_S1 | K594: =_xlfn.IFNA(VLOOKUP(Table5[[#This Row],[Section]],SubSill_Tier,2,FALSE),0) -> 0 | L594: =IFERROR(IF(LEFT(G594,2)="AI",IF(_xlfn.NUMBERVALUE(IFERROR(LEFT(IF(ISERROR(FIND("X",UPPER(B594))),UPPER(B594),RIGHT(UPPER(B594),LEN(UPPER(B594))-FIND("~",SUBSTITUTE(UPPER(B594),"X","~",LEN(UPPER(B594))-LEN(SUBSTITUTE(UPPER(B594),"X","")))))),FIND(" ",IF(ISERROR(FIND("X",UPPER(B594))),UPPER(B594),RIGHT(UPPER(B594),LEN(UPPER(B594))-FIND("~",SUBSTITUTE(UPPER(B594),"X","~",LEN(UPPER(B594))-LEN(SUBSTITUTE(UPPER(B594),"X","")))))),1)-1),IF(ISERROR(FIND("X",UPPER(B594))),UPPER(B594),RIGHT(UPPER(B594),LEN(UPPER(B594))-FIND("~",SUBSTITUTE(UPPER(B594),"X","~",LEN(UPPER(B594))-LEN(SUBSTITUTE(UPPER(B594),"X",""))))))),".")>=5,"Wall",""),""),"") | M594: {=_xlfn.IFS(NOT(ISERROR(VLOOKUP(Table5[[#This Row],[Section]],TB_notTB,1,FALSE))),"No",LEFT(Table5[[#This Row],[Section]],3)="ETB","PLS",LEFT(Table5[[#This Row],[Section]],1)="7","PDB",NOT(ISBLANK(Table5[[#This Row],[Section]])),"No")} -> No
A595: E01552 | B595: RHS 38.1x17.45x3.2 | C595: N | D595: 0.851 | E595: 111 | F595: 111 | G595: AI1090 | H595: 100012130031300018 | I595: Rectangular Hollows | J595: AB_S1 | K595: =_xlfn.IFNA(VLOOKUP(Table5[[#This Row],[Section]],SubSill_Tier,2,FALSE),0) -> 0 | L595: =IFERROR(IF(LEFT(G595,2)="AI",IF(_xlfn.NUMBERVALUE(IFERROR(LEFT(IF(ISERROR(FIND("X",UPPER(B595))),UPPER(B595),RIGHT(UPPER(B595),LEN(UPPER(B595))-FIND("~",SUBSTITUTE(UPPER(B595),"X","~",LEN(UPPER(B595))-LEN(SUBSTITUTE(UPPER(B595),"X","")))))),FIND(" ",IF(ISERROR(FIND("X",UPPER(B595))),UPPER(B595),RIGHT(UPPER(B595),LEN(UPPER(B595))-FIND("~",SUBSTITUTE(UPPER(B595),"X","~",LEN(UPPER(B595))-LEN(SUBSTITUTE(UPPER(B595),"X","")))))),1)-1),IF(ISERROR(FIND("X",UPPER(B595))),UPPER(B595),RIGHT(UPPER(B595),LEN(UPPER(B595))-FIND("~",SUBSTITUTE(UPPER(B595),"X","~",LEN(UPPER(B595))-LEN(SUBSTITUTE(UPPER(B595),"X",""))))))),".")>=5,"Wall",""),""),"") | M595: {=_xlfn.IFS(NOT(ISERROR(VLOOKUP(Table5[[#This Row],[Section]],TB_notTB,1,FALSE))),"No",LEFT(Table5[[#This Row],[Section]],3)="ETB","PLS",LEFT(Table5[[#This Row],[Section]],1)="7","PDB",NOT(ISBLANK(Table5[[#This Row],[Section]])),"No")} -> No
A596: E01575 | C596: N | D596: 0.27 | E596: 100 | F596: 100 | G596: AI1050 | H596: 100012130031300013 | I596: Angles | J596: AB_S1 | K596: =_xlfn.IFNA(VLOOKUP(Table5[[#This Row],[Section]],SubSill_Tier,2,FALSE),0) -> 0 | L596: =IFERROR(IF(LEFT(G596,2)="AI",IF(_xlfn.NUMBERVALUE(IFERROR(LEFT(IF(ISERROR(FIND("X",UPPER(B596))),UPPER(B596),RIGHT(UPPER(B596),LEN(UPPER(B596))-FIND("~",SUBSTITUTE(UPPER(B596),"X","~",LEN(UPPER(B596))-LEN(SUBSTITUTE(UPPER(B596),"X","")))))),FIND(" ",IF(ISERROR(FIND("X",UPPER(B596))),UPPER(B596),RIGHT(UPPER(B596),LEN(UPPER(B596))-FIND("~",SUBSTITUTE(UPPER(B596),"X","~",LEN(UPPER(B596))-LEN(SUBSTITUTE(UPPER(B596),"X","")))))),1)-1),IF(ISERROR(FIND("X",UPPER(B596))),UPPER(B596),RIGHT(UPPER(B596),LEN(UPPER(B596))-FIND("~",SUBSTITUTE(UPPER(B596),"X","~",LEN(UPPER(B596))-LEN(SUBSTITUTE(UPPER(B596),"X",""))))))),".")>=5,"Wall",""),""),"") | M596: {=_xlfn.IFS(NOT(ISERROR(VLOOKUP(Table5[[#This Row],[Section]],TB_notTB,1,FALSE))),"No",LEFT(Table5[[#This Row],[Section]],3)="ETB","PLS",LEFT(Table5[[#This Row],[Section]],1)="7","PDB",NOT(ISBLANK(Table5[[#This Row],[Section]])),"No")} -> No
A597: E01608 | C597: N | D597: 0.852 | E597: 100 | F597: 100 | G597: AI1170 | H597: 100012130031300021 | I597: Other Industrial - 1 | J597: AB_S3 | K597: =_xlfn.IFNA(VLOOKUP(Table5[[#This Row],[Section]],SubSill_Tier,2,FALSE),0) -> 0 | L597: =IFERROR(IF(LEFT(G597,2)="AI",IF(_xlfn.NUMBERVALUE(IFERROR(LEFT(IF(ISERROR(FIND("X",UPPER(B597))),UPPER(B597),RIGHT(UPPER(B597),LEN(UPPER(B597))-FIND("~",SUBSTITUTE(UPPER(B597),"X","~",LEN(UPPER(B597))-LEN(SUBSTITUTE(UPPER(B597),"X","")))))),FIND(" ",IF(ISERROR(FIND("X",UPPER(B597))),UPPER(B597),RIGHT(UPPER(B597),LEN(UPPER(B597))-FIND("~",SUBSTITUTE(UPPER(B597),"X","~",LEN(UPPER(B597))-LEN(SUBSTITUTE(UPPER(B597),"X","")))))),1)-1),IF(ISERROR(FIND("X",UPPER(B597))),UPPER(B597),RIGHT(UPPER(B597),LEN(UPPER(B597))-FIND("~",SUBSTITUTE(UPPER(B597),"X","~",LEN(UPPER(B597))-LEN(SUBSTITUTE(UPPER(B597),"X",""))))))),".")>=5,"Wall",""),""),"") | M597: {=_xlfn.IFS(NOT(ISERROR(VLOOKUP(Table5[[#This Row],[Section]],TB_notTB,1,FALSE))),"No",LEFT(Table5[[#This Row],[Section]],3)="ETB","PLS",LEFT(Table5[[#This Row],[Section]],1)="7","PDB",NOT(ISBLANK(Table5[[#This Row],[Section]])),"No")} -> No
A598: E01628 | C598: N | D598: 0.742 | E598: 215 | F598: 215 | G598: AI1510 | H598: 100012130031300021 | I598: Other Industrial - 1 | J598: AB_S3 | K598: =_xlfn.IFNA(VLOOKUP(Table5[[#This Row],[Section]],SubSill_Tier,2,FALSE),0) -> 0 | L598: =IFERROR(IF(LEFT(G598,2)="AI",IF(_xlfn.NUMBERVALUE(IFERROR(LEFT(IF(ISERROR(FIND("X",UPPER(B598))),UPPER(B598),RIGHT(UPPER(B598),LEN(UPPER(B598))-FIND("~",SUBSTITUTE(UPPER(B598),"X","~",LEN(UPPER(B598))-LEN(SUBSTITUTE(UPPER(B598),"X","")))))),FIND(" ",IF(ISERROR(FIND("X",UPPER(B598))),UPPER(B598),RIGHT(UPPER(B598),LEN(UPPER(B598))-FIND("~",SUBSTITUTE(UPPER(B598),"X","~",LEN(UPPER(B598))-LEN(SUBSTITUTE(UPPER(B598),"X","")))))),1)-1),IF(ISERROR(FIND("X",UPPER(B598))),UPPER(B598),RIGHT(UPPER(B598),LEN(UPPER(B598))-FIND("~",SUBSTITUTE(UPPER(B598),"X","~",LEN(UPPER(B598))-LEN(SUBSTITUTE(UPPER(B598),"X",""))))))),".")>=5,"Wall",""),""),"") | M598: {=_xlfn.IFS(NOT(ISERROR(VLOOKUP(Table5[[#This Row],[Section]],TB_notTB,1,FALSE))),"No",LEFT(Table5[[#This Row],[Section]],3)="ETB","PLS",LEFT(Table5[[#This Row],[Section]],1)="7","PDB",NOT(ISBLANK(Table5[[#This Row],[Section]])),"No")} -> No
...

Sheet DATA_EDGE
A1: Mat.Ref.No | B1: Mat.Ref.Description | C1: SAP.Mat.No | E1: Reverse sort to ensure sections are at top
A2: C001 | B2: C001 Wide Wiper Stile | C2: EP23000 | E2: This should make TB items select the ETB code rather than the 7 code
A3: C002 | B3: C002 Wide Hinge Stile | C3: EP23001
A4: C003 | B4: C003 Wide Lock Stile | C4: EP23002
A5: C004 | B5: C004 Wide Pivot Stile | C5: EP23003
A6: C0054 | B6: C0054 Overlap Sash Bead | C6: EP23004
A7: C015 | B7: C015 Glazing Base to suit C016 | C7: EP23005
A8: C016 | B8: C016 Glazing Bead to suit C015 | C8: EP23006
A9: C016-2 | B9: C016-2 Overlap Sash Bead | C9: EP23007
A10: C017 | B10: C017 Glazing Channel 18mm Pocket | C10: EP23008
A11: C0256 | B11: C0256 Hand Rail | C11: EP23009
A12: C0385 | B12: C0385 150 Sub Sill Slotted 5mm Setback | C12: EP23010
A13: C0390 | B13: C0390 45mm Door Spiggot | C13: EP23011
A14: C046 | B14: C046 Beaded Lock Stile | C14: EP23012
... A1191: C9978 | B1191: C9978 Max Hd Meeting Stile | C1191: EP23741

Sheet Validation
A1: Market Segment | B1: Product Segment | C1: Region | E1: LocAl Logo Options | G1: Sundry Type | J1: TB Pricing | K1: Subsills (slotting) | L1: Tier | N1: Thresholds | P1: TB but not TB | R1: PC Applicator | S1: Custom? | T1: AP or PP | U1: Groups (1=Capral,2=Other) | V1: Ano Applicator | W1: Finish Mill | X1: PC Groups Capral | Z1: PC Groups Other | AA1: Custom? | AB1: Ano Groups Capral | AD1: Ano Groups Other
A2: Private Residential - Detached | B2: Commercial | C2: NQ | E2: None | G2: Each length | J2: List less Discount | K2: E27281 | L2: 1 | N2: EP2366 | P2: ETB0003 | R2: n/a | S2: 0 | T2: 0 | U2: 2 | V2: n/a | W2: n/a | X2: Group 1 | Y2: -> | Z2: Group 1 | AA2: 0 | AB2: 20um Clear | AC2: -> | AD2: 20um Clear
A3: Private Residential - Other | B3: Residential | C3: NSW | E3: LocAl Green | G3: Section total | J3: Margin | K3: E18673 | L3: 1 | N3: EP5796 | P3: ETB0007 | R3: Capral P&P - Bremer (AP) | S3: 0 | T3: 0 | U3: 1 | V3: Capral/AAF QLD anodising | X3: Group 2 | Y3: -> | Z3: Group 2 | AA3: 0 | AB3: 25um Clear | AC3: -> | AD3: 25um Clear
A4: Public Dwelling | B4: Security | C4: NT | E4: LocAl SuperGreen | K4: E30786 | L4: 1 | N4: EP15939 | P4: ETB0008 | R4: Capral P&P - Campbellfield (AP) | S4: 0 | T4: 0 | U4: 1 | V4: WA Anodisers | X4: Group 3 | Y4: -> | Z4: Group 3 | AA4: 0 | AB4: Group POA | AC4: -> | AD4: Group POA
A5: Office | B5: Industrial | C5: SA | K5: E32266 | L5: 1 | N5: E35737 | P5: ETB0009 | R5: Capral P&P - Canningvale (PP) | S5: 0 | T5: 1 | U5: 1 | V5: Other - pls check pricing | X5: Group 4 | Y5: -> | Z5: Group POA | AA5: 0 | AB5: not implemented - review when anodiing groups updated
A6: Retail | B6: Shower & Robe | C6: SEQ | K6: E32359 | L6: 1 | N6: EP2212 | P6: ETB0205 | R6: Capral P&P - HWood Non-Bulk (AP) | S6: 0 | T6: 0 | U6: 1 | X6: Group 5 | Y6: -> | Z6: Group POA | AA6: 0
A7: Hotel | C7: TAS | K7: E32370 | L7: 1 | N7: EP2365 | P7: ETB0207 | R7: Capral P&P - HWood Bulk (AP) | S7: 0 | T7: 0 | U7: 1 | X7: Group POA | Y7: -> | Z7: Group POA | AA7: 1
A8: Factory | C8: VIC | E8: Anodised Thresholds | K8: E35590 | L8: 1 | N8: EP20049 | P8: ETB0217 | R8: Capral Mill (AP) | S8: 4 | T8: 0 | U8: 1
A9: Warehouse | C9: WA | E9: No | K9: E52619 | L9: 1 | N9: EP13539 | P9: ETB0344 | R9: AAF powdercoat | S9: 0 | T9: 0 | U9: 2
A10: Education | E10: 20um Clear | F10: 3A | K10: EA2924 | L10: 1 | N10: EP13540 | R10: Powderline WA | S10: 0 | T10: 1 | U10: 2
A11: Health | E11: 25um Clear | F11: 4A | K11: EAL11812 | L11: 1 | N11: EP22082 | R11: Other - pls check pricing | S11: 1 | T11: 2 | U11: 2
A12: Entertainment/Recreation | K12: ED7908 | L12: 1 | N12: EP22083 | W12: Yes No | X12: No
A13: Other | K13: ED7991 | L13: 1 | N13: E01854 | W13: Yes | X13: No
K14: ED8536 | L14: 1 | N14: EP20050 | R14: PC Price 1 (pp/ap) | S14: Finish Type | T14: Powder Supplier | W14: No
H15: Alloy Extras | K15: ED8597 | L15: 1 | R15: Anodised Perimeter (AP) | S15: Mill Finish | T15: n/a
H16: 6060 | K16: ED8654 | L16: 1 | R16: Paint Perimeter (PP) | S16: Anodised | T16: Interpon
H17: 6063 | K17: EL4088 | L17: 1 | S17: Powder | T17: Dulux
H18: 6106 | K18: EL5181 | L18: 1 | R18: PC Price 2 (ap only)
H19: 6101 | K19: EL5182 | L19: 1 | R19: Anodised Perimeter (AP)
H20: 1350 | K20: EME10009 | L20: 1
H21: 6005A | K21: EME10015 | L21: 1 | R21: PC Price 3 (PP only)
H22: 6082 | K22: EME10389 | L22: 1 | R22: Paint Perimeter (PP)
H23: 6351 | K23: EME31569 | L23: 1
H24: 6061 | K24: EN5202 | L24: 1 | R24: PC Price 4 (MF)
K25: EN5328 | L25: 1 | R25: n/a
B26: NSW | C26: 15 Huntingwood Drive | D26: Huntingwood, NSW, 2148 | H26: Temper Extras | K26: EN5980 | L26: 1
B27: SEQ | C27: 71 Ashburn Road, Bundamba QLD 4304 | D27: PO Box 768, Booval Fair QLD 4304 | H27: T1 | K27: EN6523 | L27: 1
B28: NQ | C28: 303 Woolcock St, Garbutt QLD 4814 | D28: PO Box 7385, Garbutt QLD 4814 | H28: T4 | K28: EN6524 | L28: 1 | R28: Type | S28: Applicator | T28: Result
B29: NT | C29: 8 Mataram Street, Winnellie NT 0820 | D29: PO Box 38296, Winnellie NT 0820 | H29: T5 | K29: EP10573 | L29: 1 | R29: Mill Finish | S29: n/a | T29: n/a
B30: SA | C30: 70 Grand Junction Road | D30: Kilburn SA 5084 | H30: T6 | K30: EP11442 | L30: 1 | R30: Anodised | S30: Anodiser TBC | T30: Anodised Perimeter (AP)
B31: TAS | C31: 116 Grove Road | D31: PO Box 1177 | E31: Glenorchy TAS 7010 | H31: T591 | K31: EP11928 | L31: 1 | R31: Anodised | S31: Capral/AAF QLD anodising | T31: Anodised Perimeter (AP)
B32: VIC | C32: 151 Barry Road, Campbellfield VIC 3061 | D32: PO Box 68, Cambellfield VIC 3061 | H32: T595 | K32: EP12062 | L32: 1 | R32: Anodised | S32: WA Anodisers | T32: Anodised Perimeter (AP)
B33: WA | C33: 45 - 55 Baile Road | D33: Canning Vale WA 6155 | E33: or 2 Competition Way | F33: Wangara WA 6065 | H33: T52 | K33: EP12101 | L33: 1 | R33: Anodised | S33: Ano Other - pls check pricing | T33: Anodised Perimeter (AP)
K34: EP1285 | L34: 1 | R34: Powder | S34: Powdercoater TBC | T34: Anodised Perimeter (AP)
K35: EP12896 | L35: 1 | R35: Powder | S35: Capral | T35: Anodised Perimeter (AP)
K36: EP13090 | L36: 1 | R36: Powder | S36: AAF powdercoat | T36: Anodised Perimeter (AP)
K37: EP13091 | L37: 1 | R37: Powder | S37: Powderline WA | T37: Paint Perimeter (PP)
K38: EP13388 | L38: 1 | R38: Powder | S38: PC Other - pls check pricing | T38: Anodised Perimeter (AP)
K39: EP14149 | L39: 1
K40: EP14579 | L40: 1
K41: EP15348 | L41: 1
K42: EP15450 | L42: 1
K43: EP15699 | L43: 1
K44: EP18194 | L44: 1
K45: EP18807 | L45: 1
K46: EP20158 | L46: 3
K47: EP3612 | L47: 1
K48: EP3982 | L48: 1
K49: EP3983 | L49: 1
K50: EP4782 | L50: 1
... K85: EP24018 | L85: 4

Sheet Pricing Matrix
J1: COSTS - UPDATED MONTHLY (as per Mill pricing agreement) | AG1: From MM60 (moving average cost stock on floor) Use 3010 as will be most active AE3000 to AE3999, AR2015, AR2025, AR2045, AR1245
A2: Metal Pricing | E2: PDB Metal Costing | H2: Standard delivery charge | J2: What | K2: Value | L2: Notes | S2: Thermal Break Costs | AB2: =tb_calc_type -> Margin | AC2: =tb_calc_value -> 0.5 | AH2: 46174 | AI2: 46083 | AJ2: 45840 | AK2: 45749 | AL2: 45628 | AM2: 45460 | AN2: 45313 | AO2: 45076 | AQ2: prior to 02/05/2022 | AR2: 44473 | AS2: 43886 | AT2: 43556
A3: LME + billet premium | B3: =Table_Costs[[#This Row],[Value]] -> 5.61 | C3: 46174 | D3: =TEXT(DAY(C3),"00") -> 01 | E3: Extra Spread | F3: 0.35 | G3: $/kg | H3: 97 | J3: LME incl. billet premium | K3: =M3+M4 -> 5.61 | M3: 5.1 | N3: LME | S3: Section | T3: Basic Material | U3: Length | V3: Weight/m | W3: MPG | X3: MPM Surcharge | Y3: Roll? | Z3: Rolling Factor (Cost/0.8*2.5) | AA3: List Price | AB3: TOTAL COST | AC3: Metal Sell Price | AD3: Actual Margin % | AF3: Section | AG3: Material | AH3: NEW COST | AI3: OLD COST | AJ3: OLD COST | AK3: OLD COST | AL3: OLD COST | AM3: OLD COST | AN3: OLD COST | AO3: OLD COST | AP3: OLD COST | AQ3: OLD COST | AR3: OLD COST | AS3: OLD COST | AT3: OLD COST
A4: Internal Spread | B4: =Table_Costs[[#This Row],[Value]] -> 3.12 | D4: =TEXT(MONTH(C3),"00") & "." -> 06. | E4: Metal Cost | F4: =B5+F3 -> 9.08 | G4: $/kg | J4: Spread | K4: 3.12 | L4: 500-999kg spread | M4: 0.51 | N4: Billet Prem | S4: ETB0001 | T4: =VLOOKUP(Table_TB_Cost[[#This Row],[Section]],DATA!A:K,2,FALSE) -> 425TB - Solid Mullion / Frame | U4: 6.5 | V4: =VLOOKUP(Table_TB_Cost[[#This Row],[Section]],DATA!A:K,4,FALSE) -> 2.347 | W4: =LEFT(VLOOKUP(Table_TB_Cost[[#This Row],[Section]],Table5[],10,FALSE),2) -> FJ | X4: =IF(Table_TB_Cost[[#This Row],[Weight/m]]<0.5,1*2.5,"") | Y4: Y | Z4: =IF(Table_TB_Cost[[#This Row],[Roll?]]="Y",(2.5/Table_TB_Cost[[#This Row],[Weight/m]]/0.8)*2.5,"") -> 3.3287175 | AA4: =SUM(VLOOKUP(Table_TB_Cost[[#This Row],[MPG]],TB_MPG,2,FALSE),Table_TB_Cost[[#This Row],[MPM Surcharge]],Table_TB_Cost[[#This Row],[Rolling Factor (Cost/0.8*2.5)]])*Table_TB_Cost[[#This Row],[Weight/m]]*Table_TB_Cost[[#This Row],[Length]] -> 584.87631 | AB4: =VLOOKUP(Table_TB_Cost[[#This Row],[Section]],AF:AJ,3,FALSE) -> 157.138 | AC4: =IF($AB$2="Margin",Table_TB_Cost[[#This Row],[TOTAL COST]]/(1-$AC$2),Table_TB_Cost[[#This Row],[List Price]]*(1-$AC$2)) -> 314.276 | AD4: =(Table_TB_Cost[[#This Row],[Metal Sell Price]]-Table_TB_Cost[[#This Row],[TOTAL COST]])/Table_TB_Cost[[#This Row],[Metal Sell Price]] -> 0.5 | AF4: ETB0001 | AG4: 734490 | AH4: 157.138 | AI4: 149.1742 | AJ4: 149.48989 | AK4: 145.03968 | AL4: 142.61705 | AM4: 145.27077 | AN4: 162.04271 | AO4: 177.15902 | AP4: 149.1 | AQ4: 134.3 | AR4: 137.06 | AS4: 138.41 | AT4: 143 | AW4: =VLOOKUP(AF4,Table_TB_Cost[[Section]:[Basic Material]],2,FALSE) -> 425TB - Solid Mullion / Frame | AX4: ETB0001 | AY4: =VLOOKUP(AX4,Table_TB_Cost[#All],5,FALSE) -> FJ
A5: Cost | B5: =B3+B4 -> 8.73 | D5: =YEAR(C3) & "." -> 2026. | E5: ALF Cost | F5: 6.46 | G5: $/m updated 04.02.2026 | J5: AP to PP factor | K5: 1.9 | S5: ETB0002 | T5: =VLOOKUP(Table_TB_Cost[[#This Row],[Section]],DATA!A:K,2,FALSE) -> 425TB - Sill Transom | U5: 6.5 | V5: =VLOOKUP(Table_TB_Cost[[#This Row],[Section]],DATA!A:K,4,FALSE) -> 2.112 | W5: =LEFT(VLOOKUP(Table_TB_Cost[[#This Row],[Section]],Table5[],10,FALSE),2) -> FJ | X5: =IF(Table_TB_Cost[[#This Row],[Weight/m]]<0.5,1*2.5,"") | Y5: Y | Z5: =IF(Table_TB_Cost[[#This Row],[Roll?]]="Y",(2.5/Table_TB_Cost[[#This Row],[Weight/m]]/0.8)*2.5,"") -> 3.6991004 | AA5: =SUM(VLOOKUP(Table_TB_Cost[[#This Row],[MPG]],TB_MPG,2,FALSE),Table_TB_Cost[[#This Row],[MPM Surcharge]],Table_TB_Cost[[#This Row],[Rolling Factor (Cost/0.8*2.5)]])*Table_TB_Cost[[#This Row],[Weight/m]]*Table_TB_Cost[[#This Row],[Length]] -> 531.39853 | AB5: =VLOOKUP(Table_TB_Cost[[#This Row],[Section]],AF:AJ,3,FALSE) -> 141.9625 | AC5: =IF($AB$2="Margin",Table_TB_Cost[[#This Row],[TOTAL COST]]/(1-$AC$2),Table_TB_Cost[[#This Row],[List Price]]*(1-$AC$2)) -> 283.925 | AD5: =(Table_TB_Cost[[#This Row],[Metal Sell Price]]-Table_TB_Cost[[#This Row],[TOTAL COST]])/Table_TB_Cost[[#This Row],[Metal Sell Price]] -> 0.5 | AF5: ETB0002 | AG5: 734491 | AH5: 141.9625 | AI5: 139.04936 | AJ5: 137.90146 | AK5: 135.81175 | AL5: 132.43795 | AM5: 128.664 | AN5: 146.36 | AO5: 121.49364 | AP5: 138.18 | AQ5: 124.83 | AR5: 127.17 | AS5: 128.42 | AT5: 132.68 | AW5: =VLOOKUP(AF5,Table_TB_Cost[[Section]:[Basic Material]],2,FALSE) -> 425TB - Sill Transom | AX5: ETB0002 | AY5: =VLOOKUP(AX5,Table_TB_Cost[#All],5,FALSE) -> FJ
J6: FE | K6: 118.58 | L6: Kits 1 | M6: Updated 01.06.2026 | S6: ETB0003 | T6: =VLOOKUP(Table_TB_Cost[[#This Row],[Section]],DATA!A:K,2,FALSE) -> 425TB - Square Bead | U6: 6.5 | V6: =VLOOKUP(Table_TB_Cost[[#This Row],[Section]],DATA!A:K,4,FALSE) -> 0.444 | W6: =LEFT(VLOOKUP(Table_TB_Cost[[#This Row],[Section]],Table5[],10,FALSE),2) -> FH | X6: =IF(Table_TB_Cost[[#This Row],[Weight/m]]<0.5,1*2.5,"") -> 2.5 | Y6: N | Z6: =IF(Table_TB_Cost[[#This Row],[Roll?]]="Y",(2.5/Table_TB_Cost[[#This Row],[Weight/m]]/0.8)*2.5,"") | AA6: =SUM(VLOOKUP(Table_TB_Cost[[#This Row],[MPG]],TB_MPG,2,FALSE),Table_TB_Cost[[#This Row],[MPM Surcharge]],Table_TB_Cost[[#This Row],[Rolling Factor (Cost/0.8*2.5)]])*Table_TB_Cost[[#This Row],[Weight/m]]*Table_TB_Cost[[#This Row],[Length]] -> 88.05186 | AB6: =VLOOKUP(Table_TB_Cost[[#This Row],[Section]],AF:AJ,3,FALSE) -> 24.43776 | AC6: =IF($AB$2="Margin",Table_TB_Cost[[#This Row],[TOTAL COST]]/(1-$AC$2),Table_TB_Cost[[#This Row],[List Price]]*(1-$AC$2)) -> 48.87552 | AD6: =(Table_TB_Cost[[#This Row],[Metal Sell Price]]-Table_TB_Cost[[#This Row],[TOTAL COST]])/Table_TB_Cost[[#This Row],[Metal Sell Price]] -> 0.5 | AF6: ETB0003 | AG6: 1028191 | AH6: 24.43776 | AI6: 21.91625 | AJ6: 19.79259 | AK6: 19.79255 | AL6: 19.79258 | AM6: 18.255 | AN6: 18.525 | AO6: 19.12752 | AP6: 20.72 | AQ6: 17.95 | AR6: 17.39 | AS6: 17.56 | AT6: 18.15 | AW6: =VLOOKUP(AF6,Table_TB_Cost[[Section]:[Basic Material]],2,FALSE) -> 425TB - Square Bead | AX6: ETB0003 | AY6: =VLOOKUP(AX6,Table_TB_Cost[#All],5,FALSE) -> FH
A7: Breakpoints (kg) | B7: Spread | C7: Typical | D7: Min | E7: Max | F7: Min Factor | G7: Max Factor | J7: FH | K7: 28.01 | L7: FutureLine 1 | M7: Updated 01.06.2026 | S7: ETB0004 | T7: =VLOOKUP(Table_TB_Cost[[#This Row],[Section]],DATA!A:K,2,FALSE) -> 440TB - Female Mullion / Narrow Frame | W7: =LEFT(VLOOKUP(Table_TB_Cost[[#This Row],[Section]],Table5[],10,FALSE),2) -> BB | X7: =IF(Table_TB_Cost[[#This Row],[Weight/m]]<0.5,1*2.5,"") -> 2.5 | AB7: =VLOOKUP(Table_TB_Cost[[#This Row],[Section]],AF:AJ,3,FALSE) -> 0 | AF7: ETB0004 | AR7: 101.31 | AS7: 102.3 | AT7: 105.69 | AW7: =VLOOKUP(AF7,Table_TB_Cost[[Section]:[Basic Material]],2,FALSE) -> 440TB - Female Mullion / Narrow Frame | AX7: ETB0004 | AY7: =VLOOKUP(AX7,Table_TB_Cost[#All],5,FALSE) -> BB
A8: 1 | B8: 3.5 | C8: =$B$5+B8 -> 12.23 | D8: =C8-F8 -> 11.88 | E8: =C8+G8 -> 12.73 | F8: 0.35 | G8: 0.5 | J8: FI | K8: 31.52 | L8: FutureLine 2 | M8: Updated 01.06.2026 | S8: ETB0005 | T8: =VLOOKUP(Table_TB_Cost[[#This Row],[Section]],DATA!A:K,2,FALSE) -> 440TB - Male Mullion | W8: =LEFT(VLOOKUP(Table_TB_Cost[[#This Row],[Section]],Table5[],10,FALSE),2) -> BB | X8: =IF(Table_TB_Cost[[#This Row],[Weight/m]]<0.5,1*2.5,"") -> 2.5 | AB8: =VLOOKUP(Table_TB_Cost[[#This Row],[Section]],AF:AJ,3,FALSE) -> 0 | AF8: ETB0005 | AR8: 135.25 | AS8: 136.57 | AT8: 141.1 | AW8: =VLOOKUP(AF8,Table_TB_Cost[[Section]:[Basic Material]],2,FALSE) -> 440TB - Male Mullion | AX8: ETB0005 | AY8: =VLOOKUP(AX8,Table_TB_Cost[#All],5,FALSE) -> BB
A9: 2000 | B9: 1.42 | C9: =$B$5+B9 -> 10.15 | D9: =C9-F9 -> 9.8 | E9: =C9+G9 -> 10.65 | F9: 0.35 | G9: 0.5 | J9: FJ | K9: 35.01 | L9: FutureLine 3 | M9: Updated 01.06.2026 | S9: ETB0006 | T9: =VLOOKUP(Table_TB_Cost[[#This Row],[Section]],DATA!A:K,2,FALSE) -> 425TB - Sash Adaptor | U9: 6.5 | V9: =VLOOKUP(Table_TB_Cost[[#This Row],[Section]],DATA!A:K,4,FALSE) -> 0.906 | W9: =LEFT(VLOOKUP(Table_TB_Cost[[#This Row],[Section]],Table5[],10,FALSE),2) -> FK | X9: =IF(Table_TB_Cost[[#This Row],[Weight/m]]<0.5,1*2.5,"") | Y9: Y | Z9: =IF(Table_TB_Cost[[#This Row],[Roll?]]="Y",(2.5/Table_TB_Cost[[#This Row],[Weight/m]]/0.8)*2.5,"") -> 8.6230684 | AA9: =SUM(VLOOKUP(Table_TB_Cost[[#This Row],[MPG]],TB_MPG,2,FALSE),Table_TB_Cost[[#This Row],[MPM Surcharge]],Table_TB_Cost[[#This Row],[Rolling Factor (Cost/0.8*2.5)]])*Table_TB_Cost[[#This Row],[Weight/m]]*Table_TB_Cost[[#This Row],[Length]] -> 277.62553 | AB9: =VLOOKUP(Table_TB_Cost[[#This Row],[Section]],AF:AJ,3,FALSE) -> 76.58398 | AC9: =IF($AB$2="Margin",Table_TB_Cost[[#This Row],[TOTAL COST]]/(1-$AC$2),Table_TB_Cost[[#This Row],[List Price]]*(1-$AC$2)) -> 153.16796 | AD9: =(Table_TB_Cost[[#This Row],[Metal Sell Price]]-Table_TB_Cost[[#This Row],[TOTAL COST]])/Table_TB_Cost[[#This Row],[Metal Sell Price]] -> 0.5 | AF9: ETB0006 | AG9: 734872 | AH9: 76.58398 | AI9: 74.54366 | AJ9: 73.28747 | AK9: 74.17254 | AL9: 71.5988 | AM9: 80.82754 | AN9: 116.70053 | AO9: 68.24193 | AP9: 72.21 | AQ9: 67.15 | AR9: 79.62 | AS9: 76.07 | AT9: 83.06 | AW9: =VLOOKUP(AF9,Table_TB_Cost[[Section]:[Basic Material]],2,FALSE) -> 425TB - Sash Adaptor | AX9: ETB0006 | AY9: =VLOOKUP(AX9,Table_TB_Cost[#All],5,FALSE) -> FK
A10: 3000 | B10: 1.37 | C10: =$B$5+B10 -> 10.1 | D10: =C10-F10 -> 9.75 | E10: =C10+G10 -> 10.6 | F10: 0.35 | G10: 0.5 | J10: FK | K10: 38.52 | L10: FutureLine 4 | M10: Updated 01.06.2026 | S10: ETB0007 | T10: =VLOOKUP(Table_TB_Cost[[#This Row],[Section]],DATA!A:K,2,FALSE) -> TB - 4.5mm Bead | U10: 6.5 | V10: =VLOOKUP(Table_TB_Cost[[#This Row],[Section]],DATA!A:K,4,FALSE) -> 0.187 | W10: =LEFT(VLOOKUP(Table_TB_Cost[[#This Row],[Section]],Table5[],10,FALSE),2) -> FH | X10: =IF(Table_TB_Cost[[#This Row],[Weight/m]]<0.5,1*2.5,"") -> 2.5 | Y10: N | Z10: =IF(Table_TB_Cost[[#This Row],[Roll?]]="Y",(2.5/Table_TB_Cost[[#This Row],[Weight/m]]/0.8)*2.5,"") | AA10: =SUM(VLOOKUP(Table_TB_Cost[[#This Row],[MPG]],TB_MPG,2,FALSE),Table_TB_Cost[[#This Row],[MPM Surcharge]],Table_TB_Cost[[#This Row],[Rolling Factor (Cost/0.8*2.5)]])*Table_TB_Cost[[#This Row],[Weight/m]]*Table_TB_Cost[[#This Row],[Length]] -> 37.084905 | AB10: =VLOOKUP(Table_TB_Cost[[#This Row],[Section]],AF:AJ,3,FALSE) -> 9.7378 | AC10: =IF($AB$2="Margin",Table_TB_Cost[[#This Row],[TOTAL COST]]/(1-$AC$2),Table_TB_Cost[[#This Row],[List Price]]*(1-$AC$2)) -> 19.4756 | AD10: =(Table_TB_Cost[[#This Row],[Metal Sell Price]]-Table_TB_Cost[[#This Row],[TOTAL COST]])/Table_TB_Cost[[#This Row],[Metal Sell Price]] -> 0.5 | AF10: ETB0007 | AG10: 1028194 | AH10: 9.7378 | AI10: 9.73793 | AJ10: 9.62059 | AK10: 8.97225 | AL10: 8.97211 | AM10: 8.97249 | AN10: 8.95797 | AO10: 8.95821 | AP10: 9.16 | AQ10: 7.99 | AR10: 4.82 | AS10: 4.89 | AT10: 5.2 | AW10: =VLOOKUP(AF10,Table_TB_Cost[[Section]:[Basic Material]],2,FALSE) -> TB - 4.5mm Bead | AX10: ETB0007 | AY10: =VLOOKUP(AX10,Table_TB_Cost[#All],5,FALSE) -> FH
A11: 5000 | B11: 1.32 | C11: =$B$5+B11 -> 10.05 | D11: =C11-F11 -> 9.7 | E11: =C11+G11 -> 10.55 | F11: 0.35 | G11: 0.5 | J11: FL | K11: 42.02 | L11: FutureLine 5 | M11: Updated 01.06.2026 | S11: ETB0008 | T11: =VLOOKUP(Table_TB_Cost[[#This Row],[Section]],DATA!A:K,2,FALSE) -> TB - 11.5mm Bead | U11: 6.5 | V11: =VLOOKUP(Table_TB_Cost[[#This Row],[Section]],DATA!A:K,4,FALSE) -> 0.233 | W11: =LEFT(VLOOKUP(Table_TB_Cost[[#This Row],[Section]],Table5[],10,FALSE),2) -> FH | X11: =IF(Table_TB_Cost[[#This Row],[Weight/m]]<0.5,1*2.5,"") -> 2.5 | Y11: N | Z11: =IF(Table_TB_Cost[[#This Row],[Roll?]]="Y",(2.5/Table_TB_Cost[[#This Row],[Weight/m]]/0.8)*2.5,"") | AA11: =SUM(VLOOKUP(Table_TB_Cost[[#This Row],[MPG]],TB_MPG,2,FALSE),Table_TB_Cost[[#This Row],[MPM Surcharge]],Table_TB_Cost[[#This Row],[Rolling Factor (Cost/0.8*2.5)]])*Table_TB_Cost[[#This Row],[Weight/m]]*Table_TB_Cost[[#This Row],[Length]] -> 46.207395 | AB11: =VLOOKUP(Table_TB_Cost[[#This Row],[Section]],AF:AJ,3,FALSE) -> 10.79946 | AC11: =IF($AB$2="Margin",Table_TB_Cost[[#This Row],[TOTAL COST]]/(1-$AC$2),Table_TB_Cost[[#This Row],[List Price]]*(1-$AC$2)) -> 21.59892 | AD11: =(Table_TB_Cost[[#This Row],[Metal Sell Price]]-Table_TB_Cost[[#This Row],[TOTAL COST]])/Table_TB_Cost[[#This Row],[Metal Sell Price]] -> 0.5 | AF11: ETB0008 | AG11: 1076087 | AH11: 10.79946 | AI11: 10.79949 | AJ11: 10.7995 | AK11: 9.78765 | AL11: 9.78765 | AM11: 9.78772 | AN11: 9.78772 | AO11: 7.65111 | AP11: 10.88 | AQ11: 9.42 | AR11: 8.89 | AS11: 8.98 | AT11: 9.27 | AW11: =VLOOKUP(AF11,Table_TB_Cost[[Section]:[Basic Material]],2,FALSE) -> TB - 11.5mm Bead | AX11: ETB0008 | AY11: =VLOOKUP(AX11,Table_TB_Cost[#All],5,FALSE) -> FH
A12: 7000 | B12: 1.12 | C12: =$B$5+B12 -> 9.85 | D12: =C12-F12 -> 9.7 | E12: =C12+G12 -> 10.35 | F12: 0.15 | G12: 0.5 | J12: FM | K12: 45.53 | L12: FutureLine 6 | M12: Updated 01.06.2026 | S12: ETB0009 | T12: =VLOOKUP(Table_TB_Cost[[#This Row],[Section]],DATA!A:K,2,FALSE) -> TB - 16.5mm Bead | U12: 6.5 | V12: =VLOOKUP(Table_TB_Cost[[#This Row],[Section]],DATA!A:K,4,FALSE) -> 0.241 | W12: =LEFT(VLOOKUP(Table_TB_Cost[[#This Row],[Section]],Table5[],10,FALSE),2) -> FH | X12: =IF(Table_TB_Cost[[#This Row],[Weight/m]]<0.5,1*2.5,"") -> 2.5 | Y12: N | Z12: =IF(Table_TB_Cost[[#This Row],[Roll?]]="Y",(2.5/Table_TB_Cost[[#This Row],[Weight/m]]/0.8)*2.5,"") | AA12: =SUM(VLOOKUP(Table_TB_Cost[[#This Row],[MPG]],TB_MPG,2,FALSE),Table_TB_Cost[[#This Row],[MPM Surcharge]],Table_TB_Cost[[#This Row],[Rolling Factor (Cost/0.8*2.5)]])*Table_TB_Cost[[#This Row],[Weight/m]]*Table_TB_Cost[[#This Row],[Length]] -> 47.793915 | AB12: =VLOOKUP(Table_TB_Cost[[#This Row],[Section]],AF:AJ,3,FALSE) -> 12.74236 | AC12: =IF($AB$2="Margin",Table_TB_Cost[[#This Row],[TOTAL COST]]/(1-$AC$2),Table_TB_Cost[[#This Row],[List Price]]*(1-$AC$2)) -> 25.48472 | AD12: =(Table_TB_Cost[[#This Row],[Metal Sell Price]]-Table_TB_Cost[[#This Row],[TOTAL COST]])/Table_TB_Cost[[#This Row],[Metal Sell Price]] -> 0.5 | AF12: ETB0009 | AG12: 1076088 | AH12: 12.74236 | AI12: 12.24558 | AJ12: 11.84626 | AK12: 11.84644 | AL12: 10.77432 | AM12: 10.04987 | AN12: 10.11599 | AO12: 10.05241 | AP12: 11.25 | AQ12: 9.75 | AR12: 7.96 | AS12: 8.04 | AT12: 8.3 | AW12: =VLOOKUP(AF12,Table_TB_Cost[[Section]:[Basic Material]],2,FALSE) -> TB - 16.5mm Bead | AX12: ETB0009 | AY12: =VLOOKUP(AX12,Table_TB_Cost[#All],5,FALSE) -> FH
A13: 10000 | B13: 1.02 | C13: =$B$5+B13 -> 9.75 | D13: =C13-F13 -> 9.6 | E13: =C13+G13 -> 10.25 | F13: 0.15 | G13: 0.5 | J13: FN | K13: 49.03 | L13: FutureLine 7 | M13: Updated 01.06.2026 | S13: ETB0010 | T13: =VLOOKUP(Table_TB_Cost[[#This Row],[Section]],DATA!A:K,2,FALSE) -> 46D TB - Hinge Door Stile | U13: 5 | V13: =VLOOKUP(Table_TB_Cost[[#This Row],[Section]],DATA!A:K,4,FALSE) -> 1.654 | W13: =LEFT(VLOOKUP(Table_TB_Cost[[#This Row],[Section]],Table5[],10,FALSE),2) -> FS | X13: =IF(Table_TB_Cost[[#This Row],[Weight/m]]<0.5,1*2.5,"") | Y13: N | Z13: =IF(Table_TB_Cost[[#This Row],[Roll?]]="Y",(2.5/Table_TB_Cost[[#This Row],[Weight/m]]/0.8)*2.5,"") | AA13: =SUM(VLOOKUP(Table_TB_Cost[[#This Row],[MPG]],TB_MPG,2,FALSE),Table_TB_Cost[[#This Row],[MPM Surcharge]],Table_TB_Cost[[#This Row],[Rolling Factor (Cost/0.8*2.5)]])*Table_TB_Cost[[#This Row],[Weight/m]]*Table_TB_Cost[[#This Row],[Length]] -> 550.2031 | AB13: =VLOOKUP(Table_TB_Cost[[#This Row],[Section]],AF:AJ,3,FALSE) -> 188.64125 | AC13: =IF($AB$2="Margin",Table_TB_Cost[[#This Row],[TOTAL COST]]/(1-$AC$2),Table_TB_Cost[[#This Row],[List Price]]*(1-$AC$2)) -> 377.2825 | AD13: =(Table_TB_Cost[[#This Row],[Metal Sell Price]]-Table_TB_Cost[[#This Row],[TOTAL COST]])/Table_TB_Cost[[#This Row],[Metal Sell Price]] -> 0.5 | AF13: ETB0010 | AG13: 995478 | AH13: 188.64125 | AI13: 186.49154 | AJ13: 141.60778 | AK13: 141.60806 | AL13: 134.11615 | AM13: 134.1165 | AN13: 133.97614 | AO13: 133.99846 | AP13: 138.22 | AQ13: 124.74 | AR13: 102.3 | AS13: 103.31 | AT13: 106.73 | AW13: =VLOOKUP(AF13,Table_TB_Cost[[Section]:[Basic Material]],2,FALSE) -> 46D TB - Hinge Door Stile | AX13: ETB0010 | AY13: =VLOOKUP(AX13,Table_TB_Cost[#All],5,FALSE) -> FS
A14: THERMAL BREAK | J14: FO | K14: 52.54 | L14: FutureLine 8 | M14: Updated 01.06.2026 | S14: ETB0011 | T14: =VLOOKUP(Table_TB_Cost[[#This Row],[Section]],DATA!A:K,2,FALSE) -> 46D TB - 89mm Door Rail | U14: 5 | V14: =VLOOKUP(Table_TB_Cost[[#This Row],[Section]],DATA!A:K,4,FALSE) -> 1.428 | W14: =LEFT(VLOOKUP(Table_TB_Cost[[#This Row],[Section]],Table5[],10,FALSE),2) -> FS | X14: =IF(Table_TB_Cost[[#This Row],[Weight/m]]<0.5,1*2.5,"") | Y14: N | Z14: =IF(Table_TB_Cost[[#This Row],[Roll?]]="Y",(2.5/Table_TB_Cost[[#This Row],[Weight/m]]/0.8)*2.5,"") | AA14: =SUM(VLOOKUP(Table_TB_Cost[[#This Row],[MPG]],TB_MPG,2,FALSE),Table_TB_Cost[[#This Row],[MPM Surcharge]],Table_TB_Cost[[#This Row],[Rolling Factor (Cost/0.8*2.5)]])*Table_TB_Cost[[#This Row],[Weight/m]]*Table_TB_Cost[[#This Row],[Length]] -> 475.0242 | AB14: =VLOOKUP(Table_TB_Cost[[#This Row],[Section]],AF:AJ,3,FALSE) -> 157.106 | AC14: =IF($AB$2="Margin",Table_TB_Cost[[#This Row],[TOTAL COST]]/(1-$AC$2),Table_TB_Cost[[#This Row],[List Price]]*(1-$AC$2)) -> 314.212 | AD14: =(Table_TB_Cost[[#This Row],[Metal Sell Price]]-Table_TB_Cost[[#This Row],[TOTAL COST]])/Table_TB_Cost[[#This Row],[Metal Sell Price]] -> 0.5 | AF14: ETB0011 | AG14: 995480 | AH14: 157.106 | AI14: 157.1072 | AJ14: 152.7 | AK14: 132.63 | AL14: 132.63 | AM14: 121.4 | AN14: 121.405 | AO14: 121.40553 | AP14: 122.49 | AQ14: 110.54 | AR14: 90.66 | AS14: 91.55 | AT14: 94.58 | AW14: =VLOOKUP(AF14,Table_TB_Cost[[Section]:[Basic Material]],2,FALSE) -> 46D TB - 89mm Door Rail | AX14: ETB0011 | AY14: =VLOOKUP(AX14,Table_TB_Cost[#All],5,FALSE) -> FS
A15: Breakpoints (kg) | B15: Margin Typ | C15: Mgn Min | D15: Mgn Max | E15: List Typ | F15: List Min | G15: List Max | J15: FP | K15: 56.02 | L15: FutureLine 9 | M15: Updated 01.06.2026 | S15: ETB0012 | T15: =VLOOKUP(Table_TB_Cost[[#This Row],[Section]],DATA!A:K,2,FALSE) -> 46D TB - 120mm Door Rail | U15: 5 | V15: =VLOOKUP(Table_TB_Cost[[#This Row],[Section]],DATA!A:K,4,FALSE) -> 1.732 | W15: =LEFT(VLOOKUP(Table_TB_Cost[[#This Row],[Section]],Table5[],10,FALSE),2) -> FQ | X15: =IF(Table_TB_Cost[[#This Row],[Weight/m]]<0.5,1*2.5,"") | Y15: N | Z15: =IF(Table_TB_Cost[[#This Row],[Roll?]]="Y",(2.5/Table_TB_Cost[[#This Row],[Weight/m]]/0.8)*2.5,"") | AA15: =SUM(VLOOKUP(Table_TB_Cost[[#This Row],[MPG]],TB_MPG,2,FALSE),Table_TB_Cost[[#This Row],[MPM Surcharge]],Table_TB_Cost[[#This Row],[Rolling Factor (Cost/0.8*2.5)]])*Table_TB_Cost[[#This Row],[Weight/m]]*Table_TB_Cost[[#This Row],[Length]] -> 515.5298 | AB15: =VLOOKUP(Table_TB_Cost[[#This Row],[Section]],AF:AJ,3,FALSE) -> 205.73841 | AC15: =IF($AB$2="Margin",Table_TB_Cost[[#This Row],[TOTAL COST]]/(1-$AC$2),Table_TB_Cost[[#This Row],[List Price]]*(1-$AC$2)) -> 411.47682 | AD15: =(Table_TB_Cost[[#This Row],[Metal Sell Price]]-Table_TB_Cost[[#This Row],[TOTAL COST]])/Table_TB_Cost[[#This Row],[Metal Sell Price]] -> 0.5 | AF15: ETB0012 | AG15: 995482 | AH15: 205.73841 | AI15: 205.73844 | AJ15: 123.845 | AK15: 123.845 | AL15: 123.84492 | AM15: 123.84458 | AN15: 123.84434 | AO15: 129.23222 | AP15: 134.84 | AQ15: 121.69 | AR15: 99.8 | AS15: 100.77 | AT15: 104.12 | AW15: =VLOOKUP(AF15,Table_TB_Cost[[Section]:[Basic Material]],2,FALSE) -> 46D TB - 120mm Door Rail | AX15: ETB0012 | AY15: =VLOOKUP(AX15,Table_TB_Cost[#All],5,FALSE) -> FQ
A16: 1000 | B16: 0.4 | C16: 0.38 | D16: 0.43 | E16: 0.47 | F16: 0.44 | G16: 0.5 | J16: FQ | K16: 59.53 | L16: FutureLine 10 | M16: Updated 01.06.2026 | S16: ETB0013 | T16: =VLOOKUP(Table_TB_Cost[[#This Row],[Section]],DATA!A:K,2,FALSE) -> 46D TB - 89mm Door Midrail | U16: 5 | V16: =VLOOKUP(Table_TB_Cost[[#This Row],[Section]],DATA!A:K,4,FALSE) -> 1.342 | W16: =LEFT(VLOOKUP(Table_TB_Cost[[#This Row],[Section]],Table5[],10,FALSE),2) -> FT | X16: =IF(Table_TB_Cost[[#This Row],[Weight/m]]<0.5,1*2.5,"") | Y16: N | Z16: =IF(Table_TB_Cost[[#This Row],[Roll?]]="Y",(2.5/Table_TB_Cost[[#This Row],[Weight/m]]/0.8)*2.5,"") | AA16: =SUM(VLOOKUP(Table_TB_Cost[[#This Row],[MPG]],TB_MPG,2,FALSE),Table_TB_Cost[[#This Row],[MPM Surcharge]],Table_TB_Cost[[#This Row],[Rolling Factor (Cost/0.8*2.5)]])*Table_TB_Cost[[#This Row],[Weight/m]]*Table_TB_Cost[[#This Row],[Length]] -> 469.9013 | AB16: =VLOOKUP(Table_TB_Cost[[#This Row],[Section]],AF:AJ,3,FALSE) -> 111.60571 | AC16: =IF($AB$2="Margin",Table_TB_Cost[[#This Row],[TOTAL COST]]/(1-$AC$2),Table_TB_Cost[[#This Row],[List Price]]*(1-$AC$2)) -> 223.21142 | AD16: =(Table_TB_Cost[[#This Row],[Metal Sell Price]]-Table_TB_Cost[[#This Row],[TOTAL COST]])/Table_TB_Cost[[#This Row],[Metal Sell Price]] -> 0.5 | AF16: ETB0013 | AG16: 995484 | AH16: 111.60571 | AI16: 111.605 | AJ16: 111.60571 | AK16: 111.60611 | AL16: 111.60667 | AM16: 111.60658 | AN16: 111.60667 | AO16: 111.60676 | AP16: 119.1 | AQ16: 107.49 | AR16: 88.15 | AS16: 89.02 | AT16: 91.97 | AW16: =VLOOKUP(AF16,Table_TB_Cost[[Section]:[Basic Material]],2,FALSE) -> 46D TB - 89mm Door Midrail | AX16: ETB0013 | AY16: =VLOOKUP(AX16,Table_TB_Cost[#All],5,FALSE) -> FT
A17: 2000 | B17: 0.35 | C17: 0.33 | D17: 0.38 | E17: 0.52 | F17: 0.48 | G17: 0.54 | J17: FR | K17: 63.04 | L17: FutureLine 11 | M17: Updated 01.06.2026 | S17: ETB0014 | T17: =VLOOKUP(Table_TB_Cost[[#This Row],[Section]],DATA!A:K,2,FALSE) -> 46D TB - 120mm Door Midrail | U17: 5 | V17: =VLOOKUP(Table_TB_Cost[[#This Row],[Section]],DATA!A:K,4,FALSE) -> 1.644 | W17: =LEFT(VLOOKUP(Table_TB_Cost[[#This Row],[Section]],Table5[],10,FALSE),2) -> FR | X17: =IF(Table_TB_Cost[[#This Row],[Weight/m]]<0.5,1*2.5,"") | Y17: N | Z17: =IF(Table_TB_Cost[[#This Row],[Roll?]]="Y",(2.5/Table_TB_Cost[[#This Row],[Weight/m]]/0.8)*2.5,"") | AA17: =SUM(VLOOKUP(Table_TB_Cost[[#This Row],[MPG]],TB_MPG,2,FALSE),Table_TB_Cost[[#This Row],[MPM Surcharge]],Table_TB_Cost[[#This Row],[Rolling Factor (Cost/0.8*2.5)]])*Table_TB_Cost[[#This Row],[Weight/m]]*Table_TB_Cost[[#This Row],[Length]] -> 518.1888 | AB17: =VLOOKUP(Table_TB_Cost[[#This Row],[Section]],AF:AJ,3,FALSE) -> 100.8675 | AC17: =IF($AB$2="Margin",Table_TB_Cost[[#This Row],[TOTAL COST]]/(1-$AC$2),Table_TB_Cost[[#This Row],[List Price]]*(1-$AC$2)) -> 201.735 | AD17: =(Table_TB_Cost[[#This Row],[Metal Sell Price]]-Table_TB_Cost[[#This Row],[TOTAL COST]])/Table_TB_Cost[[#This Row],[Metal Sell Price]] -> 0.5 | AF17: ETB0014 | AG17: 995486 | AH17: 100.8675 | AI17: 100.868 | AJ17: 100.8685 | AK17: 100.86857 | AL17: 100.86857 | AM17: 100.86879 | AN17: 100.86886 | AO17: 100.86894 | AP17: 131.45 | AQ17: 118.63 | AR17: 97.29 | AS17: 98.24 | AT17: 101.5 | AW17: =VLOOKUP(AF17,Table_TB_Cost[[Section]:[Basic Material]],2,FALSE) -> 46D TB - 120mm Door Midrail | AX17: ETB0014 | AY17: =VLOOKUP(AX17,Table_TB_Cost[#All],5,FALSE) -> FR
A18: 3000 | B18: 0.32 | C18: 0.3 | D18: 0.35 | E18: 0.54 | F18: 0.5 | G18: 0.56 | J18: FS | K18: 66.53 | L18: FutureLine 12 | M18: Updated 01.06.2026 | S18: ETB0015 | T18: =VLOOKUP(Table_TB_Cost[[#This Row],[Section]],DATA!A:K,2,FALSE) -> 54W TB - Awning/Casement Sash | U18: 6.5 | V18: =VLOOKUP(Table_TB_Cost[[#This Row],[Section]],DATA!A:K,4,FALSE) -> 1.04 | W18: =LEFT(VLOOKUP(Table_TB_Cost[[#This Row],[Section]],Table5[],10,FALSE),2) -> FL | X18: =IF(Table_TB_Cost[[#This Row],[Weight/m]]<0.5,1*2.5,"") | Y18: Y | Z18: =IF(Table_TB_Cost[[#This Row],[Roll?]]="Y",(2.5/Table_TB_Cost[[#This Row],[Weight/m]]/0.8)*2.5,"") -> 7.5120192 | AA18: =SUM(VLOOKUP(Table_TB_Cost[[#This Row],[MPG]],TB_MPG,2,FALSE),Table_TB_Cost[[#This Row],[MPM Surcharge]],Table_TB_Cost[[#This Row],[Rolling Factor (Cost/0.8*2.5)]])*Table_TB_Cost[[#This Row],[Weight/m]]*Table_TB_Cost[[#This Row],[Length]] -> 334.83645 | AB18: =VLOOKUP(Table_TB_Cost[[#This Row],[Section]],AF:AJ,3,FALSE) -> 93.67137 | AC18: =IF($AB$2="Margin",Table_TB_Cost[[#This Row],[TOTAL COST]]/(1-$AC$2),Table_TB_Cost[[#This Row],[List Price]]*(1-$AC$2)) -> 187.34274 | AD18: =(Table_TB_Cost[[#This Row],[Metal Sell Price]]-Table_TB_Cost[[#This Row],[TOTAL COST]])/Table_TB_Cost[[#This Row],[Metal Sell Price]] -> 0.5 | AF18: ETB0015 | AG18: 734873 | AH18: 93.67137 | AI18: 90.78595 | AJ18: 91.21444 | AK18: 89.41768 | AL18: 88.39341 | AM18: 85.34587 | AN18: 89.58864 | AO18: 90.91705 | AP18: 85.84 | AQ18: 80.18 | AR18: 83.04 | AS18: 83.85 | AT18: 86.63 | AW18: =VLOOKUP(AF18,Table_TB_Cost[[Section]:[Basic Material]],2,FALSE) -> 54W TB - Awning/Casement Sash | AX18: ETB0015 | AY18: =VLOOKUP(AX18,Table_TB_Cost[#All],5,FALSE) -> FL
A19: 5000 | B19: 0.29 | C19: 0.27 | D19: 0.32 | E19: 0.56 | F19: 0.52 | G19: 0.58 | J19: FT | K19: 70.03 | L19: FutureLine 13 | M19: Updated 01.06.2026 | S19: ETB0016 | T19: =VLOOKUP(Table_TB_Cost[[#This Row],[Section]],DATA!A:K,2,FALSE) -> 425TB - Sub Head 100x50 | U19: 6.5 | V19: =VLOOKUP(Table_TB_Cost[[#This Row],[Section]],DATA!A:K,4,FALSE) -> 1.585 | W19: =LEFT(VLOOKUP(Table_TB_Cost[[#This Row],[Section]],Table5[],10,FALSE),2) -> FJ | X19: =IF(Table_TB_Cost[[#This Row],[Weight/m]]<0.5,1*2.5,"") | Y19: Y | Z19: =IF(Table_TB_Cost[[#This Row],[Roll?]]="Y",(2.5/Table_TB_Cost[[#This Row],[Weight/m]]/0.8)*2.5,"") -> 4.9290221 | AA19: =SUM(VLOOKUP(Table_TB_Cost[[#This Row],[MPG]],TB_MPG,2,FALSE),Table_TB_Cost[[#This Row],[MPM Surcharge]],Table_TB_Cost[[#This Row],[Rolling Factor (Cost/0.8*2.5)]])*Table_TB_Cost[[#This Row],[Weight/m]]*Table_TB_Cost[[#This Row],[Length]] -> 411.47177 | AB19: =VLOOKUP(Table_TB_Cost[[#This Row],[Section]],AF:AJ,3,FALSE) -> 112.75537 | AC19: =IF($AB$2="Margin",Table_TB_Cost[[#This Row],[TOTAL COST]]/(1-$AC$2),Table_TB_Cost[[#This Row],[List Price]]*(1-$AC$2)) -> 225.51074 | AD19: =(Table_TB_Cost[[#This Row],[Metal Sell Price]]-Table_TB_Cost[[#This Row],[TOTAL COST]])/Table_TB_Cost[[#This Row],[Metal Sell Price]] -> 0.5 | AF19: ETB0016 | AG19: 734492 | AH19: 112.75537 | AI19: 111.97327 | AJ19: 109.83882 | AK19: 103.98821 | AL19: 103.98841 | AM19: 101.02 | AN19: 109.32559 | AO19: 101.11394 | AP19: 108.09 | AQ19: 98.93 | AR19: 85.3 | AS19: 86.14 | AT19: 89 | AW19: =VLOOKUP(AF19,Table_TB_Cost[[Section]:[Basic Material]],2,FALSE) -> 425TB - Sub Head 100x50 | AX19: ETB0016 | AY19: =VLOOKUP(AX19,Table_TB_Cost[#All],5,FALSE) -> FJ
A20: 7000 | B20: 0.27 | C20: 0.25 | D20: 0.3 | E20: 0.58 | F20: 0.53 | G20: 0.59 | J20: FU | K20: 73.54 | L20: FutureLine 14 | M20: Updated 01.06.2026 | S20: ETB0017 | T20: =VLOOKUP(Table_TB_Cost[[#This Row],[Section]],DATA!A:K,2,FALSE) -> 425TB - Sub Sill 100 Flat Leg | U20: 6.5 | V20: =VLOOKUP(Table_TB_Cost[[#This Row],[Section]],DATA!A:K,4,FALSE) -> 1.516 | W20: =LEFT(VLOOKUP(Table_TB_Cost[[#This Row],[Section]],Table5[],10,FALSE),2) -> FL | X20: =IF(Table_TB_Cost[[#This Row],[Weight/m]]<0.5,1*2.5,"") | Y20: Y | Z20: =IF(Table_TB_Cost[[#This Row],[Roll?]]="Y",(2.5/Table_TB_Cost[[#This Row],[Weight/m]]/0.8)*2.5,"") -> 5.1533641 | AA20: =SUM(VLOOKUP(Table_TB_Cost[[#This Row],[MPG]],TB_MPG,2,FALSE),Table_TB_Cost[[#This Row],[MPM Surcharge]],Table_TB_Cost[[#This Row],[Rolling Factor (Cost/0.8*2.5)]])*Table_TB_Cost[[#This Row],[Weight/m]]*Table_TB_Cost[[#This Row],[Length]] -> 464.84633 | AB20: =VLOOKUP(Table_TB_Cost[[#This Row],[Section]],AF:AJ,3,FALSE) -> 129.00244 | AC20: =IF($AB$2="Margin",Table_TB_Cost[[#This Row],[TOTAL COST]]/(1-$AC$2),Table_TB_Cost[[#This Row],[List Price]]*(1-$AC$2)) -> 258.00488 | AD20: =(Table_TB_Cost[[#This Row],[Metal Sell Price]]-Table_TB_Cost[[#This Row],[TOTAL COST]])/Table_TB_Cost[[#This Row],[Metal Sell Price]] -> 0.5 | AF20: ETB0017 | AG20: 734493 | AH20: 129.00244 | AI20: 124.83912 | AJ20: 124.43107 | AK20: 119.68811 | AL20: 116.90716 | AM20: 113.25352 | AN20: 118.28067 | AO20: 126.14889 | AP20: 120.29 | AQ20: 110.89 | AR20: 81.69 | AS20: 82.49 | AT20: 85.22 | AW20: =VLOOKUP(AF20,Table_TB_Cost[[Section]:[Basic Material]],2,FALSE) -> 425TB - Sub Sill 100 Flat Leg | AX20: ETB0017 | AY20: =VLOOKUP(AX20,Table_TB_Cost[#All],5,FALSE) -> FL
A21: 10000 | B21: 0.25 | C21: 0.23 | D21: 0.28 | E21: 0.59 | F21: 0.54 | G21: 0.6 | J21: FV | K21: 77.04 | L21: FutureLine 15 | M21: Updated 01.06.2026 | S21: ETB0018 | T21: =VLOOKUP(Table_TB_Cost[[#This Row],[Section]],DATA!A:K,2,FALSE) -> 425TB - Sub Frame 2-Pc Base 100x50 | U21: 6.5 | V21: =VLOOKUP(Table_TB_Cost[[#This Row],[Section]],DATA!A:K,4,FALSE) -> 1.414 | W21: =LEFT(VLOOKUP(Table_TB_Cost[[#This Row],[Section]],Table5[],10,FALSE),2) -> FJ | X21: =IF(Table_TB_Cost[[#This Row],[Weight/m]]<0.5,1*2.5,"") | Y21: Y | Z21: =IF(Table_TB_Cost[[#This Row],[Roll?]]="Y",(2.5/Table_TB_Cost[[#This Row],[Weight/m]]/0.8)*2.5,"") -> 5.5251061 | AA21: =SUM(VLOOKUP(Table_TB_Cost[[#This Row],[MPG]],TB_MPG,2,FALSE),Table_TB_Cost[[#This Row],[MPM Surcharge]],Table_TB_Cost[[#This Row],[Rolling Factor (Cost/0.8*2.5)]])*Table_TB_Cost[[#This Row],[Weight/m]]*Table_TB_Cost[[#This Row],[Length]] -> 372.55816 | AB21: =VLOOKUP(Table_TB_Cost[[#This Row],[Section]],AF:AJ,3,FALSE) -> 105.59873 | AC21: =IF($AB$2="Margin",Table_TB_Cost[[#This Row],[TOTAL COST]]/(1-$AC$2),Table_TB_Cost[[#This Row],[List Price]]*(1-$AC$2)) -> 211.19746 | AD21: =(Table_TB_Cost[[#This Row],[Metal Sell Price]]-Table_TB_Cost[[#This Row],[TOTAL COST]])/Table_TB_Cost[[#This Row],[Metal Sell Price]] -> 0.5 | AF21: ETB0018 | AG21: 734494 | AH21: 105.59873 | AI21: 104.73333 | AJ21: 95.57253 | AK21: 95.57252 | AL21: 95.57255 | AM21: 95.57252 | AN21: 97.64459 | AO21: 97.60547 | AP21: 100.1 | AQ21: 92.01 | AR21: 74.53 | AS21: 75.26 | AT21: 77.76 | AW21: =VLOOKUP(AF21,Table_TB_Cost[[Section]:[Basic Material]],2,FALSE) -> 425TB - Sub Frame 2-Pc Base 100x50 | AX21: ETB0018 | AY21: =VLOOKUP(AX21,Table_TB_Cost[#All],5,FALSE) -> FJ
J22: FW | K22: 80.55 | L22: FutureLine 16 | M22: Updated 01.06.2026 | S22: ETB0019 | T22: =VLOOKUP(Table_TB_Cost[[#This Row],[Section]],DATA!A:K,2,FALSE) -> 440TB - Sub Frame 2-PC Bead | W22: =LEFT(VLOOKUP(Table_TB_Cost[[#This Row],[Section]],Table5[],10,FALSE),2) -> BB | X22: =IF(Table_TB_Cost[[#This Row],[Weight/m]]<0.5,1*2.5,"") -> 2.5 | AB22: =VLOOKUP(Table_TB_Cost[[#This Row],[Section]],AF:AJ,3,FALSE) -> 0 | AF22: ETB0019 | AW22: =VLOOKUP(AF22,Table_TB_Cost[[Section]:[Basic Material]],2,FALSE) -> 440TB - Sub Frame 2-PC Bead | AX22: ETB0019 | AY22: =VLOOKUP(AX22,Table_TB_Cost[#All],5,FALSE) -> BB
J23: LI | K23: 97.88 | L23: KIT 10 | M23: Updated 01.06.2026 | S23: ETB0020 | T23: =VLOOKUP(Table_TB_Cost[[#This Row],[Section]],DATA!A:K,2,FALSE) -> 46D TB - 85mm Pivot Door Stile | U23: 5 | V23: =VLOOKUP(Table_TB_Cost[[#This Row],[Section]],DATA!A:K,4,FALSE) -> 2.054 | W23: =LEFT(VLOOKUP(Table_TB_Cost[[#This Row],[Section]],Table5[],10,FALSE),2) -> FK | X23: =IF(Table_TB_Cost[[#This Row],[Weight/m]]<0.5,1*2.5,"") | Y23: N | Z23: =IF(Table_TB_Cost[[#This Row],[Roll?]]="Y",(2.5/Table_TB_Cost[[#This Row],[Weight/m]]/0.8)*2.5,"") | AA23: =SUM(VLOOKUP(Table_TB_Cost[[#This Row],[MPG]],TB_MPG,2,FALSE),Table_TB_Cost[[#This Row],[MPM Surcharge]],Table_TB_Cost[[#This Row],[Rolling Factor (Cost/0.8*2.5)]])*Table_TB_Cost[[#This Row],[Weight/m]]*Table_TB_Cost[[#This Row],[Length]] -> 395.6004 | AB23: =VLOOKUP(Table_TB_Cost[[#This Row],[Section]],AF:AJ,3,FALSE) -> 226.53228 | AC23: =IF($AB$2="Margin",Table_TB_Cost[[#This Row],[TOTAL COST]]/(1-$AC$2),Table_TB_Cost[[#This Row],[List Price]]*(1-$AC$2)) -> 453.06456 | AD23: =(Table_TB_Cost[[#This Row],[Metal Sell Price]]-Table_TB_Cost[[#This Row],[TOTAL COST]])/Table_TB_Cost[[#This Row],[Metal Sell Price]] -> 0.5 | AF23: ETB0020 | AG23: 999221 | AH23: 226.53228 | AI23: 232.55453 | AJ23: 182.88333 | AK23: 154.24714 | AL23: 145.4225 | AM23: 145.42265 | AN23: 145.42255 | AO23: 90.21 | AP23: 101.5 | AQ23: 91.6 | AR23: 75.12 | AS23: 75.86 | AT23: 78.37 | AW23: =VLOOKUP(AF23,Table_TB_Cost[[Section]:[Basic Material]],2,FALSE) -> 46D TB - 85mm Pivot Door Stile | AX23: ETB0020 | AY23: =VLOOKUP(AX23,Table_TB_Cost[#All],5,FALSE) -> FK
J24: BU | K24: 25.82 | L24: Com Arch 5 | M24: Updated 01.06.2026 | S24: ETB0021 | T24: =VLOOKUP(Table_TB_Cost[[#This Row],[Section]],DATA!A:K,2,FALSE) -> 46D TB - 120mm Pivot Door Stile | U24: 5 | V24: =VLOOKUP(Table_TB_Cost[[#This Row],[Section]],DATA!A:K,4,FALSE) -> 2.536 | W24: =LEFT(VLOOKUP(Table_TB_Cost[[#This Row],[Section]],Table5[],10,FALSE),2) -> FQ | X24: =IF(Table_TB_Cost[[#This Row],[Weight/m]]<0.5,1*2.5,"") | Y24: N | Z24: =IF(Table_TB_Cost[[#This Row],[Roll?]]="Y",(2.5/Table_TB_Cost[[#This Row],[Weight/m]]/0.8)*2.5,"") | AA24: =SUM(VLOOKUP(Table_TB_Cost[[#This Row],[MPG]],TB_MPG,2,FALSE),Table_TB_Cost[[#This Row],[MPM Surcharge]],Table_TB_Cost[[#This Row],[Rolling Factor (Cost/0.8*2.5)]])*Table_TB_Cost[[#This Row],[Weight/m]]*Table_TB_Cost[[#This Row],[Length]] -> 754.8404 | AB24: =VLOOKUP(Table_TB_Cost[[#This Row],[Section]],AF:AJ,3,FALSE) -> 258.44962 | AC24: =IF($AB$2="Margin",Table_TB_Cost[[#This Row],[TOTAL COST]]/(1-$AC$2),Table_TB_Cost[[#This Row],[List Price]]*(1-$AC$2)) -> 516.89924 | AD24: =(Table_TB_Cost[[#This Row],[Metal Sell Price]]-Table_TB_Cost[[#This Row],[TOTAL COST]])/Table_TB_Cost[[#This Row],[Metal Sell Price]] -> 0.5 | AF24: ETB0021 | AG24: 999223 | AH24: 258.44962 | AI24: 272.33 | AJ24: 236.065 | AK24: 164.832 | AL24: 164.83262 | AM24: 164.83269 | AN24: 164.83271 | AO24: 178.995 | AP24: 187.73 | AQ24: 169.43 | AR24: 138.95 | AS24: 140.31 | AT24: 144.97 | AW24: =VLOOKUP(AF24,Table_TB_Cost[[Section]:[Basic Material]],2,FALSE) -> 46D TB - 120mm Pivot Door Stile | AX24: ETB0021 | AY24: =VLOOKUP(AX24,Table_TB_Cost[#All],5,FALSE) -> FQ
J25: U3 | K25: 25.85 | L25: Artisan Panoramic Dr | M25: Updated 01.06.2026 | S25: ETB0022 | T25: =VLOOKUP(Table_TB_Cost[[#This Row],[Section]],DATA!A:K,2,FALSE) -> 46D TB - Meeting Bolt Stile | U25: 5 | V25: =VLOOKUP(Table_TB_Cost[[#This Row],[Section]],DATA!A:K,4,FALSE) -> 2.082 | W25: =LEFT(VLOOKUP(Table_TB_Cost[[#This Row],[Section]],Table5[],10,FALSE),2) -> FP | X25: =IF(Table_TB_Cost[[#This Row],[Weight/m]]<0.5,1*2.5,"") | Y25: N | Z25: =IF(Table_TB_Cost[[#This Row],[Roll?]]="Y",(2.5/Table_TB_Cost[[#This Row],[Weight/m]]/0.8)*2.5,"") | AA25: =SUM(VLOOKUP(Table_TB_Cost[[#This Row],[MPG]],TB_MPG,2,FALSE),Table_TB_Cost[[#This Row],[MPM Surcharge]],Table_TB_Cost[[#This Row],[Rolling Factor (Cost/0.8*2.5)]])*Table_TB_Cost[[#This Row],[Weight/m]]*Table_TB_Cost[[#This Row],[Length]] -> 583.1682 | AB25: =VLOOKUP(Table_TB_Cost[[#This Row],[Section]],AF:AJ,3,FALSE) -> 209.13118 | AC25: =IF($AB$2="Margin",Table_TB_Cost[[#This Row],[TOTAL COST]]/(1-$AC$2),Table_TB_Cost[[#This Row],[List Price]]*(1-$AC$2)) -> 418.26236 | AD25: =(Table_TB_Cost[[#This Row],[Metal Sell Price]]-Table_TB_Cost[[#This Row],[TOTAL COST]])/Table_TB_Cost[[#This Row],[Metal Sell Price]] -> 0.5 | AF25: ETB0022 | AG25: 1008782 | AH25: 209.13118 | AI25: 209.13103 | AJ25: 221 | AK25: 162.95 | AL25: 135.59 | AM25: 135.59 | AN25: 135.59 | AO25: 135.59 | AP25: 152.56 | AQ25: 137.68 | AR25: 112.92 | AS25: 114.02 | AT25: 117.81 | AW25: =VLOOKUP(AF25,Table_TB_Cost[[Section]:[Basic Material]],2,FALSE) -> 46D TB - Meeting Bolt Stile | AX25: ETB0022 | AY25: =VLOOKUP(AX25,Table_TB_Cost[#All],5,FALSE) -> FP
A26: POWDER COST TABLE | B26: edit powder costs here (red text only) | S26: ETB0023 | T26: =VLOOKUP(Table_TB_Cost[[#This Row],[Section]],DATA!A:K,2,FALSE) -> 46D TB - Meeting Lock Stile | U26: 5 | V26: =VLOOKUP(Table_TB_Cost[[#This Row],[Section]],DATA!A:K,4,FALSE) -> 2.122 | W26: =LEFT(VLOOKUP(Table_TB_Cost[[#This Row],[Section]],Table5[],10,FALSE),2) -> FP | X26: =IF(Table_TB_Cost[[#This Row],[Weight/m]]<0.5,1*2.5,"") | Y26: N | Z26: =IF(Table_TB_Cost[[#This Row],[Roll?]]="Y",(2.5/Table_TB_Cost[[#This Row],[Weight/m]]/0.8)*2.5,"") | AA26: =SUM(VLOOKUP(Table_TB_Cost[[#This Row],[MPG]],TB_MPG,2,FALSE),Table_TB_Cost[[#This Row],[MPM Surcharge]],Table_TB_Cost[[#This Row],[Rolling Factor (Cost/0.8*2.5)]])*Table_TB_Cost[[#This Row],[Weight/m]]*Table_TB_Cost[[#This Row],[Length]] -> 594.3722 | AB26: =VLOOKUP(Table_TB_Cost[[#This Row],[Section]],AF:AJ,3,FALSE) -> 218.715 | AC26: =IF($AB$2="Margin",Table_TB_Cost[[#This Row],[TOTAL COST]]/(1-$AC$2),Table_TB_Cost[[#This Row],[List Price]]*(1-$AC$2)) -> 437.43 | AD26: =(Table_TB_Cost[[#This Row],[Metal Sell Price]]-Table_TB_Cost[[#This Row],[TOTAL COST]])/Table_TB_Cost[[#This Row],[Metal Sell Price]] -> 0.5 | AF26: ETB0023 | AG26: 1008783 | AH26: 218.715 | AI26: 218.712 | AJ26: 195.78773 | AK26: 144.66727 | AL26: 144.6676 | AM26: 144.66818 | AN26: 144.66843 | AO26: 111.78 | AP26: 152.76 | AQ26: 137.68 | AR26: 113.06 | AS26: 114.17 | AT26: 117.96 | AW26: =VLOOKUP(AF26,Table_TB_Cost[[Section]:[Basic Material]],2,FALSE) -> 46D TB - Meeting Lock Stile | AX26: ETB0023 | AY26: =VLOOKUP(AX26,Table_TB_Cost[#All],5,FALSE) -> FP
A27: Type | B27: Vendor | C27: AP/PP | D27: Group 1 | E27: Group 2 | F27: Group 3 | G27: Group 4 | H27: Group 5 | I27: 20um Clear | J27: 25um Clear | K27: Group POA | S27: ETB0024 | T27: =VLOOKUP(Table_TB_Cost[[#This Row],[Section]],DATA!A:K,2,FALSE) -> Ftrline - Threshold | U27: 5.8 | V27: =VLOOKUP(Table_TB_Cost[[#This Row],[Section]],DATA!A:K,4,FALSE) -> 1.952 | W27: =LEFT(VLOOKUP(Table_TB_Cost[[#This Row],[Section]],Table5[],10,FALSE),2) -> FO | X27: =IF(Table_TB_Cost[[#This Row],[Weight/m]]<0.5,1*2.5,"") | Y27: N | Z27: =IF(Table_TB_Cost[[#This Row],[Roll?]]="Y",(2.5/Table_TB_Cost[[#This Row],[Weight/m]]/0.8)*2.5,"") | AA27: =SUM(VLOOKUP(Table_TB_Cost[[#This Row],[MPG]],TB_MPG,2,FALSE),Table_TB_Cost[[#This Row],[MPM Surcharge]],Table_TB_Cost[[#This Row],[Rolling Factor (Cost/0.8*2.5)]])*Table_TB_Cost[[#This Row],[Weight/m]]*Table_TB_Cost[[#This Row],[Length]] -> 594.83686 | AB27: =VLOOKUP(Table_TB_Cost[[#This Row],[Section]],AF:AJ,3,FALSE) -> 144.86481 | AC27: =IF($AB$2="Margin",Table_TB_Cost[[#This Row],[TOTAL COST]]/(1-$AC$2),Table_TB_Cost[[#This Row],[List Price]]*(1-$AC$2)) -> 289.72962 | AD27: =(Table_TB_Cost[[#This Row],[Metal Sell Price]]-Table_TB_Cost[[#This Row],[TOTAL COST]])/Table_TB_Cost[[#This Row],[Metal Sell Price]] -> 0.5 | AF27: ETB0024 | AG27: 1014589 | AH27: 144.86481 | AI27: 144.86529 | AJ27: 145.27707 | AK27: 145.27733 | AL27: 139.12167 | AM27: 139.121 | AN27: 139.12091 | AO27: 139.12067 | AP27: 152.64 | AQ27: 137.75 | AR27: 112.97 | AS27: 114.08 | AT27: 108.45 | AW27: =VLOOKUP(AF27,Table_TB_Cost[[Section]:[Basic Material]],2,FALSE) -> Ftrline - Threshold | AX27: ETB0024 | AY27: =VLOOKUP(AX27,Table_TB_Cost[#All],5,FALSE) -> FO
A28: Powder | B28: Capral P&P - Bremer (AP) | C28: AP | D28: 6.22 | E28: 6.89 | F28: 7.44 | G28: 11.15 | H28: 12.64 | K28: ='3.Edit Pricing'!$B$42 -> 99 | L28: Updated 02.02.2026 | S28: ETB0025 | T28: =VLOOKUP(Table_TB_Cost[[#This Row],[Section]],DATA!A:K,2,FALSE) -> 425TB - Female Mullion/Narrow Frame V2 | U28: 6.5 | V28: =VLOOKUP(Table_TB_Cost[[#This Row],[Section]],DATA!A:K,4,FALSE) -> 1.811 | W28: =LEFT(VLOOKUP(Table_TB_Cost[[#This Row],[Section]],Table5[],10,FALSE),2) -> FJ | X28: =IF(Table_TB_Cost[[#This Row],[Weight/m]]<0.5,1*2.5,"") | Y28: Y | Z28: =IF(Table_TB_Cost[[#This Row],[Roll?]]="Y",(2.5/Table_TB_Cost[[#This Row],[Weight/m]]/0.8)*2.5,"") -> 4.313915 | AA28: =SUM(VLOOKUP(Table_TB_Cost[[#This Row],[MPG]],TB_MPG,2,FALSE),Table_TB_Cost[[#This Row],[MPM Surcharge]],Table_TB_Cost[[#This Row],[Rolling Factor (Cost/0.8*2.5)]])*Table_TB_Cost[[#This Row],[Weight/m]]*Table_TB_Cost[[#This Row],[Length]] -> 462.90146 | AB28: =VLOOKUP(Table_TB_Cost[[#This Row],[Section]],AF:AJ,3,FALSE) -> 130.99795 | AC28: =IF($AB$2="Margin",Table_TB_Cost[[#This Row],[TOTAL COST]]/(1-$AC$2),Table_TB_Cost[[#This Row],[List Price]]*(1-$AC$2)) -> 261.9959 | AD28: =(Table_TB_Cost[[#This Row],[Metal Sell Price]]-Table_TB_Cost[[#This Row],[TOTAL COST]])/Table_TB_Cost[[#This Row],[Metal Sell Price]] -> 0.5 | AF28: EP14756 | AG28: 1013954 | AH28: 14.21 | AI28: 14.21 | AJ28: 14.21 | AK28: 14.21 | AL28: 14.21 | AM28: 14.21 | AN28: 14.21 | AO28: 14.21 | AP28: 15.78 | AQ28: 13.67 | AW28: =VLOOKUP(AF28,Table_TB_Cost[[Section]:[Basic Material]],2,FALSE) -> 425TB - Flat Filler | AX28: EP14756 | AY28: =VLOOKUP(AX28,Table_TB_Cost[#All],5,FALSE) -> FH
A29: Powder | B29: Capral P&P - Campbellfield (AP) | C29: AP | D29: 6.45 | E29: 6.89 | F29: 9.42 | G29: 11.45 | H29: 12.64 | K29: ='3.Edit Pricing'!$B$42 -> 99 | L29: Updated 02.02.2026 | S29: ETB0026 | T29: =VLOOKUP(Table_TB_Cost[[#This Row],[Section]],DATA!A:K,2,FALSE) -> 425TB - Male Mullion V2 | U29: 6.5 | V29: =VLOOKUP(Table_TB_Cost[[#This Row],[Section]],DATA!A:K,4,FALSE) -> 2.297 | W29: =LEFT(VLOOKUP(Table_TB_Cost[[#This Row],[Section]],Table5[],10,FALSE),2) -> FJ | X29: =IF(Table_TB_Cost[[#This Row],[Weight/m]]<0.5,1*2.5,"") | Y29: Y | Z29: =IF(Table_TB_Cost[[#This Row],[Roll?]]="Y",(2.5/Table_TB_Cost[[#This Row],[Weight/m]]/0.8)*2.5,"") -> 3.4011754 | AA29: =SUM(VLOOKUP(Table_TB_Cost[[#This Row],[MPG]],TB_MPG,2,FALSE),Table_TB_Cost[[#This Row],[MPM Surcharge]],Table_TB_Cost[[#This Row],[Rolling Factor (Cost/0.8*2.5)]])*Table_TB_Cost[[#This Row],[Weight/m]]*Table_TB_Cost[[#This Row],[Length]] -> 573.49806 | AB29: =VLOOKUP(Table_TB_Cost[[#This Row],[Section]],AF:AJ,3,FALSE) -> 148.92147 | AC29: =IF($AB$2="Margin",Table_TB_Cost[[#This Row],[TOTAL COST]]/(1-$AC$2),Table_TB_Cost[[#This Row],[List Price]]*(1-$AC$2)) -> 297.84294 | AD29: =(Table_TB_Cost[[#This Row],[Metal Sell Price]]-Table_TB_Cost[[#This Row],[TOTAL COST]])/Table_TB_Cost[[#This Row],[Metal Sell Price]] -> 0.5 | AF29: ETB0030 | AG29: 1014868 | AH29: 556.3768 | AI29: 556.3768 | AJ29: 556.3768 | AK29: 556.3768 | AL29: 556.3768 | AM29: 556.37679 | AN29: 556.377 | AO29: 556.377 | AP29: 410.94304 | AQ29: 332.38 | AW29: =VLOOKUP(AF29,Table_TB_Cost[[Section]:[Basic Material]],2,FALSE) -> Ftrline - LS/SD/SW - Head/Sill/Jamb | AX29: ETB0030 | AY29: =VLOOKUP(AX29,Table_TB_Cost[#All],5,FALSE) -> LI
A30: Powder | B30: Capral P&P - Canningvale (PP) | C30: PP | D30: 6.89 | E30: 9.45 | F30: 10.95 | G30: 16.43 | H30: 18.62 | K30: ='3.Edit Pricing'!$B$42 -> 99 | L30: Updated 02.02.2026 | S30: ETB0027 | T30: =VLOOKUP(Table_TB_Cost[[#This Row],[Section]],DATA!A:K,2,FALSE) -> 425TB - Frame | U30: 6.5 | V30: =VLOOKUP(Table_TB_Cost[[#This Row],[Section]],DATA!A:K,4,FALSE) -> 1.74 | W30: =LEFT(VLOOKUP(Table_TB_Cost[[#This Row],[Section]],Table5[],10,FALSE),2) -> FJ | X30: =IF(Table_TB_Cost[[#This Row],[Weight/m]]<0.5,1*2.5,"") | Y30: Y | Z30: =IF(Table_TB_Cost[[#This Row],[Roll?]]="Y",(2.5/Table_TB_Cost[[#This Row],[Weight/m]]/0.8)*2.5,"") -> 4.4899425 | AA30: =SUM(VLOOKUP(Table_TB_Cost[[#This Row],[MPG]],TB_MPG,2,FALSE),Table_TB_Cost[[#This Row],[MPM Surcharge]],Table_TB_Cost[[#This Row],[Rolling Factor (Cost/0.8*2.5)]])*Table_TB_Cost[[#This Row],[Weight/m]]*Table_TB_Cost[[#This Row],[Length]] -> 446.74435 | AB30: =VLOOKUP(Table_TB_Cost[[#This Row],[Section]],AF:AJ,3,FALSE) -> 125.43021 | AC30: =IF($AB$2="Margin",Table_TB_Cost[[#This Row],[TOTAL COST]]/(1-$AC$2),Table_TB_Cost[[#This Row],[List Price]]*(1-$AC$2)) -> 250.86042 | AD30: =(Table_TB_Cost[[#This Row],[Metal Sell Price]]-Table_TB_Cost[[#This Row],[TOTAL COST]])/Table_TB_Cost[[#This Row],[Metal Sell Price]] -> 0.5 | AF30: ETB0031 | AG30: 1014870 | AH30: 310.43558 | AI30: 310.43558 | AJ30: 310.43558 | AK30: 310.43558 | AL30: 310.43558 | AM30: 310.43563 | AN30: 310.4357 | AO30: 310.43585 | AP30: 300.71986 | AQ30: 243.23 | AW30: =VLOOKUP(AF30,Table_TB_Cost[[Section]:[Basic Material]],2,FALSE) -> Ftrline - LS/SD/SW - Sash | AX30: ETB0031 | AY30: =VLOOKUP(AX30,Table_TB_Cost[#All],5,FALSE) -> LI
A31: Powder | B31: AAF powdercoat | C31: AP | D31: 5.06 | E31: 6.2 | F31: 7.27 | K31: ='3.Edit Pricing'!$B$42 -> 99 | S31: ETB0028 | T31: =VLOOKUP(Table_TB_Cost[[#This Row],[Section]],DATA!A:K,2,FALSE) -> 425TB - Pocket Filler | U31: 6.5 | V31: =VLOOKUP(Table_TB_Cost[[#This Row],[Section]],DATA!A:K,4,FALSE) -> 0.972 | W31: =LEFT(VLOOKUP(Table_TB_Cost[[#This Row],[Section]],Table5[],10,FALSE),2) -> FK | X31: =IF(Table_TB_Cost[[#This Row],[Weight/m]]<0.5,1*2.5,"") | Y31: Y | Z31: =IF(Table_TB_Cost[[#This Row],[Roll?]]="Y",(2.5/Table_TB_Cost[[#This Row],[Weight/m]]/0.8)*2.5,"") -> 8.0375514 | AA31: =SUM(VLOOKUP(Table_TB_Cost[[#This Row],[MPG]],TB_MPG,2,FALSE),Table_TB_Cost[[#This Row],[MPM Surcharge]],Table_TB_Cost[[#This Row],[Rolling Factor (Cost/0.8*2.5)]])*Table_TB_Cost[[#This Row],[Weight/m]]*Table_TB_Cost[[#This Row],[Length]] -> 294.15061 | AB31: =VLOOKUP(Table_TB_Cost[[#This Row],[Section]],AF:AJ,3,FALSE) -> 87.41515 | AC31: =IF($AB$2="Margin",Table_TB_Cost[[#This Row],[TOTAL COST]]/(1-$AC$2),Table_TB_Cost[[#This Row],[List Price]]*(1-$AC$2)) -> 174.8303 | AD31: =(Table_TB_Cost[[#This Row],[Metal Sell Price]]-Table_TB_Cost[[#This Row],[TOTAL COST]])/Table_TB_Cost[[#This Row],[Metal Sell Price]] -> 0.5 | AF31: ETB0032 | AG31: 1014878 | AH31: 28.78492 | AI31: 28.78492 | AJ31: 28.78492 | AK31: 28.78492 | AL31: 28.78492 | AM31: 28.785 | AN31: 28.78496 | AO31: 28.785 | AP31: 36.69 | AQ31: 29.67 | AW31: =VLOOKUP(AF31,Table_TB_Cost[[Section]:[Basic Material]],2,FALSE) -> Ftrline - SD/SW - Sash Spacer | AX31: ETB0032 | AY31: =VLOOKUP(AX31,Table_TB_Cost[#All],5,FALSE) -> FP
A32: Powder | B32: Powderline WA | C32: PP | D32: 6.75 | E32: 10.15 | F32: 11 | K32: ='3.Edit Pricing'!$B$42 -> 99 | S32: EP14756 | T32: =VLOOKUP(Table_TB_Cost[[#This Row],[Section]],DATA!A:K,2,FALSE) -> 425TB - Flat Filler | U32: 5.8 | V32: =VLOOKUP(Table_TB_Cost[[#This Row],[Section]],DATA!A:K,4,FALSE) -> 0.379 | W32: =LEFT(VLOOKUP(Table_TB_Cost[[#This Row],[Section]],Table5[],10,FALSE),2) -> FH | X32: =IF(Table_TB_Cost[[#This Row],[Weight/m]]<0.5,1*2.5,"") -> 2.5 | Z32: =IF(Table_TB_Cost[[#This Row],[Roll?]]="Y",(2.5/Table_TB_Cost[[#This Row],[Weight/m]]/0.8)*2.5,"") | AA32: =SUM(VLOOKUP(Table_TB_Cost[[#This Row],[MPG]],TB_MPG,2,FALSE),Table_TB_Cost[[#This Row],[MPM Surcharge]],Table_TB_Cost[[#This Row],[Rolling Factor (Cost/0.8*2.5)]])*Table_TB_Cost[[#This Row],[Weight/m]]*Table_TB_Cost[[#This Row],[Length]] -> 67.067082 | AB32: =VLOOKUP(Table_TB_Cost[[#This Row],[Section]],AF:AJ,3,FALSE) -> 14.21 | AC32: =IF($AB$2="Margin",Table_TB_Cost[[#This Row],[TOTAL COST]]/(1-$AC$2),Table_TB_Cost[[#This Row],[List Price]]*(1-$AC$2)) -> 28.42 | AD32: =(Table_TB_Cost[[#This Row],[Metal Sell Price]]-Table_TB_Cost[[#This Row],[TOTAL COST]])/Table_TB_Cost[[#This Row],[Metal Sell Price]] -> 0.5 | AF32: ETB0033 | AG32: 1014880 | AH32: 30.17193 | AI32: 30.17193 | AJ32: 30.17193 | AK32: 30.17193 | AL32: 30.17193 | AM32: 30.17193 | AN32: 30.17186 | AO32: 30.17182 | AP32: 47.54 | AQ32: 38.45 | AW32: =VLOOKUP(AF32,Table_TB_Cost[[Section]:[Basic Material]],2,FALSE) -> Ftrline - LS - Sash Spacer | AX32: ETB0033 | AY32: =VLOOKUP(AX32,Table_TB_Cost[#All],5,FALSE) -> FP
A33: Powder/Anodised | B33: Other - pls check pricing | C33: AP | D33: ='3.Edit Pricing'!$B$42 -> 99 | E33: ='3.Edit Pricing'!$B$42 -> 99 | F33: ='3.Edit Pricing'!$B$42 -> 99 | G33: ='3.Edit Pricing'!$B$42 -> 99 | H33: ='3.Edit Pricing'!$B$42 -> 99 | I33: ='3.Edit Pricing'!$B$42 -> 99 | J33: ='3.Edit Pricing'!$B$42 -> 99 | K33: ='3.Edit Pricing'!$B$42 -> 99 | S33: ETB0030 | T33: =VLOOKUP(Table_TB_Cost[[#This Row],[Section]],DATA!A:K,2,FALSE) -> Ftrline - LS/SD/SW - Head/Sill/Jamb | U33: 6.5 | V33: =VLOOKUP(Table_TB_Cost[[#This Row],[Section]],DATA!A:K,4,FALSE) -> 2.74 | W33: =LEFT(VLOOKUP(Table_TB_Cost[[#This Row],[Section]],Table5[],10,FALSE),2) -> LI | X33: =IF(Table_TB_Cost[[#This Row],[Weight/m]]<0.5,1*2.5,"") | Y33: N | Z33: =IF(Table_TB_Cost[[#This Row],[Roll?]]="Y",(2.5/Table_TB_Cost[[#This Row],[Weight/m]]/0.8)*2.5,"") | AA33: =SUM(VLOOKUP(Table_TB_Cost[[#This Row],[MPG]],TB_MPG,2,FALSE),Table_TB_Cost[[#This Row],[MPM Surcharge]],Table_TB_Cost[[#This Row],[Rolling Factor (Cost/0.8*2.5)]])*Table_TB_Cost[[#This Row],[Weight/m]]*Table_TB_Cost[[#This Row],[Length]] -> 1743.2428 | AB33: =VLOOKUP(Table_TB_Cost[[#This Row],[Section]],AF:AJ,3,FALSE) -> 556.3768 | AC33: =IF($AB$2="Margin",Table_TB_Cost[[#This Row],[TOTAL COST]]/(1-$AC$2),Table_TB_Cost[[#This Row],[List Price]]*(1-$AC$2)) -> 1112.7536 | AD33: =(Table_TB_Cost[[#This Row],[Metal Sell Price]]-Table_TB_Cost[[#This Row],[TOTAL COST]])/Table_TB_Cost[[#This Row],[Metal Sell Price]] -> 0.5 | AF33: ETB0034 | AG33: 1014882 | AH33: 239.75976 | AI33: 239.75976 | AJ33: 239.75976 | AK33: 239.75976 | AL33: 239.75976 | AM33: 239.75976 | AN33: 239.75976 | AO33: 239.75976 | AP33: 213.47041 | AQ33: 172.66 | AW33: =VLOOKUP(AF33,Table_TB_Cost[[Section]:[Basic Material]],2,FALSE) -> Ftrline - LS/SD/SW - Midrail | AX33: ETB0034 | AY33: =VLOOKUP(AX33,Table_TB_Cost[#All],5,FALSE) -> FW
A34: Anodised | B34: Capral/AAF QLD anodising | C34: AP | I34: 10.65 | J34: 13.02 | K34: ='3.Edit Pricing'!$B$42 -> 99 | L34: Updated 02.02.2026 (AAF rates) | S34: ETB0031 | T34: =VLOOKUP(Table_TB_Cost[[#This Row],[Section]],DATA!A:K,2,FALSE) -> Ftrline - LS/SD/SW - Sash | U34: 6.5 | V34: =VLOOKUP(Table_TB_Cost[[#This Row],[Section]],DATA!A:K,4,FALSE) -> 2.005 | W34: =LEFT(VLOOKUP(Table_TB_Cost[[#This Row],[Section]],Table5[],10,FALSE),2) -> LI | X34: =IF(Table_TB_Cost[[#This Row],[Weight/m]]<0.5,1*2.5,"") | Y34: N | Z34: =IF(Table_TB_Cost[[#This Row],[Roll?]]="Y",(2.5/Table_TB_Cost[[#This Row],[Weight/m]]/0.8)*2.5,"") | AA34: =SUM(VLOOKUP(Table_TB_Cost[[#This Row],[MPG]],TB_MPG,2,FALSE),Table_TB_Cost[[#This Row],[MPM Surcharge]],Table_TB_Cost[[#This Row],[Rolling Factor (Cost/0.8*2.5)]])*Table_TB_Cost[[#This Row],[Weight/m]]*Table_TB_Cost[[#This Row],[Length]] -> 1275.6211 | AB34: =VLOOKUP(Table_TB_Cost[[#This Row],[Section]],AF:AJ,3,FALSE) -> 310.43558 | AC34: =IF($AB$2="Margin",Table_TB_Cost[[#This Row],[TOTAL COST]]/(1-$AC$2),Table_TB_Cost[[#This Row],[List Price]]*(1-$AC$2)) -> 620.87116 | AD34: =(Table_TB_Cost[[#This Row],[Metal Sell Price]]-Table_TB_Cost[[#This Row],[TOTAL COST]])/Table_TB_Cost[[#This Row],[Metal Sell Price]] -> 0.5 | AF34: ETB0035 | AG34: 1014884 | AH34: 21.46798 | AI34: 21.46798 | AJ34: 21.46798 | AK34: 21.46798 | AL34: 21.46798 | AM34: 21.46798 | AN34: 21.46798 | AO34: 21.46798 | AP34: 15.4 | AQ34: 12.45 | AW34: =VLOOKUP(AF34,Table_TB_Cost[[Section]:[Basic Material]],2,FALSE) -> Ftrline - LS/SD/SW - STD DG Bead | AX34: ETB0035 | AY34: =VLOOKUP(AX34,Table_TB_Cost[#All],5,FALSE) -> FP
A35: Anodised | B35: WA Anodisers | C35: AP | I35: 10.69 | J35: 12.98 | K35: ='3.Edit Pricing'!$B$42 -> 99 | L35: Updated 02.02.2026 | S35: ETB0032 | T35: =VLOOKUP(Table_TB_Cost[[#This Row],[Section]],DATA!A:K,2,FALSE) -> Ftrline - SD/SW - Sash Spacer | U35: 6.5 | V35: =VLOOKUP(Table_TB_Cost[[#This Row],[Section]],DATA!A:K,4,FALSE) -> 0.405 | W35: =LEFT(VLOOKUP(Table_TB_Cost[[#This Row],[Section]],Table5[],10,FALSE),2) -> FP | X35: =IF(Table_TB_Cost[[#This Row],[Weight/m]]<0.5,1*2.5,"") -> 2.5 | Y35: N | Z35: =IF(Table_TB_Cost[[#This Row],[Roll?]]="Y",(2.5/Table_TB_Cost[[#This Row],[Weight/m]]/0.8)*2.5,"") | AA35: =SUM(VLOOKUP(Table_TB_Cost[[#This Row],[MPG]],TB_MPG,2,FALSE),Table_TB_Cost[[#This Row],[MPM Surcharge]],Table_TB_Cost[[#This Row],[Rolling Factor (Cost/0.8*2.5)]])*Table_TB_Cost[[#This Row],[Weight/m]]*Table_TB_Cost[[#This Row],[Length]] -> 154.0539 | AB35: =VLOOKUP(Table_TB_Cost[[#This Row],[Section]],AF:AJ,3,FALSE) -> 28.78492 | AC35: =IF($AB$2="Margin",Table_TB_Cost[[#This Row],[TOTAL COST]]/(1-$AC$2),Table_TB_Cost[[#This Row],[List Price]]*(1-$AC$2)) -> 57.56984 | AD35: =(Table_TB_Cost[[#This Row],[Metal Sell Price]]-Table_TB_Cost[[#This Row],[TOTAL COST]])/Table_TB_Cost[[#This Row],[Metal Sell Price]] -> 0.5 | AF35: ETB0036 | AG35: 1014886 | AH35: 8.18232 | AI35: 8.18232 | AJ35: 8.18232 | AK35: 8.18232 | AL35: 8.18232 | AM35: 8.18232 | AN35: 8.18232 | AO35: 8.18231 | AP35: 12.86 | AQ35: 10.4 | AW35: =VLOOKUP(AF35,Table_TB_Cost[[Section]:[Basic Material]],2,FALSE) -> Ftrline - LS/SD/SW - Wide DG Bead | AX35: ETB0036 | AY35: =VLOOKUP(AX35,Table_TB_Cost[#All],5,FALSE) -> FP
A36: Breakpoint Range | D36: a | E36: b | F36: b | G36: b | H36: b | I36: c | J36: c | K36: d | S36: ETB0033 | T36: =VLOOKUP(Table_TB_Cost[[#This Row],[Section]],DATA!A:K,2,FALSE) -> Ftrline - LS - Sash Spacer | U36: 6.5 | V36: =VLOOKUP(Table_TB_Cost[[#This Row],[Section]],DATA!A:K,4,FALSE) -> 0.524 | W36: =LEFT(VLOOKUP(Table_TB_Cost[[#This Row],[Section]],Table5[],10,FALSE),2) -> FP | X36: =IF(Table_TB_Cost[[#This Row],[Weight/m]]<0.5,1*2.5,"") | Y36: N | Z36: =IF(Table_TB_Cost[[#This Row],[Roll?]]="Y",(2.5/Table_TB_Cost[[#This Row],[Weight/m]]/0.8)*2.5,"") | AA36: =SUM(VLOOKUP(Table_TB_Cost[[#This Row],[MPG]],TB_MPG,2,FALSE),Table_TB_Cost[[#This Row],[MPM Surcharge]],Table_TB_Cost[[#This Row],[Rolling Factor (Cost/0.8*2.5)]])*Table_TB_Cost[[#This Row],[Weight/m]]*Table_TB_Cost[[#This Row],[Length]] -> 190.80412 | AB36: =VLOOKUP(Table_TB_Cost[[#This Row],[Section]],AF:AJ,3,FALSE) -> 30.17193 | AC36: =IF($AB$2="Margin",Table_TB_Cost[[#This Row],[TOTAL COST]]/(1-$AC$2),Table_TB_Cost[[#This Row],[List Price]]*(1-$AC$2)) -> 60.34386 | AD36: =(Table_TB_Cost[[#This Row],[Metal Sell Price]]-Table_TB_Cost[[#This Row],[TOTAL COST]])/Table_TB_Cost[[#This Row],[Metal Sell Price]] -> 0.5 | AF36: ETB0037 | AG36: 1014888 | AH36: 72.80583 | AI36: 72.80583 | AJ36: 72.80583 | AK36: 72.80583 | AL36: 72.80583 | AM36: 72.80592 | AN36: 72.80595 | AO36: 72.806 | AP36: 119.64885 | AQ36: 96.77 | AW36: =VLOOKUP(AF36,Table_TB_Cost[[Section]:[Basic Material]],2,FALSE) -> Ftrline - LS/SD/SW - OXXO Adaptor | AX36: ETB0037 | AY36: =VLOOKUP(AX36,Table_TB_Cost[#All],5,FALSE) -> FW
A37: Powder | B37: Capral Mill - non-Bulk (AP) | C37: AP | D37: 6.22 | E37: 6.89 | F37: 7.44 | G37: 11.15 | H37: 12.64 | K37: ='3.Edit Pricing'!$B$52 -> 99 | L37: Updated 02.02.2026 | S37: ETB0034 | T37: =VLOOKUP(Table_TB_Cost[[#This Row],[Section]],DATA!A:K,2,FALSE) -> Ftrline - LS/SD/SW - Midrail | U37: 6.5 | V37: =VLOOKUP(Table_TB_Cost[[#This Row],[Section]],DATA!A:K,4,FALSE) -> 1.62 | W37: =LEFT(VLOOKUP(Table_TB_Cost[[#This Row],[Section]],Table5[],10,FALSE),2) -> FW | X37: =IF(Table_TB_Cost[[#This Row],[Weight/m]]<0.5,1*2.5,"") | Y37: N | Z37: =IF(Table_TB_Cost[[#This Row],[Roll?]]="Y",(2.5/Table_TB_Cost[[#This Row],[Weight/m]]/0.8)*2.5,"") | AA37: =SUM(VLOOKUP(Table_TB_Cost[[#This Row],[MPG]],TB_MPG,2,FALSE),Table_TB_Cost[[#This Row],[MPM Surcharge]],Table_TB_Cost[[#This Row],[Rolling Factor (Cost/0.8*2.5)]])*Table_TB_Cost[[#This Row],[Weight/m]]*Table_TB_Cost[[#This Row],[Length]] -> 848.1915 | AB37: =VLOOKUP(Table_TB_Cost[[#This Row],[Section]],AF:AJ,3,FALSE) -> 239.75976 | AC37: =IF($AB$2="Margin",Table_TB_Cost[[#This Row],[TOTAL COST]]/(1-$AC$2),Table_TB_Cost[[#This Row],[List Price]]*(1-$AC$2)) -> 479.51952 | AD37: =(Table_TB_Cost[[#This Row],[Metal Sell Price]]-Table_TB_Cost[[#This Row],[TOTAL COST]])/Table_TB_Cost[[#This Row],[Metal Sell Price]] -> 0.5 | AF37: ETB0038 | AG37: 1014890 | AH37: 85.82839 | AI37: 85.82839 | AJ37: 85.82836 | AK37: 85.82836 | AL37: 85.82834 | AM37: 85.82835 | AN37: 72.78082 | AO37: 72.78084 | AP37: 44.84 | AQ37: 36.27 | AW37: =VLOOKUP(AF37,Table_TB_Cost[[Section]:[Basic Material]],2,FALSE) -> Ftrline - LS/SD/SW - Interlock Adaptor | AX37: ETB0038 | AY37: =VLOOKUP(AX37,Table_TB_Cost[#All],5,FALSE) -> FP
A38: Powder | B38: Capral Mill (AP) | C38: AP | D38: 3.81 | E38: 4.47 | F38: 5.34 | G38: 6.02 | H38: 7.67 | K38: ='3.Edit Pricing'!$B$48 -> 99 | L38: Updated 02.02.2026 | S38: ETB0035 | T38: =VLOOKUP(Table_TB_Cost[[#This Row],[Section]],DATA!A:K,2,FALSE) -> Ftrline - LS/SD/SW - STD DG Bead | U38: 6.5 | V38: =VLOOKUP(Table_TB_Cost[[#This Row],[Section]],DATA!A:K,4,FALSE) -> 0.17 | W38: =LEFT(VLOOKUP(Table_TB_Cost[[#This Row],[Section]],Table5[],10,FALSE),2) -> FP | X38: =IF(Table_TB_Cost[[#This Row],[Weight/m]]<0.5,1*2.5,"") -> 2.5 | Y38: N | Z38: =IF(Table_TB_Cost[[#This Row],[Roll?]]="Y",(2.5/Table_TB_Cost[[#This Row],[Weight/m]]/0.8)*2.5,"") | AA38: =SUM(VLOOKUP(Table_TB_Cost[[#This Row],[MPG]],TB_MPG,2,FALSE),Table_TB_Cost[[#This Row],[MPM Surcharge]],Table_TB_Cost[[#This Row],[Rolling Factor (Cost/0.8*2.5)]])*Table_TB_Cost[[#This Row],[Weight/m]]*Table_TB_Cost[[#This Row],[Length]] -> 64.6646 | AB38: =VLOOKUP(Table_TB_Cost[[#This Row],[Section]],AF:AJ,3,FALSE) -> 21.46798 | AC38: =IF($AB$2="Margin",Table_TB_Cost[[#This Row],[TOTAL COST]]/(1-$AC$2),Table_TB_Cost[[#This Row],[List Price]]*(1-$AC$2)) -> 42.93596 | AD38: =(Table_TB_Cost[[#This Row],[Metal Sell Price]]-Table_TB_Cost[[#This Row],[TOTAL COST]])/Table_TB_Cost[[#This Row],[Metal Sell Price]] -> 0.5 | AF38: ETB0039 | AG38: 1014892 | AH38: 503.93 | AI38: 503.93 | AJ38: 503.93 | AK38: 503.93 | AL38: 503.93 | AM38: 503.93 | AN38: 503.93 | AO38: 503.93167 | AP38: 557.33077 | AQ38: 450.78 | AW38: =VLOOKUP(AF38,Table_TB_Cost[[Section]:[Basic Material]],2,FALSE) -> Ftrline - LS/SD/SW - Stacking Head/Sill/Jamb | AX38: ETB0039 | AY38: =VLOOKUP(AX38,Table_TB_Cost[#All],5,FALSE) -> FE
A39: Powder | B39: Capral P&P - HWood Non-Bulk (AP) | C39: AP | D39: 7.6 | E39: 9.36 | F39: 11 | G39: 17.63 | H39: 18.75 | K39: ='3.Edit Pricing'!$B$42 -> 99 | L39: Updated 02.02.2026 | S39: ETB0036 | T39: =VLOOKUP(Table_TB_Cost[[#This Row],[Section]],DATA!A:K,2,FALSE) -> Ftrline - LS/SD/SW - Wide DG Bead | U39: 6.5 | V39: =VLOOKUP(Table_TB_Cost[[#This Row],[Section]],DATA!A:K,4,FALSE) -> 0.142 | W39: =LEFT(VLOOKUP(Table_TB_Cost[[#This Row],[Section]],Table5[],10,FALSE),2) -> FP | X39: =IF(Table_TB_Cost[[#This Row],[Weight/m]]<0.5,1*2.5,"") -> 2.5 | Y39: N | Z39: =IF(Table_TB_Cost[[#This Row],[Roll?]]="Y",(2.5/Table_TB_Cost[[#This Row],[Weight/m]]/0.8)*2.5,"") | AA39: =SUM(VLOOKUP(Table_TB_Cost[[#This Row],[MPG]],TB_MPG,2,FALSE),Table_TB_Cost[[#This Row],[MPM Surcharge]],Table_TB_Cost[[#This Row],[Rolling Factor (Cost/0.8*2.5)]])*Table_TB_Cost[[#This Row],[Weight/m]]*Table_TB_Cost[[#This Row],[Length]] -> 54.01396 | AB39: =VLOOKUP(Table_TB_Cost[[#This Row],[Section]],AF:AJ,3,FALSE) -> 8.18232 | AC39: =IF($AB$2="Margin",Table_TB_Cost[[#This Row],[TOTAL COST]]/(1-$AC$2),Table_TB_Cost[[#This Row],[List Price]]*(1-$AC$2)) -> 16.36464 | AD39: =(Table_TB_Cost[[#This Row],[Metal Sell Price]]-Table_TB_Cost[[#This Row],[TOTAL COST]])/Table_TB_Cost[[#This Row],[Metal Sell Price]] -> 0.5 | AF39: ETB0041 | AG39: 1014894 | AH39: 17.15247 | AI39: 17.15247 | AJ39: 17.15247 | AK39: 17.15247 | AL39: 17.15247 | AM39: 17.15247 | AN39: 17.15247 | AO39: 17.15244 | AP39: 32.7 | AQ39: 26.45 | AW39: =VLOOKUP(AF39,Table_TB_Cost[[Section]:[Basic Material]],2,FALSE) -> Ftrline - LS/SD/SW - Flyscreen Adaptor | AX39: ETB0041 | AY39: =VLOOKUP(AX39,Table_TB_Cost[#All],5,FALSE) -> FP
A40: Powder | B40: Capral P&P - HWood Bulk (AP) | C40: AP | D40: 5.44 | E40: 6.72 | F40: 7.91 | G40: 12.71 | H40: 13.83 | K40: ='3.Edit Pricing'!$B$42 -> 99 | L40: Updated 02.02.2026 | S40: ETB0037 | T40: =VLOOKUP(Table_TB_Cost[[#This Row],[Section]],DATA!A:K,2,FALSE) -> Ftrline - LS/SD/SW - OXXO Adaptor | U40: 6.5 | V40: =VLOOKUP(Table_TB_Cost[[#This Row],[Section]],DATA!A:K,4,FALSE) -> 0.908 | W40: =LEFT(VLOOKUP(Table_TB_Cost[[#This Row],[Section]],Table5[],10,FALSE),2) -> FW | X40: =IF(Table_TB_Cost[[#This Row],[Weight/m]]<0.5,1*2.5,"") | Y40: N | Z40: =IF(Table_TB_Cost[[#This Row],[Roll?]]="Y",(2.5/Table_TB_Cost[[#This Row],[Weight/m]]/0.8)*2.5,"") | AA40: =SUM(VLOOKUP(Table_TB_Cost[[#This Row],[MPG]],TB_MPG,2,FALSE),Table_TB_Cost[[#This Row],[MPM Surcharge]],Table_TB_Cost[[#This Row],[Rolling Factor (Cost/0.8*2.5)]])*Table_TB_Cost[[#This Row],[Weight/m]]*Table_TB_Cost[[#This Row],[Length]] -> 475.4061 | AB40: =VLOOKUP(Table_TB_Cost[[#This Row],[Section]],AF:AJ,3,FALSE) -> 72.80583 | AC40: =IF($AB$2="Margin",Table_TB_Cost[[#This Row],[TOTAL COST]]/(1-$AC$2),Table_TB_Cost[[#This Row],[List Price]]*(1-$AC$2)) -> 145.61166 | AD40: =(Table_TB_Cost[[#This Row],[Metal Sell Price]]-Table_TB_Cost[[#This Row],[TOTAL COST]])/Table_TB_Cost[[#This Row],[Metal Sell Price]] -> 0.5 | AF40: ETB0042 | AG40: 1019244 | AH40: 25.44532 | AI40: 25.44532 | AJ40: 25.44532 | AK40: 25.44532 | AL40: 25.44532 | AM40: 25.44532 | AN40: 25.44538 | AO40: 25.4454 | AP40: 34.02 | AQ40: 27.52 | AW40: =VLOOKUP(AF40,Table_TB_Cost[[Section]:[Basic Material]],2,FALSE) -> Ftrline - SD/SW Drive Gear Trim | AX40: ETB0042 | AY40: =VLOOKUP(AX40,Table_TB_Cost[#All],5,FALSE) -> FP
S41: ETB0038 | T41: =VLOOKUP(Table_TB_Cost[[#This Row],[Section]],DATA!A:K,2,FALSE) -> Ftrline - LS/SD/SW - Interlock Adaptor | U41: 6.5 | V41: =VLOOKUP(Table_TB_Cost[[#This Row],[Section]],DATA!A:K,4,FALSE) -> 0.495 | W41: =LEFT(VLOOKUP(Table_TB_Cost[[#This Row],[Section]],Table5[],10,FALSE),2) -> FP | X41: =IF(Table_TB_Cost[[#This Row],[Weight/m]]<0.5,1*2.5,"") -> 2.5 | Y41: N | Z41: =IF(Table_TB_Cost[[#This Row],[Roll?]]="Y",(2.5/Table_TB_Cost[[#This Row],[Weight/m]]/0.8)*2.5,"") | AA41: =SUM(VLOOKUP(Table_TB_Cost[[#This Row],[MPG]],TB_MPG,2,FALSE),Table_TB_Cost[[#This Row],[MPM Surcharge]],Table_TB_Cost[[#This Row],[Rolling Factor (Cost/0.8*2.5)]])*Table_TB_Cost[[#This Row],[Weight/m]]*Table_TB_Cost[[#This Row],[Length]] -> 188.2881 | AB41: =VLOOKUP(Table_TB_Cost[[#This Row],[Section]],AF:AJ,3,FALSE) -> 85.82839 | AC41: =IF($AB$2="Margin",Table_TB_Cost[[#This Row],[TOTAL COST]]/(1-$AC$2),Table_TB_Cost[[#This Row],[List Price]]*(1-$AC$2)) -> 171.65678 | AD41: =(Table_TB_Cost[[#This Row],[Metal Sell Price]]-Table_TB_Cost[[#This Row],[TOTAL COST]])/Table_TB_Cost[[#This Row],[Metal Sell Price]] -> 0.5 | AF41: ETB0043 | AG41: 1023149 | AH41: 8.35879 | AI41: 8.35879 | AJ41: 8.35879 | AK41: 8.35879 | AL41: 8.35879 | AM41: 8.35879 | AN41: 8.35879 | AO41: 8.35872 | AP41: 16.99 | AQ41: 14.72 | AW41: =VLOOKUP(AF41,Table_TB_Cost[[Section]:[Basic Material]],2,FALSE) -> Ftrline - Transom/Mullion Coupler | AX41: ETB0043 | AY41: =VLOOKUP(AX41,Table_TB_Cost[#All],5,FALSE) -> FH
A42: SELECTED FINISH DETAILS | S42: ETB0039 | T42: =VLOOKUP(Table_TB_Cost[[#This Row],[Section]],DATA!A:K,2,FALSE) -> Ftrline - LS/SD/SW - Stacking Head/Sill/Jamb | U42: 6.5 | V42: =VLOOKUP(Table_TB_Cost[[#This Row],[Section]],DATA!A:K,4,FALSE) -> 3.188 | W42: =LEFT(VLOOKUP(Table_TB_Cost[[#This Row],[Section]],Table5[],10,FALSE),2) -> FE | X42: =IF(Table_TB_Cost[[#This Row],[Weight/m]]<0.5,1*2.5,"") | Y42: N | Z42: =IF(Table_TB_Cost[[#This Row],[Roll?]]="Y",(2.5/Table_TB_Cost[[#This Row],[Weight/m]]/0.8)*2.5,"") | AA42: =SUM(VLOOKUP(Table_TB_Cost[[#This Row],[MPG]],TB_MPG,2,FALSE),Table_TB_Cost[[#This Row],[MPM Surcharge]],Table_TB_Cost[[#This Row],[Rolling Factor (Cost/0.8*2.5)]])*Table_TB_Cost[[#This Row],[Weight/m]]*Table_TB_Cost[[#This Row],[Length]] -> 2457.2148 | AB42: =VLOOKUP(Table_TB_Cost[[#This Row],[Section]],AF:AJ,3,FALSE) -> 503.93 | AC42: =IF($AB$2="Margin",Table_TB_Cost[[#This Row],[TOTAL COST]]/(1-$AC$2),Table_TB_Cost[[#This Row],[List Price]]*(1-$AC$2)) -> 1007.86 | AD42: =(Table_TB_Cost[[#This Row],[Metal Sell Price]]-Table_TB_Cost[[#This Row],[TOTAL COST]])/Table_TB_Cost[[#This Row],[Metal Sell Price]] -> 0.5 | AF42: ETB0200 | AG42: 734876 | AH42: 137.28393 | AI42: 131.92106 | AJ42: 130.59829 | AK42: 121.61316 | AL42: 119.47783 | AM42: 117.54167 | AN42: 126.85619 | AO42: 128.34 | AP42: 127.31 | AQ42: 115.59 | AR42: 126.09 | AS42: 127.32 | AT42: 131.55 | AW42: =VLOOKUP(AF42,Table_TB_Cost[[Section]:[Basic Material]],2,FALSE) -> 629TB - 150MM Sub Head 150X50 | AX42: ETB0200 | AY42: =VLOOKUP(AX42,Table_TB_Cost[#All],5,FALSE) -> FJ
A43: Type | B43: Applicator | C43: AP/PP | D43: Group | E43: Cost | F43: Sell | G43: Typical | H43: Min | I43: Max | J43: Project m2 | K43: Breakpoint Category | L43: Typical_column | M43: Min_column | N43: Max_column | S43: ETB0040 | T43: ** NOT USED ** | X43: =IF(Table_TB_Cost[[#This Row],[Weight/m]]<0.5,1*2.5,"") -> 2.5 | AA43: =SUM(VLOOKUP(Table_TB_Cost[[#This Row],[MPG]],TB_MPG,2,FALSE),Table_TB_Cost[[#This Row],[MPM Surcharge]],Table_TB_Cost[[#This Row],[Rolling Factor (Cost/0.8*2.5)]])*Table_TB_Cost[[#This Row],[Weight/m]]*Table_TB_Cost[[#This Row],[Length]] -> #N/A | AB43: =VLOOKUP(Table_TB_Cost[[#This Row],[Section]],AF:AJ,3,FALSE) -> #N/A | AC43: =IF($AB$2="Margin",Table_TB_Cost[[#This Row],[TOTAL COST]]/(1-$AC$2),Table_TB_Cost[[#This Row],[List Price]]*(1-$AC$2)) -> #N/A | AD43: =(Table_TB_Cost[[#This Row],[Metal Sell Price]]-Table_TB_Cost[[#This Row],[TOTAL COST]])/Table_TB_Cost[[#This Row],[Metal Sell Price]] -> #N/A | AF43: ETB0201 | AG43: 734877 | AH43: 143.66152 | AI43: 142.58548 | AJ43: 140.40162 | AK43: 131.1494 | AL43: 132.8592 | AM43: 129.29991 | AN43: 136.53658 | AO43: 136.53658 | AP43: 137.74 | AQ43: 126.01 | AR43: 122.19 | AS43: 123.39 | AT43: 127.48 | AW43: =VLOOKUP(AF43,Table_TB_Cost[[Section]:[Basic Material]],2,FALSE) -> 629TB - 150MM Sub Sill Flat Leg | AX43: ETB0201 | AY43: =VLOOKUP(AX43,Table_TB_Cost[#All],5,FALSE) -> FL
A44: ='1.Project Details'!$B$24 -> Mill Finish | B44: ='1.Project Details'!$B$26 -> 0 | C44: =VLOOKUP(B44,$B$28:$C$40,2,FALSE) -> #N/A | D44: ='1.Project Details'!$B$28 -> 0 | E44: =VLOOKUP(B44,$B$27:$K$40,MATCH(D44,$B$27:$K$27,0),FALSE) -> #N/A | F44: ='3.Edit Pricing'!$B$44 -> 99 | G44: =$E$44/(1-VLOOKUP($J$44,$A$54:$N$60,L44)) -> #N/A | H44: =$E$44/(1-VLOOKUP($J$44,$A$54:$N$60,M44)) -> #N/A | I44: =$E$44/(1-VLOOKUP($J$44,$A$54:$N$60,N44)) -> #N/A | J44: ='3.Edit Pricing'!$B$28 -> 2.4115 | K44: =HLOOKUP($D$44,$D$27:$K$40,10,FALSE) -> #N/A | L44: =IF($K$44="a",3,IF($K$44="b",6,IF($K$44="c",9,IF($K$44="d",12,0)))) -> #N/A | M44: =L44+1 -> #N/A | N44: =L44+2 -> #N/A | S44: ETB0041 | T44: =VLOOKUP(Table_TB_Cost[[#This Row],[Section]],DATA!A:K,2,FALSE) -> Ftrline - LS/SD/SW - Flyscreen Adaptor | U44: 6.5 | V44: =VLOOKUP(Table_TB_Cost[[#This Row],[Section]],DATA!A:K,4,FALSE) -> 0.361 | W44: =LEFT(VLOOKUP(Table_TB_Cost[[#This Row],[Section]],Table5[],10,FALSE),2) -> FP | X44: =IF(Table_TB_Cost[[#This Row],[Weight/m]]<0.5,1*2.5,"") -> 2.5 | Y44: N | Z44: =IF(Table_TB_Cost[[#This Row],[Roll?]]="Y",(2.5/Table_TB_Cost[[#This Row],[Weight/m]]/0.8)*2.5,"") | AA44: =SUM(VLOOKUP(Table_TB_Cost[[#This Row],[MPG]],TB_MPG,2,FALSE),Table_TB_Cost[[#This Row],[MPM Surcharge]],Table_TB_Cost[[#This Row],[Rolling Factor (Cost/0.8*2.5)]])*Table_TB_Cost[[#This Row],[Weight/m]]*Table_TB_Cost[[#This Row],[Length]] -> 137.31718 | AB44: =VLOOKUP(Table_TB_Cost[[#This Row],[Section]],AF:AJ,3,FALSE) -> 17.15247 | AC44: =IF($AB$2="Margin",Table_TB_Cost[[#This Row],[TOTAL COST]]/(1-$AC$2),Table_TB_Cost[[#This Row],[List Price]]*(1-$AC$2)) -> 34.30494 | AD44: =(Table_TB_Cost[[#This Row],[Metal Sell Price]]-Table_TB_Cost[[#This Row],[TOTAL COST]])/Table_TB_Cost[[#This Row],[Metal Sell Price]] -> 0.5 | AF44: ETB0202 | AG44: 734878 | AH44: 126.68232 | AI44: 122.39605 | AJ44: 118.3598 | AK44: 118.35984 | AL44: 111.89758 | AM44: 111.89778 | AN44: 127.92179 | AO44: 119.05932 | AP44: 119.32 | AQ44: 108.66 | AR44: 118.92 | AS44: 120.08 | AT44: 124.07 | AW44: =VLOOKUP(AF44,Table_TB_Cost[[Section]:[Basic Material]],2,FALSE) -> 629TB - 150MM Sub Frame 2-PC Base | AX44: ETB0202 | AY44: =VLOOKUP(AX44,Table_TB_Cost[#All],5,FALSE) -> FJ
G45: =VLOOKUP($J$44,$A$54:$N$60,L44) -> #REF! | H45: =VLOOKUP($J$44,$A$54:$N$60,M44) -> #REF! | I45: =VLOOKUP($J$44,$A$54:$N$60,N44) -> #REF! | S45: ETB0042 | T45: =VLOOKUP(Table_TB_Cost[[#This Row],[Section]],DATA!A:K,2,FALSE) -> Ftrline - SD/SW Drive Gear Trim | U45: 6.5 | V45: =VLOOKUP(Table_TB_Cost[[#This Row],[Section]],DATA!A:K,4,FALSE) -> 0.365 | W45: =LEFT(VLOOKUP(Table_TB_Cost[[#This Row],[Section]],Table5[],10,FALSE),2) -> FP | X45: =IF(Table_TB_Cost[[#This Row],[Weight/m]]<0.5,1*2.5,"") -> 2.5 | Y45: N | Z45: =IF(Table_TB_Cost[[#This Row],[Roll?]]="Y",(2.5/Table_TB_Cost[[#This Row],[Weight/m]]/0.8)*2.5,"") | AA45: =SUM(VLOOKUP(Table_TB_Cost[[#This Row],[MPG]],TB_MPG,2,FALSE),Table_TB_Cost[[#This Row],[MPM Surcharge]],Table_TB_Cost[[#This Row],[Rolling Factor (Cost/0.8*2.5)]])*Table_TB_Cost[[#This Row],[Weight/m]]*Table_TB_Cost[[#This Row],[Length]] -> 138.8387 | AB45: =VLOOKUP(Table_TB_Cost[[#This Row],[Section]],AF:AJ,3,FALSE) -> 25.44532 | AC45: =IF($AB$2="Margin",Table_TB_Cost[[#This Row],[TOTAL COST]]/(1-$AC$2),Table_TB_Cost[[#This Row],[List Price]]*(1-$AC$2)) -> 50.89064 | AD45: =(Table_TB_Cost[[#This Row],[Metal Sell Price]]-Table_TB_Cost[[#This Row],[TOTAL COST]])/Table_TB_Cost[[#This Row],[Metal Sell Price]] -> 0.5 | AF45: ETB0203 | AG45: 734879 | AH45: 222.23593 | AI45: 212.93651 | AJ45: 214.37261 | AK45: 196.84763 | AL45: 196.44497 | AM45: 189.87765 | AN45: 215.67638 | AO45: 192.25395 | AP45: 203.49 | AQ45: 182.11 | AR45: 202.9 | AS45: 204.88 | AT45: 211.68 | AW45: =VLOOKUP(AF45,Table_TB_Cost[[Section]:[Basic Material]],2,FALSE) -> 629TB - 150MM Frame/Mullion | AX45: ETB0203 | AY45: =VLOOKUP(AX45,Table_TB_Cost[#All],5,FALSE) -> FI
A46: ='1.Project Details'!$B$24 -> Mill Finish | B46: Capral Mill (AP) | C46: AP | D46: ='1.Project Details'!$B$28 -> 0 | E46: =VLOOKUP(B46,$B$27:$K$40,MATCH(D46,$B$27:$K$27,0),FALSE) -> #N/A | F46: ='3.Edit Pricing'!$B$50 -> 99 | G46: =$E$46/(1-VLOOKUP($J$46,$A$54:$N$60,L46)) -> #N/A | H46: =$E$46/(1-VLOOKUP($J$46,$A$54:$N$60,M46)) -> #N/A | I46: =$E$46/(1-VLOOKUP($J$46,$A$54:$N$60,N46)) -> #N/A | J46: ='3.Edit Pricing'!$B$28 -> 2.4115 | K46: =HLOOKUP($D$46,$D$27:$K$38,10,FALSE) -> #N/A | L46: =IF($K$46="a",3,IF($K$46="b",6,IF($K$46="c",9,IF($K$46="d",12,0)))) -> #N/A | M46: =L46+1 -> #N/A | N46: =L46+2 -> #N/A | S46: ETB0043 | T46: =VLOOKUP(Table_TB_Cost[[#This Row],[Section]],DATA!A:K,2,FALSE) -> Ftrline - Transom/Mullion Coupler | U46: 6.5 | V46: =VLOOKUP(Table_TB_Cost[[#This Row],[Section]],DATA!A:K,4,FALSE) -> 0.364 | W46: =LEFT(VLOOKUP(Table_TB_Cost[[#This Row],[Section]],Table5[],10,FALSE),2) -> FH | X46: =IF(Table_TB_Cost[[#This Row],[Weight/m]]<0.5,1*2.5,"") -> 2.5 | Y46: N | Z46: =IF(Table_TB_Cost[[#This Row],[Roll?]]="Y",(2.5/Table_TB_Cost[[#This Row],[Weight/m]]/0.8)*2.5,"") | AA46: =SUM(VLOOKUP(Table_TB_Cost[[#This Row],[MPG]],TB_MPG,2,FALSE),Table_TB_Cost[[#This Row],[MPM Surcharge]],Table_TB_Cost[[#This Row],[Rolling Factor (Cost/0.8*2.5)]])*Table_TB_Cost[[#This Row],[Weight/m]]*Table_TB_Cost[[#This Row],[Length]] -> 72.18666 | AB46: =VLOOKUP(Table_TB_Cost[[#This Row],[Section]],AF:AJ,3,FALSE) -> 8.35879 | AC46: =IF($AB$2="Margin",Table_TB_Cost[[#This Row],[TOTAL COST]]/(1-$AC$2),Table_TB_Cost[[#This Row],[List Price]]*(1-$AC$2)) -> 16.71758 | AD46: =(Table_TB_Cost[[#This Row],[Metal Sell Price]]-Table_TB_Cost[[#This Row],[TOTAL COST]])/Table_TB_Cost[[#This Row],[Metal Sell Price]] -> 0.5 | AF46: ETB0204 | AG46: 734880 | AH46: 196.69452 | AI46: 192.80854 | AJ46: 186.55456 | AK46: 179.75274 | AL46: 176.20965 | AM46: 173.02952 | AN46: 222.97333 | AO46: 152.32162 | AP46: 184.87 | AQ46: 165.97 | AR46: 178.66 | AS46: 180.41 | AT46: 186.4 | AW46: =VLOOKUP(AF46,Table_TB_Cost[[Section]:[Basic Material]],2,FALSE) -> 629TB - 150MM External Sill/Transom | AX46: ETB0204 | AY46: =VLOOKUP(AX46,Table_TB_Cost[#All],5,FALSE) -> FJ
A47: ='1.Project Details'!$B$24 -> Mill Finish | B47: Capral Mill - non-Bulk (AP) | C47: AP | D47: ='1.Project Details'!$B$28 -> 0 | E47: =VLOOKUP(B47,$B$27:$K$40,MATCH(D47,$B$27:$K$27,0),FALSE) -> #N/A | F47: ='3.Edit Pricing'!$B$54 -> 99 | G47: =$E$47/(1-VLOOKUP($J$47,$A$54:$N$60,L47)) -> #N/A | H47: =$E$47/(1-VLOOKUP($J$47,$A$54:$N$60,M47)) -> #N/A | I47: =$E$47/(1-VLOOKUP($J$47,$A$54:$N$60,N47)) -> #N/A | J47: ='3.Edit Pricing'!$B$28 -> 2.4115 | K47: =HLOOKUP($D$47,$D$27:$K$40,10,FALSE) -> #N/A | L47: =IF($K$47="a",3,IF($K$47="b",6,IF($K$47="c",9,IF($K$47="d",12,0)))) -> #N/A | M47: =L47+1 -> #N/A | N47: =L47+2 -> #N/A | S47: ETB0200 | T47: =VLOOKUP(Table_TB_Cost[[#This Row],[Section]],DATA!A:K,2,FALSE) -> 629TB - 150MM Sub Head 150X50 | U47: 6.5 | V47: =VLOOKUP(Table_TB_Cost[[#This Row],[Section]],DATA!A:K,4,FALSE) -> 1.88 | W47: =LEFT(VLOOKUP(Table_TB_Cost[[#This Row],[Section]],Table5[],10,FALSE),2) -> FJ | X47: =IF(Table_TB_Cost[[#This Row],[Weight/m]]<0.5,1*2.5,"") | Y47: Y | Z47: =IF(Table_TB_Cost[[#This Row],[Roll?]]="Y",(2.5/Table_TB_Cost[[#This Row],[Weight/m]]/0.8)*2.5,"") -> 4.1555851 | AA47: =SUM(VLOOKUP(Table_TB_Cost[[#This Row],[MPG]],TB_MPG,2,FALSE),Table_TB_Cost[[#This Row],[MPM Surcharge]],Table_TB_Cost[[#This Row],[Rolling Factor (Cost/0.8*2.5)]])*Table_TB_Cost[[#This Row],[Weight/m]]*Table_TB_Cost[[#This Row],[Length]] -> 478.60345 | AB47: =VLOOKUP(Table_TB_Cost[[#This Row],[Section]],AF:AJ,3,FALSE) -> 137.28393 | AC47: =IF($AB$2="Margin",Table_TB_Cost[[#This Row],[TOTAL COST]]/(1-$AC$2),Table_TB_Cost[[#This Row],[List Price]]*(1-$AC$2)) -> 274.56786 | AD47: =(Table_TB_Cost[[#This Row],[Metal Sell Price]]-Table_TB_Cost[[#This Row],[TOTAL COST]])/Table_TB_Cost[[#This Row],[Metal Sell Price]] -> 0.5 | AF47: ETB0205 | AG47: 1067552 | AH47: 30.08933 | AI47: 30.87705 | AJ47: 28.061 | AK47: 24.77568 | AL47: 24.77567 | AM47: 24.77573 | AN47: 23.62571 | AO47: 23.93974 | AP47: 26.51 | AQ47: 22.97 | AR47: 29.41 | AS47: 29.7 | AT47: 30.69 | AW47: =VLOOKUP(AF47,Table_TB_Cost[[Section]:[Basic Material]],2,FALSE) -> 419TB - 150mm Sill Bead External | AX47: ETB0205 | AY47: =VLOOKUP(AX47,Table_TB_Cost[#All],5,FALSE) -> FH
F48: ='3.Edit Pricing'!$B$50 -> 99 | G48: =VLOOKUP($J$44,$A$54:$N$60,L47) -> #REF! | H48: =VLOOKUP($J$44,$A$54:$N$60,M47) -> #REF! | I48: =VLOOKUP($J$44,$A$54:$N$60,N47) -> #REF! | S48: ETB0201 | T48: =VLOOKUP(Table_TB_Cost[[#This Row],[Section]],DATA!A:K,2,FALSE) -> 629TB - 150MM Sub Sill Flat Leg | U48: 6.5 | V48: =VLOOKUP(Table_TB_Cost[[#This Row],[Section]],DATA!A:K,4,FALSE) -> 1.789 | W48: =LEFT(VLOOKUP(Table_TB_Cost[[#This Row],[Section]],Table5[],10,FALSE),2) -> FL | X48: =IF(Table_TB_Cost[[#This Row],[Weight/m]]<0.5,1*2.5,"") | Y48: Y | Z48: =IF(Table_TB_Cost[[#This Row],[Roll?]]="Y",(2.5/Table_TB_Cost[[#This Row],[Weight/m]]/0.8)*2.5,"") -> 4.3669648 | AA48: =SUM(VLOOKUP(Table_TB_Cost[[#This Row],[MPG]],TB_MPG,2,FALSE),Table_TB_Cost[[#This Row],[MPM Surcharge]],Table_TB_Cost[[#This Row],[Rolling Factor (Cost/0.8*2.5)]])*Table_TB_Cost[[#This Row],[Weight/m]]*Table_TB_Cost[[#This Row],[Length]] -> 539.41082 | AB48: =VLOOKUP(Table_TB_Cost[[#This Row],[Section]],AF:AJ,3,FALSE) -> 143.66152 | AC48: =IF($AB$2="Margin",Table_TB_Cost[[#This Row],[TOTAL COST]]/(1-$AC$2),Table_TB_Cost[[#This Row],[List Price]]*(1-$AC$2)) -> 287.32304 | AD48: =(Table_TB_Cost[[#This Row],[Metal Sell Price]]-Table_TB_Cost[[#This Row],[TOTAL COST]])/Table_TB_Cost[[#This Row],[Metal Sell Price]] -> 0.5 | AF48: ETB0206 | AG48: 734881 | AH48: 206.65795 | AI48: 194.29615 | AJ48: 193.51383 | AK48: 195.74905 | AL48: 178.97474 | AM48: 178.97517 | AN48: 186.31846 | AO48: 197.70286 | AP48: 187.15 | AQ48: 167.96 | AR48: 181 | AS48: 182.78 | AT48: 188.84 | AW48: =VLOOKUP(AF48,Table_TB_Cost[[Section]:[Basic Material]],2,FALSE) -> 629TB - 150MM Internal Sill/Transom | AX48: ETB0206 | AY48: =VLOOKUP(AX48,Table_TB_Cost[#All],5,FALSE) -> FJ
